Workbook
Name ListaFluxo: PARAMETROS!$M$6:$M$51
Name ListaGerentes: PARAMETROS!$D$6:$D$56
Name ListaIndicadores: PARAMETROS!$S$6:$S$51
Name ListaMandato: PARAMETROS!$P$6:$P$49
Name ListaMotivos: PARAMETROS!$V$6:$V$51
Name ListaOperacoes: PARAMETROS!$G$6:$G$57
Name ListaParceiros: PARAMETROS!$A$6:$A$111
Name ListaStatus: PARAMETROS!$J$6:$J$52

Sheet João Pullig
A6: CLIENTE | B6: OPERAÇÃO | C6: VALOR | D6: FEE | E6: RECEITA | F6: MANDATO | G6: QTD | H6: INSTITUIÇÃO | I6: PARCEIRO INDICADOR | J6: ATUALIZAÇÃO | K6: FLUXO | L6: STATUS | M6: DATA FECHAMENTO | N6: MOTIVO DE RECUSA | O6: OBSERVAÇÃO
A7: CGPM CONSTRUTORA GOIANIA | B7: ⁠Antecipação de Recebíveis | C7: 3000000 | D7: 0.02 | E7: =D7*C7 -> 60000 | F7: Assinado | G7: 1 | H7: 7 ALDABRAN | I7: PJC Consultoria | J7: 46288 | K7: Em andamento | L7: Análise de Crédito | O7: Contratos públicos
A8: CGPM CONSTRUTORA GOIANIA | B8: ⁠Antecipação de Recebíveis | C8: 4000000 | D8: 0.02 | E8: =D8*C8 -> 80000 | F8: Assinado | G8: 1 | H8: DIAMOND | I8: PJC Consultoria | J8: 46288 | K8: Em andamento | L8: Análise de Crédito | O8: Contratos públicos
A9: PEDRO BRIDI | B9: ⁠Credito Rural | C9: 8000000 | D9: 0.01 | E9: =D9*C9 -> 80000 | F9: Não enviado | G9: 1 | H9: 7 ALDABRAN | I9: ⁠VM Consultoria | J9: 46288 | K9: Em andamento | L9: Análise de Crédito
A10: GRUPO GR ALIMENTOS | B10: Capital de Giro | C10: 40000000 | D10: 0.01 | E10: =D10*C10 -> 400000 | F10: Não enviado | G10: 1 | H10: SAPIENS CAPITAL | I10: ⁠MB Finance | J10: 46288 | K10: Em andamento | L10: Cadastro
A11: GRUPO GR ALIMENTOS | B11: ⁠Antecipação de Recebíveis | C11: 2000000 | D11: 0.01 | E11: =D11*C11 -> 20000 | F11: Não enviado | G11: 1 | H11: SAPIENS CAPITAL | I11: ⁠MB Finance | J11: 46288 | K11: Em andamento | L11: Cadastro
A12: GRUPO GR ALIMENTOS | B12: Capital de Giro | C12: 40000000 | D12: 0.01 | E12: =D12*C12 -> 400000 | F12: Não enviado | G12: 1 | H12: INVISTA FIDC | I12: ⁠MB Finance | J12: 46288 | K12: Em andamento | L12: Cadastro
A13: ROV ENGENHARIA E CONSTRUCAO LTDA | B13: ⁠Antecipação de Recebíveis | C13: 1000000 | D13: 0.04 | E13: =D13*C13 -> 40000 | F13: Não enviado | G13: 1 | H13: SAPIENS CAPITAL | I13: ⁠Blue Score | J13: 46288 | K13: Em andamento | L13: Aprovado
A14: ROV ENGENHARIA E CONSTRUCAO LTDA | B14: ⁠Antecipação de Recebíveis | C14: 1000000 | D14: 0.04 | E14: =D14*C14 -> 40000 | F14: Não enviado | G14: 1 | H14: OXIGENIO CAPITAL | I14: ⁠Blue Score | J14: 46288 | K14: Em andamento | L14: Análise de Crédito
A15: ROV ENGENHARIA E CONSTRUCAO LTDA | B15: ⁠Antecipação de Recebíveis | C15: 1000000 | D15: 0.04 | E15: =D15*C15 -> 40000 | F15: Não enviado | G15: 1 | H15: 7 ALDABRAN | I15: ⁠Blue Score | J15: 46288 | K15: Em andamento | L15: Análise de Crédito
A16: TISSOT MOVEIS LTDA | B16: Capital de Giro | C16: 3000000 | D16: 0.02 | E16: =D16*C16 -> 60000 | F16: Não enviado | G16: 1 | H16: NÃO ATRIBUÍDO | I16: PJC Consultoria | J16: 46288 | K16: Não enviado | L16: Cadastro
A17: SG FACAS ARTESANAIS | B17: ⁠Antecipação de Recebíveis | C17: 500000 | D17: 0.03 | E17: =D17*C17 -> 15000 | F17: Não enviado | G17: 1 | H17: NÃO ATRIBUÍDO | I17: PJC Consultoria | J17: 46288 | K17: Não enviado | L17: Cadastro
A18: LOBE CONTABILIDADE | B18: Pronampe | C18: 500000 | D18: 0.03 | E18: =D18*C18 -> 15000 | F18: Assinado | G18: 1 | H18: 7 ALDABRAN | I18: PJC Consultoria | J18: 46288 | K18: Em andamento | L18: Análise de Crédito
A19: RENOVADORA ALVORADA COMERCIO | B19: ⁠Antecipação de Recebíveis | C19: 300000 | D19: 0.03 | E19: =D19*C19 -> 9000 | F19: Não enviado | G19: 1 | H19: AFFIX FIDC | I19: PJC Consultoria | J19: 46288 | K19: Em andamento | L19: Análise de Crédito
A20: RENOVADORA ALVORADA COMERCIO | B20: ⁠Antecipação de Recebíveis | C20: 300000 | D20: 0.03 | E20: =D20*C20 -> 9000 | F20: Não enviado | G20: 1 | H20: DIAMOND | I20: PJC Consultoria | J20: 46288 | K20: Em andamento | L20: Análise de Crédito
... A37: ROTEC METAIS | B37: ⁠Antecipação de Recebíveis | C37: 500000 | D37: 0.02 | E37: =D37*C37 -> 10000 | F37: Não enviado | G37: 1 | H37: NÃO ATRIBUÍDO | I37: PJC Consultoria | J37: 46288 | K37: Não enviado | L37: Cadastro
E38: =D38*C38 -> 0
E39: =D39*C39 -> 0
E40: =D40*C40 -> 0
E41: =D41*C41 -> 0
E42: =D42*C42 -> 0
E43: =D43*C43 -> 0
E44: =D44*C44 -> 0
E45: =D45*C45 -> 0
E46: =D46*C46 -> 0
E47: =D47*C47 -> 0
E48: =D48*C48 -> 0
E49: =D49*C49 -> 0
... E277: =D277*C277 -> 0
E278: =IF(OR(C278="",D278=""),"",C278*D278)
E279: =IF(OR(C279="",D279=""),"",C279*D279)
E280: =IF(OR(C280="",D280=""),"",C280*D280)
E281: =IF(OR(C281="",D281=""),"",C281*D281)
E282: =IF(OR(C282="",D282=""),"",C282*D282)
E283: =IF(OR(C283="",D283=""),"",C283*D283)
E284: =IF(OR(C284="",D284=""),"",C284*D284)
E285: =IF(OR(C285="",D285=""),"",C285*D285)
E286: =IF(OR(C286="",D286=""),"",C286*D286)
E287: =IF(OR(C287="",D287=""),"",C287*D287)
E288: =IF(OR(C288="",D288=""),"",C288*D288)
E289: =IF(OR(C289="",D289=""),"",C289*D289)
... E385: =IF(OR(C385="",D385=""),"",C385*D385)

Sheet Kaio Dias
A6: CLIENTE | B6: OPERAÇÃO | C6: VALOR | D6: FEE | E6: RECEITA | F6: MANDATO | G6: QTD | H6: INSTITUIÇÃO | I6: PARCEIRO INDICADOR | J6: ATUALIZAÇÃO | K6: FLUXO | L6: STATUS | M6: DATA FECHAMENTO | N6: MOTIVO DE RECUSA | O6: OBSERVAÇÃO
A7: SIMEMP SERVICOS TECNICOS E OBRAS LTDA | B7: Capital de Giro | C7: 700000 | D7: 0.015 | E7: =D7*C7 -> 10500 | F7: Enviado | G7: 1 | H7: SAPIENS CAPITAL | I7: PJC Consultoria | J7: 46287 | K7: Enviado | L7: Análise de Crédito | O7: Enviados contratos, aguardando retorno da analise
A8: SIMEMP SERVICOS TECNICOS E OBRAS LTDA | B8: Capital de Giro | C8: 5000000 | D8: 0.015 | E8: =D8*C8 -> 75000 | F8: Enviado | G8: 1 | H8: 7 ALDABRAN | I8: PJC Consultoria | J8: 46287 | K8: Enviado | L8: Análise de Crédito | O8: Enviados contratos recebidos, aguardando retorno
A9: SIMEMP SERVICOS TECNICOS E OBRAS LTDA | B9: ⁠Antecipação de Recebíveis | C9: 5000000 | D9: 0.015 | E9: =D9*C9 -> 75000 | F9: Enviado | G9: 1 | H9: DIAMOND | I9: PJC Consultoria | J9: 46287 | K9: Enviado | L9: Cadastro | O9: Cadastro enviado 22/09/2026
A10: MMA BRAZIL COMERCIO DE ALIMENTOS LTDA | B10: ⁠Antecipação de Recebíveis | C10: 300000 | D10: 0.03 | E10: =D10*C10 -> 9000 | F10: Assinado | G10: 1 | H10: SAPIENS CAPITAL | I10: PJC Consultoria | J10: 46287 | K10: Enviado | L10: Comitê | O10: Em comite de credito
A11: MMA BRAZIL COMERCIO DE ALIMENTOS LTDA | B11: Capital de Giro | C11: 300000 | D11: 0.03 | E11: =D11*C11 -> 9000 | F11: Assinado | G11: 1 | H11: 7 ALDABRAN | I11: PJC Consultoria | J11: 46287 | K11: Enviado | L11: Cadastro | O11: Aguardando documentação atualizada
A12: N DIDINI ENGENHARIA E CONSTRUCAO LTDA | B12: Capital de Giro | C12: 1500000 | D12: 0.03 | E12: =D12*C12 -> 45000 | F12: Assinado | G12: 1 | H12: 7 ALDABRAN | I12: PJC Consultoria | J12: 46287 | K12: Enviado | L12: Análise de Crédito | O12: Esta sendo feito trabalho para melhora do risco, aguardando retorno da cintia
A13: N DIDINI ENGENHARIA E CONSTRUCAO LTDA | B13: Capital de Giro | C13: 1500000 | D13: 0.03 | E13: =D13*C13 -> 45000 | F13: Assinado | G13: 1 | H13: DIAMOND | I13: PJC Consultoria | J13: 46288 | K13: Enviado | L13: Cadastro | O13: Subir documentação
A14: HIPERAGRO COMERCIO DE GRÃO LTDA | B14: ⁠Antecipação de Recebíveis | C14: 777242 | D14: 0.025 | E14: =D14*C14 -> 19431.05 | F14: Assinado | G14: 1 | H14: AFFIX FIDC | I14: PJC Consultoria | J14: 46287 | K14: Enviado | L14: Aprovado | O14: Op 1 - 1906,59 / Op 2 - 1794,50 / Op 3 - 2263 / Op 4 - 2.985,08 / Op 5 - 5000 Total a recebido R$ 13.949,17 / A receber R$ 5481,88
A15: INTEGRAL ALIMENTOS LTDA | B15: ⁠Antecipação de Recebíveis | C15: 1000000 | D15: 0.05 | E15: =D15*C15 -> 50000 | F15: Assinado | G15: 1 | H15: 7 ALDABRAN | I15: PJC Consultoria | J15: 46287 | K15: Enviado | L15: Comitê | O15: Feito reunião
A16: AGRICOLA RIZZI LTDA | B16: Capital de Giro | C16: 20000000 | D16: 0.01 | E16: =D16*C16 -> 200000 | F16: Assinado | G16: 1 | H16: 7 ALDABRAN | I16: PJC Consultoria | J16: 46288 | K16: Enviado | L16: Cadastro | O16: aguardando posição da documentação enviada
A17: AGRICOLA RIZZI LTDA | B17: ⁠Consórcio | C17: 4500000 | D17: 0.01 | E17: =D17*C17 -> 45000 | F17: Assinado | G17: 1 | H17: COSTA AZUL INVESTIMENTOS | I17: PJC Consultoria | J17: 46287 | K17: Enviado | L17: Análise de Crédito | O17: Agendar reunião com fundo
A18: JARDEL | B18: ⁠Consórcio | C18: 9000000 | D18: 0.01 | E18: =D18*C18 -> 90000 | F18: Enviado | G18: 1 | H18: 7 ALDABRAN | I18: ⁠VM Consultoria | J18: 46287 | K18: Enviado | L18: Cadastro | O18: Em analise com o guilherme sobre viabilidade da operação
... A39: PEDRO BRIDI | B39: Capital de Giro | C39: 7000000 | D39: 0.03 | E39: =D39*C39 -> 210000 | F39: Enviado | G39: 1 | H39: 7 ALDABRAN | I39: ⁠VM Consultoria | J39: 46288 | K39: Enviado | L39: Cadastro | O39: Encaminhado para verificar possibilidades
E40: =D40*C40 -> 0
E41: =D41*C41 -> 0
E42: =D42*C42 -> 0
E43: =D43*C43 -> 0
E44: =D44*C44 -> 0
E45: =D45*C45 -> 0
E46: =D46*C46 -> 0
E47: =D47*C47 -> 0
E48: =D48*C48 -> 0
E49: =D49*C49 -> 0
E50: =D50*C50 -> 0
E51: =D51*C51 -> 0
... E276: =D276*C276 -> 0
E277: =IF(OR(C277="",D277=""),"",C277*D277)
E278: =IF(OR(C278="",D278=""),"",C278*D278)
E279: =IF(OR(C279="",D279=""),"",C279*D279)
E280: =IF(OR(C280="",D280=""),"",C280*D280)
E281: =IF(OR(C281="",D281=""),"",C281*D281)
E282: =IF(OR(C282="",D282=""),"",C282*D282)
E283: =IF(OR(C283="",D283=""),"",C283*D283)
E284: =IF(OR(C284="",D284=""),"",C284*D284)
E285: =IF(OR(C285="",D285=""),"",C285*D285)
E286: =IF(OR(C286="",D286=""),"",C286*D286)
E287: =IF(OR(C287="",D287=""),"",C287*D287)
E288: =IF(OR(C288="",D288=""),"",C288*D288)
... E374: =IF(OR(C374="",D374=""),"",C374*D374)

Sheet Pablo Ruan
A6: CLIENTE | B6: OPERAÇÃO | C6: VALOR | D6: FEE | E6: RECEITA | F6: MANDATO | G6: QTD | H6: INSTITUIÇÃO | I6: PARCEIRO INDICADOR | J6: ATUALIZAÇÃO | K6: FLUXO | L6: STATUS | M6: DATA FECHAMENTO | N6: MOTIVO DE RECUSA | O6: OBSERVAÇÃO
A7: RENOVAR | B7: ⁠Antecipação de Recebíveis | C7: 800000 | D7: 0.02 | E7: =D7*C7 -> 16000 | F7: Enviado | G7: 1 | H7: AFFIX FIDC | I7: PJC Consultoria | J7: 46288 | K7: Enviado | L7: Aprovado | O7: ESTA SEM OPERAÇAO
A8: GRUPO MOMENTO | B8: ⁠Antecipação de Recebíveis | C8: 1000000 | D8: 0.015 | E8: =D8*C8 -> 15000 | F8: Não assinado | G8: 1 | H8: RNX FIDIC | I8: PJC Consultoria | J8: 46288 | K8: Enviado | L8: Aprovado | O8: ESTA SEM OPERAÇAO
A9: GRUPO MOMENTO | B9: ⁠Antecipação de Recebíveis | C9: 1500000 | D9: 0.015 | E9: =D9*C9 -> 22500 | F9: Não assinado | G9: 1 | H9: SOMA ASSET | I9: PJC Consultoria | J9: 46288 | K9: Enviado | L9: Aprovado | O9: TRAVOU OPERAÇAO
A10: CB AGRO | B10: ⁠Antecipação de Recebíveis | C10: 500000 | D10: 0.02 | E10: =D10*C10 -> 10000 | F10: Não enviado | G10: 1 | H10: PRIX EMPRESARIAL | I10: PJC Consultoria | J10: 46288 | K10: Enviado | L10: Aprovado | O10: ESTA OPERANDO POUCO
A11: JOAO MARTINS | B11: ⁠Antecipação de Recebíveis | C11: 400000 | D11: 0.02 | E11: =D11*C11 -> 8000 | F11: Não enviado | G11: 1 | H11: AFFIX FIDC | I11: PJC Consultoria | J11: 46288 | K11: Enviado | L11: Análise de Crédito | O11: AGUARD DOC PENDENTE
A12: MS MONTAGENS | B12: ⁠Consultoria | C12: 6000 | E12: =D12*C12 -> 0 | F12: Enviado | G12: 1 | H12: PJC CONSULTORIA | I12: PJC Consultoria | J12: 46288 | K12: Enviado | L12: Cadastro | O12: ESTAMOS EM TRATATIVAS
A13: REI DO PAPELAO | B13: ⁠Antecipação de Recebíveis | C13: 300000 | D13: 0.01 | E13: =D13*C13 -> 3000 | F13: Enviado | G13: 1 | H13: ALX NEGOCIOS | I13: PJC Consultoria | J13: 46288 | K13: Pré-análise | L13: Cadastro | O13: AGUARD DOC PEN/ ABERTURA LIMITE/ ATRASO AFFIX
A14: AGROPECURIA ESTANCIA | B14: ⁠Antecipação de Recebíveis | C14: 300000 | D14: 0.02 | E14: =D14*C14 -> 6000 | F14: Não enviado | G14: 1 | H14: PJC CONSULTORIA | I14: PJC Consultoria | J14: 46257 | K14: Aguardando retorno | L14: Cadastro | O14: DIFICIL COMUNICAÇAO
A15: ROTEC | B15: ⁠Antecipação de Recebíveis | C15: 500000 | D15: 0.02 | E15: =D15*C15 -> 10000 | F15: Não enviado | G15: 1 | H15: PJC CONSULTORIA | I15: PJC Consultoria | J15: 46288 | K15: Aguardando retorno | L15: Cadastro | O15: MARCANDO REUNIAO CALL
A16: TOTAL TEXTIL | B16: ⁠Antecipação de Recebíveis | C16: 300000 | D16: 0.02 | E16: =D16*C16 -> 6000 | F16: Não assinado | G16: 1 | H16: NÃO ATRIBUÍDO | I16: PJC Consultoria | J16: 46288 | K16: Aguardando retorno | L16: Cadastro | O16: AGUARDANDO DOCUMENTAÇAO
A17: INNOVA BRAZIL | B17: ⁠Antecipação de Recebíveis | C17: 3000000 | D17: 0.02 | E17: =D17*C17 -> 60000 | F17: Não assinado | G17: 1 | H17: SOMA ASSET | I17: PJC Consultoria | J17: 46288 | K17: Aguardando retorno | L17: Análise de Crédito | O17: CERTIDAO SIMPLIFICADA
A18: NATIVA AGRICOLA | B18: Cobrança | C18: 6000000 | D18: 0.1 | E18: =D18*C18 -> 600000 | F18: Enviado | G18: 1 | H18: PJC CONSULTORIA | I18: PJC Consultoria | J18: 46288 | K18: Em andamento | L18: Assinatura de Contrato | O18: NAO MANDA A CARTEIRA PARA COBRANÇAS
A19: BELA AGRO | B19: Capital de Giro | C19: 781000 | D19: 0.02 | E19: =D19*C19 -> 15620 | F19: Enviado | G19: 1 | H19: 7 ALDABRAN | I19: PJC Consultoria | J19: 46288 | K19: Enviado | L19: Análise de Crédito | O19: COMPRA DE DIVIDA
A20: PRAT -K | B20: ⁠Antecipação de Recebíveis | C20: 1000000 | D20: 0.02 | E20: =D20*C20 -> 20000 | F20: Não enviado | G20: 1 | H20: NÃO ATRIBUÍDO | I20: PJC Consultoria | J20: 46288 | K20: Não enviado | L20: Cadastro | O20: CALL APOS DIA 23/09
A21: BENINI INDUSTRIA | B21: ⁠Antecipação de Recebíveis | C21: 500000 | D21: 0.02 | E21: =D21*C21 -> 10000 | F21: Não enviado | G21: 1 | H21: NÃO ATRIBUÍDO | I21: PJC Consultoria | J21: 46288 | K21: Não enviado | L21: Cadastro | O21: DIFICIL COMUNICAÇAO
A22: INNOVA BRAZIL | B22: ⁠Antecipação de Recebíveis | C22: 2000000 | D22: 0.02 | E22: =D22*C22 -> 40000 | F22: Não assinado | G22: 1 | H22: INVISTA FIDC | I22: PJC Consultoria | J22: 46288 | K22: Pré-análise | L22: Análise de Crédito
A23: INNOVA BRAZIL | B23: ⁠Antecipação de Recebíveis | C23: 2000000 | D23: 0.02 | E23: =D23*C23 -> 40000 | F23: Não enviado | G23: 1 | H23: JPI FIDC | I23: PJC Consultoria | J23: 46288 | K23: Pré-análise | L23: Análise de Crédito
A24: THP INDUSTRIA | B24: ⁠Antecipação de Recebíveis | C24: 1000000 | D24: 0.02 | E24: =D24*C24 -> 20000 | F24: Enviado | G24: 1 | H24: SAPIENS CAPITAL | I24: PJC Consultoria | J24: 46288 | K24: Pré-análise | L24: Análise de Crédito | O24: REUNIAO MARCADA SEGUNDA FEIRA
A25: THP INDUSTRIA | B25: ⁠Antecipação de Recebíveis | C25: 1000000 | D25: 0.02 | E25: =D25*C25 -> 20000 | F25: Enviado | G25: 1 | H25: INVISTA FIDC | I25: PJC Consultoria | J25: 46288 | K25: Pré-análise | L25: Cadastro
A26: COTRITECH | B26: ⁠Antecipação de Recebíveis | C26: 1000000 | D26: 0.02 | E26: =D26*C26 -> 20000 | F26: Enviado | G26: 1 | H26: SAPIENS CAPITAL | I26: PJC Consultoria | J26: 46288 | K26: Não enviado | L26: Comitê
A27: COTRITECH | B27: ⁠Antecipação de Recebíveis | C27: 1000000 | D27: 0.02 | E27: =D27*C27 -> 20000 | F27: Enviado | G27: 1 | H27: ALX NEGOCIOS | I27: PJC Consultoria | J27: 46288 | K27: Não enviado | L27: Cadastro | O27: ORGANIZANDO DATA PARA REUNIAO
A28: LIPON QUIMICA | B28: ⁠Antecipação de Recebíveis | C28: 1000000 | D28: 0.02 | E28: =D28*C28 -> 20000 | F28: Não enviado | G28: 1 | H28: ALX NEGOCIOS | I28: PJC Consultoria | J28: 46288 | K28: Não enviado | L28: Cadastro
A29: LIPON QUIMICA | B29: ⁠Antecipação de Recebíveis | C29: 1000000 | D29: 0.02 | E29: =D29*C29 -> 20000 | F29: Não enviado | G29: 1 | H29: SAPIENS CAPITAL | I29: PJC Consultoria | J29: 46288 | K29: Não enviado | L29: Cadastro
A30: FRIGORIFICO CHESINI | B30: ⁠Antecipação de Recebíveis | C30: 3000000 | D30: 0.02 | E30: =D30*C30 -> 60000 | F30: Não enviado | G30: 1 | H30: SOMA ASSET | I30: PJC Consultoria | J30: 46288 | K30: Não enviado | L30: Cadastro | O30: REUNIAO PROXIMO MES
A31: ACRILYS TECNOLOGIA | B31: ⁠Antecipação de Recebíveis | C31: 1000000 | D31: 0.02 | E31: =D31*C31 -> 20000 | F31: Não enviado | G31: 1 | H31: NÃO ATRIBUÍDO | I31: PJC Consultoria | J31: 46288 | K31: Não enviado | L31: Cadastro | O31: DIFICIL COMUNICAÇAO
A32: AIRSIDE | B32: ⁠Antecipação de Recebíveis | C32: 500000 | D32: 0.02 | E32: =D32*C32 -> 10000 | F32: Não enviado | G32: 1 | H32: NÃO ATRIBUÍDO | I32: PJC Consultoria | J32: 46288 | K32: Não enviado | L32: Cadastro | O32: MARCANDO REUNIAO
A33: BAP IMPORTS | B33: ⁠Antecipação de Recebíveis | C33: 1000000 | D33: 0.02 | E33: =D33*C33 -> 20000 | F33: Não enviado | G33: 1 | H33: NÃO ATRIBUÍDO | I33: PJC Consultoria | J33: 46288 | K33: Não enviado | L33: Cadastro | O33: REUNIAOSEXTA PRESENCIAL 09:00 HRS
A34: RENOVAR | B34: Capital de Giro | C34: 350000 | D34: 0.02 | E34: =D34*C34 -> 7000 | F34: Enviado | G34: 1 | H34: CASHME | I34: PJC Consultoria | J34: 46288 | K34: Enviado | L34: Cadastro | O34: AGUARD DOC PENDENTE
A35: FRIGOGYN | B35: Capital de Giro | C35: 500000 | D35: 0.02 | E35: =D35*C35 -> 10000 | F35: Enviado | G35: 1 | H35: TRUST CAPITAL | I35: PJC Consultoria | J35: 46288 | K35: Não enviado | L35: Cadastro | O35: AGUARDANDO PLATAFORMA
A36: FRIGOGYN | B36: Capital de Giro | C36: 500000 | D36: 0.02 | E36: =D36*C36 -> 10000 | F36: Enviado | G36: 1 | H36: 7 ALDABRAN | I36: PJC Consultoria | J36: 46288 | K36: Não enviado | L36: Cadastro
A37: LABARCA | B37: ⁠Antecipação de Recebíveis | C37: 1000000 | D37: 0.02 | E37: =D37*C37 -> 20000 | F37: Não enviado | G37: 1 | H37: NÃO ATRIBUÍDO | I37: PJC Consultoria | J37: 46288 | K37: Não enviado | L37: Cadastro | O37: PRIMEIRO CONTATO
A38: INNOVA BRAZIL | B38: ⁠Antecipação de Recebíveis | C38: 1000000 | D38: 0.02 | E38: =D38*C38 -> 20000 | F38: Não enviado | G38: 1 | H38: DIAMOND | I38: PJC Consultoria | J38: 46288 | K38: Enviado | L38: Cadastro
A39: THP INDUSTRIA | B39: ⁠Antecipação de Recebíveis | C39: 1000000 | D39: 0.025 | E39: =D39*C39 -> 25000 | F39: Enviado | G39: 1 | H39: DIAMOND | I39: PJC Consultoria | J39: 46287 | K39: Enviado | L39: Cadastro
A40: RAPIDO IGREJINHA | B40: ⁠Antecipação de Recebíveis | C40: 500000 | D40: 0.02 | E40: =D40*C40 -> 10000 | F40: Não enviado | G40: 1 | H40: NÃO ATRIBUÍDO | I40: PJC Consultoria | J40: 46288 | K40: Não enviado | L40: Cadastro
A41: PARABONI FERRAMENTAS | B41: ⁠Antecipação de Recebíveis | C41: 1000000 | D41: 0.02 | E41: =D41*C41 -> 20000 | F41: Não enviado | G41: 1 | H41: NÃO ATRIBUÍDO | I41: PJC Consultoria | J41: 46288 | K41: Não enviado | L41: Cadastro
E42: =D42*C42 -> 0
E43: =D43*C43 -> 0
E44: =D44*C44 -> 0
E45: =D45*C45 -> 0
E46: =D46*C46 -> 0
E47: =D47*C47 -> 0
E48: =D48*C48 -> 0
E49: =D49*C49 -> 0
E50: =D50*C50 -> 0
E51: =D51*C51 -> 0
E52: =D52*C52 -> 0
E53: =D53*C53 -> 0
... E274: =D274*C274 -> 0
D275: =C275*B275 -> 0 | E275: =IF(OR(C275="",D275=""),"",C275*D275)
D276: =C276*B276 -> 0 | E276: =IF(OR(C276="",D276=""),"",C276*D276)
D277: =C277*B277 -> 0 | E277: =IF(OR(C277="",D277=""),"",C277*D277)
D278: =C278*B278 -> 0 | E278: =IF(OR(C278="",D278=""),"",C278*D278)
D279: =C279*B279 -> 0 | E279: =IF(OR(C279="",D279=""),"",C279*D279)
D280: =C280*B280 -> 0 | E280: =IF(OR(C280="",D280=""),"",C280*D280)
D281: =C281*B281 -> 0 | E281: =IF(OR(C281="",D281=""),"",C281*D281)
D282: =C282*B282 -> 0 | E282: =IF(OR(C282="",D282=""),"",C282*D282)
D283: =C283*B283 -> 0 | E283: =IF(OR(C283="",D283=""),"",C283*D283)
D284: =C284*B284 -> 0 | E284: =IF(OR(C284="",D284=""),"",C284*D284)
D285: =C285*B285 -> 0 | E285: =IF(OR(C285="",D285=""),"",C285*D285)
D286: =C286*B286 -> 0 | E286: =IF(OR(C286="",D286=""),"",C286*D286)
... D290: =C290*B290 -> 0 | E290: =IF(OR(C290="",D290=""),"",C290*D290)
E291: =IF(OR(C291="",D291=""),"",C291*D291)
E292: =IF(OR(C292="",D292=""),"",C292*D292)
E293: =IF(OR(C293="",D293=""),"",C293*D293)
E294: =IF(OR(C294="",D294=""),"",C294*D294)
E295: =IF(OR(C295="",D295=""),"",C295*D295)
E296: =IF(OR(C296="",D296=""),"",C296*D296)
E297: =IF(OR(C297="",D297=""),"",C297*D297)
E298: =IF(OR(C298="",D298=""),"",C298*D298)
E299: =IF(OR(C299="",D299=""),"",C299*D299)
E300: =IF(OR(C300="",D300=""),"",C300*D300)
E301: =IF(OR(C301="",D301=""),"",C301*D301)
E302: =IF(OR(C302="",D302=""),"",C302*D302)
... E382: =IF(OR(C382="",D382=""),"",C382*D382)

Sheet André Pullig
A6: CLIENTE | B6: OPERAÇÃO | C6: VALOR | D6: FEE | E6: RECEITA | F6: MANDATO | G6: QTD | H6: INSTITUIÇÃO | I6: PARCEIRO INDICADOR | J6: ATUALIZAÇÃO | K6: FLUXO | L6: STATUS | M6: DATA FECHAMENTO | N6: MOTIVO DE RECUSA | O6: OBSERVAÇÃO
A7: LUKMAM - 38.249.690/0001-90 | B7: ⁠Antecipação de Recebíveis | C7: 300000 | D7: 0.03 | E7: =D7*C7 -> 9000 | F7: Assinado | G7: 1 | H7: NÃO ATRIBUÍDO | I7: ⁠Blue Score | J7: 46288 | K7: Em andamento | L7: Reprovado | M7: 46288 | N7: Outro (detalhar na observação) | O7: Não possui documentação
A8: NUTRIMAX - 53.039.803/0001-16 | B8: ⁠Antecipação de Recebíveis | C8: 500000 | D8: 0.03 | E8: =D8*C8 -> 15000 | F8: Assinado | G8: 1 | H8: NÃO ATRIBUÍDO | I8: ⁠Blue Score | J8: 46288 | K8: Em andamento | L8: Reprovado | M8: 46288 | O8: FALTANDO DOCUMENTO - RAFAEL
A9: GUILHERME - 37.752.853/0001-90 | B9: ⁠Antecipação de Recebíveis | C9: 300000 | D9: 0.03 | E9: =D9*C9 -> 9000 | F9: Enviado | G9: 1 | H9: NÃO ATRIBUÍDO | I9: Astrum Finance | J9: 46288 | K9: Em andamento | L9: Cadastro | O9: FALTANDO DOCUMENTO - POLIANA ASTRUM
A10: BARRIERE - 51.544.166/0001-00 | B10: ⁠Antecipação de Recebíveis | C10: 300000 | D10: 0.03 | E10: =D10*C10 -> 9000 | F10: Assinado | G10: 1 | H10: 7 ALDABRAN | I10: ⁠Blue Score | J10: 46288 | K10: Em andamento | L10: Análise de Crédito | O10: AGUARDANDO ALFREDO
A11: RIBEIRO - 24.467.220/0001-98 | B11: ⁠Antecipação de Recebíveis | C11: 300000 | D11: 0.03 | E11: =D11*C11 -> 9000 | F11: Assinado | G11: 1 | H11: 7 ALDABRAN | I11: ⁠Blue Score | J11: 46288 | K11: Em andamento | L11: Análise de Crédito | O11: AGUARDANDO REUNIAO
A12: PLUMEY - 01.326.832/0001-65 | B12: ⁠Antecipação de Recebíveis | C12: 500000 | D12: 0.03 | E12: =D12*C12 -> 15000 | F12: Enviado | G12: 1 | H12: NÃO ATRIBUÍDO | I12: Astrum Finance | J12: 46288 | K12: Em andamento | L12: Cadastro | O12: FALTANDO DOCUMENTO - POLIANA ASTRUM
A13: ALBIERE TRANSPORTES - ALFA | B13: ⁠Antecipação de Recebíveis | C13: 600000 | D13: 0.0075 | E13: =D13*C13 -> 4500 | F13: Enviado | G13: 1 | H13: RNX FIDIC | I13: ⁠Blue Score | J13: 46288 | K13: Enviado | L13: Finalizado | M13: 46274 | O13: AGUARDANDO PROPOSTA
A14: ALBIERE TRANSPORTES - ALFA | B14: ⁠Antecipação de Recebíveis | C14: 5000000 | D14: 0.01 | E14: =D14*C14 -> 50000 | F14: Enviado | G14: 1 | H14: SOMA ASSET | I14: ⁠Blue Score | J14: 46288 | K14: Em andamento | L14: Cadastro | O14: AGUARDANDO PROPOSTA
A15: DALBIERE TRANSPORTES - ALFA | B15: ⁠Antecipação de Recebíveis | C15: 5000000 | D15: 0.01 | E15: =D15*C15 -> 50000 | F15: Enviado | G15: 1 | H15: SOMA ASSET | I15: ⁠Blue Score | J15: 46288 | K15: Em andamento | L15: Cadastro | O15: AGUARDANDO PROPOSTA
A16: PARQUE ENGENHARIA | B16: ⁠Antecipação de Recebíveis | C16: 150000 | D16: 0 | E16: =D16*C16 -> 0 | F16: Assinado | G16: 1 | H16: GOIAS BANK | I16: PJC Consultoria | J16: 46288 | K16: Em andamento | L16: Finalizado | M16: 46274 | O16: JÁ ESTA OPERANDO
A17: PARQUE ENGENHARIA | B17: ⁠FGI | C17: 500000 | D17: 0.05 | E17: =D17*C17 -> 25000 | F17: Assinado | G17: 1 | H17: 7 ALDABRAN | I17: PJC Consultoria | J17: 46288 | K17: Em andamento | L17: Análise de Crédito
A18: PARQUE ENGENHARIA | B18: ⁠Antecipação de Recebíveis | C18: 300000 | D18: 0 | E18: =D18*C18 -> 0 | F18: Assinado | G18: 1 | H18: ALX NEGOCIOS | I18: PJC Consultoria | J18: 46288 | K18: Em andamento | L18: Cadastro | O18: AGUARDANDO LIMPAR O NOME
A19: LAP COSMETICOS | B19: ⁠Antecipação de Recebíveis | C19: 4000000 | D19: 0.03 | E19: =D19*C19 -> 120000 | F19: Não enviado | G19: 1 | H19: SOMA ASSET | I19: PJC Consultoria | J19: 46288 | K19: Não enviado | L19: Cadastro | O19: AGUARDANDO DOCUMENTOS
A20: LAP COSMETICOS | B20: ⁠Antecipação de Recebíveis | C20: 1500000 | D20: 0.03 | E20: =D20*C20 -> 45000 | F20: Não enviado | G20: 1 | H20: RNX FIDIC | I20: PJC Consultoria | J20: 46288 | K20: Não enviado | L20: Cadastro
A21: LAP COSMETICOS | B21: ⁠Antecipação de Recebíveis | C21: 1500000 | D21: 0.03 | E21: =D21*C21 -> 45000 | F21: Não enviado | G21: 1 | H21: AFFIX FIDC | I21: PJC Consultoria | J21: 46288 | K21: Não enviado | L21: Cadastro
A22: SAFRA BRASIL 34.984.590/0001-56 | B22: ⁠Antecipação de Recebíveis | C22: 1000000 | D22: 0.05 | E22: =D22*C22 -> 50000 | F22: Assinado | G22: 1 | H22: 7 ALDABRAN | I22: ⁠Blue Score | J22: 46288 | K22: Em andamento | L22: Cadastro | O22: AGUARDANDO DOCUMENTOS
A23: SAFRA BRASIL 34.984.590/0002-37 | B23: ⁠Antecipação de Recebíveis | C23: 1000000 | D23: 0.05 | E23: =D23*C23 -> 50000 | F23: Assinado | G23: 1 | H23: 7 ALDABRAN | I23: ⁠Blue Score | J23: 46288 | K23: Em andamento | L23: Cadastro | O23: AGUARDANDO DOCUMENTOS
A24: SAFRA BRASIL 05.052.142/0001-16 | B24: ⁠Antecipação de Recebíveis | C24: 1000000 | D24: 0.05 | E24: =D24*C24 -> 50000 | F24: Assinado | G24: 1 | H24: 7 ALDABRAN | I24: ⁠Blue Score | J24: 46288 | K24: Em andamento | L24: Cadastro | O24: AGUARDANDO DOCUMENTOS
A25: CMX COMERCIO 52.961.756/0001-09 | B25: Capital de Giro | C25: 3000000 | D25: 0.05 | E25: =D25*C25 -> 150000 | F25: Não enviado | G25: 1 | H25: 7 ALDABRAN | I25: ⁠Blue Score | J25: 46288 | K25: Enviado | L25: Cadastro | O25: AGUARDANDO DOCUMENTOS
A26: MS COMPRA E VENDA 53.241.901/0001-31 | B26: Pronampe | C26: 500000 | D26: 0.15 | E26: =D26*C26 -> 75000 | F26: Assinado | G26: 1 | H26: 7 ALDABRAN | I26: Sandro | J26: 46288 | K26: Em andamento | L26: Cadastro | O26: AGUARDANDO DOCUMENTOS
A27: MS COMPRA E VENDA 53.241.901/0001-31 | B27: ⁠FGI | C27: 300000 | D27: 0.1 | E27: =D27*C27 -> 30000 | F27: Assinado | G27: 1 | H27: PS FINANCE | I27: Sandro | J27: 46288 | K27: Em andamento | L27: Cadastro
A28: AGRONORTE - 30.480.055/0001-07 | B28: Pronampe | C28: 500000 | D28: 0.15 | E28: =D28*C28 -> 75000 | F28: Assinado | G28: 1 | H28: 7 ALDABRAN | I28: Sandro | J28: 46288 | K28: Em andamento | L28: Cadastro | O28: AGUARDANDO DOCUMENTOS
A29: AGRONORTE - 30.480.055/0001-07 | B29: ⁠FGI | C29: 500000 | D29: 0.1 | E29: =D29*C29 -> 50000 | F29: Assinado | G29: 1 | H29: PS FINANCE | I29: Sandro | J29: 46288 | K29: Em andamento | L29: Cadastro
A30: PRIME SERVIÇOS - 40.905.651/0001-45 | B30: Pronampe | C30: 500000 | D30: 0.15 | E30: =D30*C30 -> 75000 | F30: Assinado | G30: 1 | H30: 7 ALDABRAN | I30: Sandro | J30: 46288 | K30: Em andamento | L30: Cadastro | O30: AGUARDANDO DOCUMENTOS
A31: BIOCRIM - 58.352.399/0001-50 | B31: ⁠FGI | C31: 1500000 | D31: 0.05 | E31: =D31*C31 -> 75000 | F31: Não enviado | G31: 1 | H31: 7 ALDABRAN | I31: Astrum Finance | J31: 46288 | K31: Em andamento | L31: Cadastro | O31: AGUARDANDO DOCUMENTOS
A32: PACIFICO COMERCIAL DE ALIMENTOS E PRODUTOS DE LIMPEZA LTDA | B32: Pronampe | C32: 500000 | D32: 0.15 | E32: =D32*C32 -> 75000 | F32: Assinado | G32: 1 | H32: 7 ALDABRAN | I32: Sandro | J32: 46288 | K32: Em andamento | L32: Cadastro | O32: AGUARDANDO DOCUMENTOS
A33: C2C COMÉRCIO DE ALIMENTOS LTDA | B33: Pronampe | C33: 500000 | D33: 0.15 | E33: =D33*C33 -> 75000 | F33: Assinado | G33: 1 | H33: 7 ALDABRAN | I33: Sandro | J33: 46288 | K33: Em andamento | L33: Cadastro | O33: AGUARDANDO DOCUMENTOS
A34: CABRAL CICLA COMERCIO VAREJISTA DE MATERIAIS DE CONSTRUÇÃO LTDA | B34: Pronampe | C34: 500000 | D34: 0.15 | E34: =D34*C34 -> 75000 | F34: Assinado | G34: 1 | H34: 7 ALDABRAN | I34: Sandro | J34: 46288 | K34: Em andamento | L34: Cadastro | O34: AGUARDANDO DOCUMENTOS
A35: TIO PNEUS COMERCIO VAREJISTA - 50.152.219/0001-84 | B35: ⁠Antecipação de Recebíveis | C35: 200000 | D35: 0.03 | E35: =D35*C35 -> 6000 | F35: Assinado | G35: 1 | H35: 7 ALDABRAN | I35: Walber | J35: 46288 | K35: Em andamento | L35: Cadastro | O35: AGUARDANDO DOCUMENTOS
A36: TIO PNEUS COMERCIO VAREJISTA - 50.152.219/0001-84 | B36: ⁠Antecipação de Recebíveis | C36: 200000 | D36: 0.03 | E36: =D36*C36 -> 6000 | F36: Assinado | G36: 1 | H36: AFFIX FIDC | I36: Walber | J36: 46288 | K36: Em andamento | L36: Finalizado | M36: 46288 | O36: AGUARDANDO DOCUMENTOS
A37: TIO PNEUS COMERCIO VAREJISTA - 50.152.219/0001-84 | B37: ⁠Antecipação de Recebíveis | C37: 200000 | D37: 0.03 | E37: =D37*C37 -> 6000 | F37: Assinado | G37: 1 | H37: RNX FIDIC | I37: Walber | J37: 46288 | K37: Em andamento | L37: Reprovado | O37: AGUARDANDO DOCUMENTOS
A38: TIO PNEUS COMERCIO VAREJISTA - 50.152.219/0001-84 | B38: ⁠Antecipação de Recebíveis | C38: 200000 | D38: 0.03 | E38: =D38*C38 -> 6000 | F38: Assinado | G38: 1 | H38: SAPIENS CAPITAL | I38: Walber | J38: 46288 | K38: Em andamento | L38: Cadastro
A39: SERGIO GONCALVES DE OLIVEIRA | B39: Capital de Giro | C39: 10000000 | D39: 0.025 | E39: =D39*C39 -> 250000 | F39: Assinado | G39: 1 | H39: 7 ALDABRAN | I39: ⁠PS Finance | J39: 46286 | K39: Em andamento | L39: Cadastro
A40: LINDOMAR DA COSTA LIMA | B40: ⁠Home Equity | C40: 4000000 | D40: 0.05 | E40: =D40*C40 -> 200000 | F40: Não assinado | G40: 1 | H40: 7 ALDABRAN | I40: ⁠Blue Score | J40: 46286 | K40: Pré-análise | L40: Cadastro | M40: Aguardando documentos
E41: =D41*C41 -> 0
E42: =D42*C42 -> 0
E43: =D43*C43 -> 0
E44: =D44*C44 -> 0
E45: =D45*C45 -> 0
E46: =D46*C46 -> 0
E47: =D47*C47 -> 0
E48: =D48*C48 -> 0
E49: =D49*C49 -> 0
E50: =D50*C50 -> 0
E51: =D51*C51 -> 0
E52: =D52*C52 -> 0
... E288: =D288*C288 -> 0
D289: =C289*B289 -> 0 | E289: =IF(OR(C289="",D289=""),"",C289*D289)
D290: =C290*B290 -> 0 | E290: =IF(OR(C290="",D290=""),"",C290*D290)
D291: =C291*B291 -> 0 | E291: =IF(OR(C291="",D291=""),"",C291*D291)
D292: =C292*B292 -> 0 | E292: =IF(OR(C292="",D292=""),"",C292*D292)
D293: =C293*B293 -> 0 | E293: =IF(OR(C293="",D293=""),"",C293*D293)
D294: =C294*B294 -> 0 | E294: =IF(OR(C294="",D294=""),"",C294*D294)
D295: =C295*B295 -> 0 | E295: =IF(OR(C295="",D295=""),"",C295*D295)
D296: =C296*B296 -> 0 | E296: =IF(OR(C296="",D296=""),"",C296*D296)
D297: =C297*B297 -> 0 | E297: =IF(OR(C297="",D297=""),"",C297*D297)
D298: =C298*B298 -> 0 | E298: =IF(OR(C298="",D298=""),"",C298*D298)
D299: =C299*B299 -> 0 | E299: =IF(OR(C299="",D299=""),"",C299*D299)
D300: =C300*B300 -> 0 | E300: =IF(OR(C300="",D300=""),"",C300*D300)
... D308: =C308*B308 -> 0 | E308: =IF(OR(C308="",D308=""),"",C308*D308)
E309: =IF(OR(C309="",D309=""),"",C309*D309)
E310: =IF(OR(C310="",D310=""),"",C310*D310)
E311: =IF(OR(C311="",D311=""),"",C311*D311)
E312: =IF(OR(C312="",D312=""),"",C312*D312)
E313: =IF(OR(C313="",D313=""),"",C313*D313)
E314: =IF(OR(C314="",D314=""),"",C314*D314)
E315: =IF(OR(C315="",D315=""),"",C315*D315)
E316: =IF(OR(C316="",D316=""),"",C316*D316)
E317: =IF(OR(C317="",D317=""),"",C317*D317)
E318: =IF(OR(C318="",D318=""),"",C318*D318)
E319: =IF(OR(C319="",D319=""),"",C319*D319)
E320: =IF(OR(C320="",D320=""),"",C320*D320)
... E396: =IF(OR(C396="",D396=""),"",C396*D396)

Sheet Betania Ribeiro
A6: CLIENTE | B6: OPERAÇÃO | C6: VALOR | D6: FEE | E6: RECEITA | F6: MANDATO | G6: QTD | H6: INSTITUIÇÃO | I6: PARCEIRO INDICADOR | J6: ATUALIZAÇÃO | K6: FLUXO | L6: STATUS | M6: DATA FECHAMENTO | N6: MOTIVO DE RECUSA | O6: OBSERVAÇÃO
A7: JOTAAGRO PRODUCOES E COMERCIALIZACOES AGRICOLAS LTDA | B7: Custeio | C7: 8000000 | D7: 0.06 | E7: =D7*C7 -> 480000 | F7: Assinado | G7: 1 | H7: 7 ALDABRAN | J7: 46288 | K7: Aguardando retorno | L7: já passou em comitê e aguardando visita tecnica | O7: doc. com Guilherme - op. agro
A8: GILMAR AUGUSTO GOMES | B8: ⁠Credito Rural | C8: 10000000 | D8: 0.06 | E8: =D8*C8 -> 600000 | F8: Assinado | G8: 1 | H8: 7 ALDABRAN | J8: 46288 | K8: Pré-análise | L8: Análise de Crédito
E9: =D9*C9 -> 0
E10: =D10*C10 -> 0
E11: =D11*C11 -> 0
E12: =D12*C12 -> 0
E13: =D13*C13 -> 0
E14: =D14*C14 -> 0
E15: =D15*C15 -> 0
E16: =D16*C16 -> 0
E17: =D17*C17 -> 0
E18: =D18*C18 -> 0
E19: =D19*C19 -> 0
E20: =D20*C20 -> 0
... E292: =D292*C292 -> 0
E293: =IF(OR(C293="",D293=""),"",C293*D293)
E294: =IF(OR(C294="",D294=""),"",C294*D294)
E295: =IF(OR(C295="",D295=""),"",C295*D295)
E296: =IF(OR(C296="",D296=""),"",C296*D296)
E297: =IF(OR(C297="",D297=""),"",C297*D297)
E298: =IF(OR(C298="",D298=""),"",C298*D298)
E299: =IF(OR(C299="",D299=""),"",C299*D299)
E300: =IF(OR(C300="",D300=""),"",C300*D300)
E301: =IF(OR(C301="",D301=""),"",C301*D301)
E302: =IF(OR(C302="",D302=""),"",C302*D302)
E303: =IF(OR(C303="",D303=""),"",C303*D303)
E304: =IF(OR(C304="",D304=""),"",C304*D304)
... E400: =IF(OR(C400="",D400=""),"",C400*D400)

Sheet PARAMETROS
A1: PARÂMETROS — LISTAS OFICIAIS
A2: As abas dos gerentes puxam daqui. Para incluir um item, escreva na primeira linha vazia da coluna: a lista suspensa reconhece sozinha.
A3: Itens com * ainda precisam de confirmação (nome ou existência). Não apague item já usado: troque a Situação para Inativo.
A5: PARCEIRO (INSTITUIÇÃO) | B5: Situação | D5: GERENTE | E5: Situação | G5: TIPO DE OPERAÇÃO | H5: Situação | J5: STATUS | K5: Situação | M5: FLUXO | N5: Situação | P5: MANDATO | Q5: Situação | S5: ORIGEM | T5: Situação | V5: MOTIVO DE RECUSA | W5: Situação
A6: 7 ALDABRAN | B6: Ativo | D6: ⁠André Pullig | E6: Ativo | G6: Capital de Giro | H6: Ativo | J6: Cadastro | K6: Ativo | M6: Não enviado | N6: Ativo | P6: Não enviado | Q6: Ativo | S6: PJC Consultoria | T6: Ativo | V6: Restrição cadastral (Serasa / protesto) | W6: Ativo
A7: ACREDITAR FIDC | B7: Ativo | D7: ⁠Betania Ribeiro | E7: Ativo | G7: ⁠Antecipação de Recebíveis | H7: Ativo | J7: Análise de Crédito | K7: Ativo | M7: Pré-análise | N7: Ativo | P7: Enviado | Q7: Ativo | S7: ⁠LOBE Contabilidade | T7: Ativo | V7: Faturamento insuficiente | W7: Ativo
A8: AFFIX FIDC | B8: Ativo | D8: ⁠João Pullig | E8: Ativo | G8: ⁠Pro-Soluto | H8: Ativo | J8: Comitê | K8: Ativo | M8: Enviado | N8: Ativo | P8: Assinado | Q8: Ativo | S8: ⁠Sapiens Capital | T8: Ativo | V8: Garantia insuficiente | W8: Ativo
A9: ALIA CAPITAL | B9: Ativo | D9: Kaio Dias | E9: Ativo | G9: ⁠Credito Rural | H9: Ativo | J9: Aprovação | K9: Ativo | M9: Em andamento | N9: Ativo | P9: Não assinado | Q9: Ativo | S9: ⁠Alia Capital | T9: Ativo | V9: Documentação incompleta | W9: Ativo
A10: ALX NEGOCIOS | B10: Ativo | D10: ⁠Pablo Ruan | E10: Ativo | G10: ⁠Consórcio | H10: Ativo | J10: Assinatura de Contrato | K10: Ativo | M10: Aguardando retorno | N10: Ativo | S10: ⁠Blue Score | T10: Ativo | V10: Fora do perfil da instituição | W10: Ativo
A11: APX Finance | B11: Ativo | D11: ⁠Rafael Nedino | E11: Ativo | G11: ⁠FGI | H11: Ativo | J11: Aprovado | K11: Ativo | S11: ⁠Integra Negócios | T11: Ativo | V11: Outro (detalhar na observação) | W11: Ativo
A12: AR3 CAPITAL | B12: Ativo | G12: ⁠Home Equity | H12: Ativo | J12: Reprovado | K12: Ativo | S12: ⁠VM Consultoria | T12: Ativo
A13: ASTRUM FINANCEIRA | B13: Ativo | G13: ⁠CRA | H13: Ativo | J13: Finalizado | K13: Ativo | S13: ⁠LA Advogados | T13: Ativo
A14: BANCO BCG | B14: Ativo | G14: ⁠CRI | H14: Ativo | S14: ⁠PS Finance | T14: Ativo
A15: BANCO BMG | B15: Ativo | G15: ⁠CPR-F | H15: Ativo | S15: ⁠MB Finance | T15: Ativo
A16: BANCO BS2 | B16: Ativo | G16: ⁠Cambio | H16: Ativo | S16: ⁠Valor Investimentos | T16: Ativo
A17: BANCO BSB | B17: Ativo | G17: ⁠Antecipação de Contrato | H17: Ativo | S17: Astrum Finance | T17: Ativo
A18: BANCO BTG | B18: Ativo | G18: ⁠Seguro | H18: Ativo | S18: Diamond | T18: Ativo
A19: BANCO BV | B19: Ativo | G19: ⁠Limpa Nome | H19: Ativo
A20: BANCO C6 | B20: Ativo | G20: ⁠Antecipação SUS | H20: Ativo
A21: BANCO CNH | B21: Ativo | G21: ⁠Valuation | H21: Ativo
A22: BANCO DA AMAZONIA | B22: Ativo | G22: ⁠Reformulação Contábil | H22: Ativo
A23: BANCO DO BRASIL | B23: Ativo | G23: ⁠Financiamento de Máquinas | H23: Ativo
A24: BANCO DO NORDESTE | B24: Ativo | G24: ⁠Financiamento de Veículos | H24: Ativo
A25: BANCO INTER | B25: Ativo | G25: ⁠Financiamento de Imóvel | H25: Ativo
A26: BANCO ORIGINAL | B26: Ativo | G26: ⁠FCO | H26: Ativo
A27: BANCO SAFRA | B27: Ativo | G27: ⁠BNDES | H27: Ativo
A28: BANCO SOFISA | B28: Ativo | G28: ⁠Auto Equity | H28: Ativo
A29: BANRISUL | B29: Ativo | G29: ⁠Plano de Saúde | H29: Ativo
A30: BLUE SCORE | B30: Ativo | G30: ⁠ACC | H30: Ativo
... A38: DAVOS FIDC | B38: Ativo | G38: Investimento | H38: Ativo
A39: DAYCOVAL | B39: Ativo
A40: DMX CAPITAL | B40: Ativo
A41: FIRMA CAPITAL | B41: Ativo
A42: GOIAS BANK | B42: Ativo
A43: GUARA SECURITIZADORA | B43: Ativo
A44: GUPRO SIFRA | B44: Ativo
A45: INTRABANK | B45: Ativo
A46: INVISTA FIDC | B46: Ativo
A47: ITAU | B47: Ativo
A48: ITAU BBA | B48: Ativo
A49: MADCAP | B49: Ativo
A50: MAFEK BG BANK | B50: Ativo
... A83: DIAMOND | B83: Ativo

Sheet DASHBOARD
A1: DASHBOARD — VISÃO GERAL
A2: Consolidado das abas dos gerentes. Tudo se atualiza sozinho ao preencher as operações — não há botão a apertar.
A4: RESUMO GERAL
A5: Operações ativas | C5: Em negociação | E5: Volume aprovado | G5: Receita aprovada
A6: =COUNTIFS('André Pullig'!$A$7:$A$396,"<>")+COUNTIFS('Betania Ribeiro'!$A$7:$A$400,"<>")+COUNTIFS('João Pullig'!$A$7:$A$385,"<>")+COUNTIFS('Kaio Dias'!$A$7:$A$374,"<>")+COUNTIFS('Pablo Ruan'!$A$7:$A$382,"<>")+COUNTIFS(#REF!,"<>") -> #REF! | C6: =SUMIFS('André Pullig'!$C$7:$C$396,'André Pullig'!$L$7:$L$396,"<>Aprovado",'André Pullig'!$L$7:$L$396,"<>Reprovado",'André Pullig'!$L$7:$L$396,"<>")+SUMIFS('Betania Ribeiro'!$C$7:$C$400,'Betania Ribeiro'!$L$7:$L$400,"<>Aprovado",'Betania Ribeiro'!$L$7:$L$400,"<>Reprovado",'Betania Ribeiro'!$L$7:$L$400,"<>")+SUMIFS('João Pullig'!$C$7:$C$385,'João Pullig'!$L$7:$L$385,"<>Aprovado",'João Pullig'!$L$7:$L$385,"<>Reprovado",'João Pullig'!$L$7:$L$385,"<>")+SUMIFS('Kaio Dias'!$C$7:$C$374,'Kaio Dias'!$L$7:$L$374,"<>Aprovado",'Kaio Dias'!$L$7:$L$374,"<>Reprovado",'Kaio Dias'!$L$7:$L$374,"<>")+SUMIFS('Pablo Ruan'!$C$7:$C$382,'Pablo Ruan'!$L$7:$L$382,"<>Aprovado",'Pablo Ruan'!$L$7:$L$382,"<>Reprovado",'Pablo Ruan'!$L$7:$L$382,"<>")+SUMIFS(#REF!,#REF!,"<>Aprovado",#REF!,"<>Reprovado",#REF!,"<>") -> #REF! | E6: =SUMIFS('André Pullig'!$C$7:$C$396,'André Pullig'!$L$7:$L$396,"Aprovado")+SUMIFS('Betania Ribeiro'!$C$7:$C$400,'Betania Ribeiro'!$L$7:$L$400,"Aprovado")+SUMIFS('João Pullig'!$C$7:$C$385,'João Pullig'!$L$7:$L$385,"Aprovado")+SUMIFS('Kaio Dias'!$C$7:$C$374,'Kaio Dias'!$L$7:$L$374,"Aprovado")+SUMIFS('Pablo Ruan'!$C$7:$C$382,'Pablo Ruan'!$L$7:$L$382,"Aprovado")+SUMIFS(#REF!,#REF!,"Aprovado") -> #REF! | G6: =SUMIFS('André Pullig'!$E$7:$E$396,'André Pullig'!$L$7:$L$396,"Aprovado")+SUMIFS('Betania Ribeiro'!$E$7:$E$400,'Betania Ribeiro'!$L$7:$L$400,"Aprovado")+SUMIFS('João Pullig'!$E$7:$E$385,'João Pullig'!$L$7:$L$385,"Aprovado")+SUMIFS('Kaio Dias'!$E$7:$E$374,'Kaio Dias'!$L$7:$L$374,"Aprovado")+SUMIFS('Pablo Ruan'!$E$7:$E$382,'Pablo Ruan'!$L$7:$L$382,"Aprovado")+SUMIFS(#REF!,#REF!,"Aprovado") -> #REF!
A8: POR GERENTE
A9: Gerente | B9: Operações | C9: Sem valor | D9: Em negociação | E9: Volume aprovado | F9: Receita aprovada | G9: % da receita
A10: André Pullig | B10: =COUNTIFS('André Pullig'!$A$7:$A$396,"<>") -> 34 | C10: =COUNTIFS('André Pullig'!$A$7:$A$396,"<>",'André Pullig'!$C$7:$C$396,"") -> 0 | D10: =SUMIFS('André Pullig'!$C$7:$C$396,'André Pullig'!$L$7:$L$396,"<>Aprovado",'André Pullig'!$L$7:$L$396,"<>Reprovado",'André Pullig'!$L$7:$L$396,"<>") -> 45850000 | E10: =SUMIFS('André Pullig'!$C$7:$C$396,'André Pullig'!$L$7:$L$396,"Aprovado") -> 0 | F10: =SUMIFS('André Pullig'!$E$7:$E$396,'André Pullig'!$L$7:$L$396,"Aprovado") -> 0 | G10: =IF(N($F$16)=0,"",F10/$F$16) -> #REF!
A11: Betania Ribeiro | B11: =COUNTIFS('Betania Ribeiro'!$A$7:$A$400,"<>") -> 2 | C11: =COUNTIFS('Betania Ribeiro'!$A$7:$A$400,"<>",'Betania Ribeiro'!$C$7:$C$400,"") -> 0 | D11: =SUMIFS('Betania Ribeiro'!$C$7:$C$400,'Betania Ribeiro'!$L$7:$L$400,"<>Aprovado",'Betania Ribeiro'!$L$7:$L$400,"<>Reprovado",'Betania Ribeiro'!$L$7:$L$400,"<>") -> 18000000 | E11: =SUMIFS('Betania Ribeiro'!$C$7:$C$400,'Betania Ribeiro'!$L$7:$L$400,"Aprovado") -> 0 | F11: =SUMIFS('Betania Ribeiro'!$E$7:$E$400,'Betania Ribeiro'!$L$7:$L$400,"Aprovado") -> 0 | G11: =IF(N($F$16)=0,"",F11/$F$16) -> #REF!
A12: João Pullig | B12: =COUNTIFS('João Pullig'!$A$7:$A$385,"<>") -> 31 | C12: =COUNTIFS('João Pullig'!$A$7:$A$385,"<>",'João Pullig'!$C$7:$C$385,"") -> 0 | D12: =SUMIFS('João Pullig'!$C$7:$C$385,'João Pullig'!$L$7:$L$385,"<>Aprovado",'João Pullig'!$L$7:$L$385,"<>Reprovado",'João Pullig'!$L$7:$L$385,"<>") -> 180100000 | E12: =SUMIFS('João Pullig'!$C$7:$C$385,'João Pullig'!$L$7:$L$385,"Aprovado") -> 2000000 | F12: =SUMIFS('João Pullig'!$E$7:$E$385,'João Pullig'!$L$7:$L$385,"Aprovado") -> 65000 | G12: =IF(N($F$16)=0,"",F12/$F$16) -> #REF!
A13: Kaio Dias | B13: =COUNTIFS('Kaio Dias'!$A$7:$A$374,"<>") -> 33 | C13: =COUNTIFS('Kaio Dias'!$A$7:$A$374,"<>",'Kaio Dias'!$C$7:$C$374,"") -> 0 | D13: =SUMIFS('Kaio Dias'!$C$7:$C$374,'Kaio Dias'!$L$7:$L$374,"<>Aprovado",'Kaio Dias'!$L$7:$L$374,"<>Reprovado",'Kaio Dias'!$L$7:$L$374,"<>") -> 132006000 | E13: =SUMIFS('Kaio Dias'!$C$7:$C$374,'Kaio Dias'!$L$7:$L$374,"Aprovado") -> 777242 | F13: =SUMIFS('Kaio Dias'!$E$7:$E$374,'Kaio Dias'!$L$7:$L$374,"Aprovado") -> 19431.05 | G13: =IF(N($F$16)=0,"",F13/$F$16) -> #REF!
A14: Pablo Ruan | B14: =COUNTIFS('Pablo Ruan'!$A$7:$A$382,"<>") -> 35 | C14: =COUNTIFS('Pablo Ruan'!$A$7:$A$382,"<>",'Pablo Ruan'!$C$7:$C$382,"") -> 0 | D14: =SUMIFS('Pablo Ruan'!$C$7:$C$382,'Pablo Ruan'!$L$7:$L$382,"<>Aprovado",'Pablo Ruan'!$L$7:$L$382,"<>Reprovado",'Pablo Ruan'!$L$7:$L$382,"<>") -> 34437000 | E14: =SUMIFS('Pablo Ruan'!$C$7:$C$382,'Pablo Ruan'!$L$7:$L$382,"Aprovado") -> 3800000 | F14: =SUMIFS('Pablo Ruan'!$E$7:$E$382,'Pablo Ruan'!$L$7:$L$382,"Aprovado") -> 63500 | G14: =IF(N($F$16)=0,"",F14/$F$16) -> #REF!
A15: Rafael Nedino | B15: =COUNTIFS(#REF!,"<>") -> #REF! | C15: =COUNTIFS(#REF!,"<>",#REF!,"") -> #REF! | D15: =SUMIFS(#REF!,#REF!,"<>Aprovado",#REF!,"<>Reprovado",#REF!,"<>") -> #REF! | E15: =SUMIFS(#REF!,#REF!,"Aprovado") -> #REF! | F15: =SUMIFS(#REF!,#REF!,"Aprovado") -> #REF! | G15: =IF(N($F$16)=0,"",F15/$F$16) -> #REF!
A16: TOTAL | B16: =SUM(B10:B15) -> #REF! | C16: =SUM(C10:C15) -> #REF! | D16: =SUM(D10:D15) -> #REF! | E16: =SUM(E10:E15) -> #REF! | F16: =SUM(F10:F15) -> #REF! | G16: =SUM(G10:G15) -> #REF!
A18: SITUAÇÃO DAS OPERAÇÕES
A19: Status | B19: Operações | C19: Volume | D19: % do volume
A20: Cadastro | B20: =COUNTIFS('André Pullig'!$L$7:$L$396,"Cadastro")+COUNTIFS('Betania Ribeiro'!$L$7:$L$400,"Cadastro")+COUNTIFS('João Pullig'!$L$7:$L$385,"Cadastro")+COUNTIFS('Kaio Dias'!$L$7:$L$374,"Cadastro")+COUNTIFS('Pablo Ruan'!$L$7:$L$382,"Cadastro")+COUNTIFS(#REF!,"Cadastro") -> #REF! | C20: =SUMIFS('André Pullig'!$C$7:$C$396,'André Pullig'!$L$7:$L$396,"Cadastro")+SUMIFS('Betania Ribeiro'!$C$7:$C$400,'Betania Ribeiro'!$L$7:$L$400,"Cadastro")+SUMIFS('João Pullig'!$C$7:$C$385,'João Pullig'!$L$7:$L$385,"Cadastro")+SUMIFS('Kaio Dias'!$C$7:$C$374,'Kaio Dias'!$L$7:$L$374,"Cadastro")+SUMIFS('Pablo Ruan'!$C$7:$C$382,'Pablo Ruan'!$L$7:$L$382,"Cadastro")+SUMIFS(#REF!,#REF!,"Cadastro") -> #REF! | D20: =IF(SUM($C$20:$C$26)=0,"",C20/SUM($C$20:$C$26)) -> #REF!
A21: Análise de Crédito | B21: =COUNTIFS('André Pullig'!$L$7:$L$396,"Análise de Crédito")+COUNTIFS('Betania Ribeiro'!$L$7:$L$400,"Análise de Crédito")+COUNTIFS('João Pullig'!$L$7:$L$385,"Análise de Crédito")+COUNTIFS('Kaio Dias'!$L$7:$L$374,"Análise de Crédito")+COUNTIFS('Pablo Ruan'!$L$7:$L$382,"Análise de Crédito")+COUNTIFS(#REF!,"Análise de Crédito") -> #REF! | C21: =SUMIFS('André Pullig'!$C$7:$C$396,'André Pullig'!$L$7:$L$396,"Análise de Crédito")+SUMIFS('Betania Ribeiro'!$C$7:$C$400,'Betania Ribeiro'!$L$7:$L$400,"Análise de Crédito")+SUMIFS('João Pullig'!$C$7:$C$385,'João Pullig'!$L$7:$L$385,"Análise de Crédito")+SUMIFS('Kaio Dias'!$C$7:$C$374,'Kaio Dias'!$L$7:$L$374,"Análise de Crédito")+SUMIFS('Pablo Ruan'!$C$7:$C$382,'Pablo Ruan'!$L$7:$L$382,"Análise de Crédito")+SUMIFS(#REF!,#REF!,"Análise de Crédito") -> #REF! | D21: =IF(SUM($C$20:$C$26)=0,"",C21/SUM($C$20:$C$26)) -> #REF!
A22: Comitê | B22: =COUNTIFS('André Pullig'!$L$7:$L$396,"Comitê")+COUNTIFS('Betania Ribeiro'!$L$7:$L$400,"Comitê")+COUNTIFS('João Pullig'!$L$7:$L$385,"Comitê")+COUNTIFS('Kaio Dias'!$L$7:$L$374,"Comitê")+COUNTIFS('Pablo Ruan'!$L$7:$L$382,"Comitê")+COUNTIFS(#REF!,"Comitê") -> #REF! | C22: =SUMIFS('André Pullig'!$C$7:$C$396,'André Pullig'!$L$7:$L$396,"Comitê")+SUMIFS('Betania Ribeiro'!$C$7:$C$400,'Betania Ribeiro'!$L$7:$L$400,"Comitê")+SUMIFS('João Pullig'!$C$7:$C$385,'João Pullig'!$L$7:$L$385,"Comitê")+SUMIFS('Kaio Dias'!$C$7:$C$374,'Kaio Dias'!$L$7:$L$374,"Comitê")+SUMIFS('Pablo Ruan'!$C$7:$C$382,'Pablo Ruan'!$L$7:$L$382,"Comitê")+SUMIFS(#REF!,#REF!,"Comitê") -> #REF! | D22: =IF(SUM($C$20:$C$26)=0,"",C22/SUM($C$20:$C$26)) -> #REF!
A23: Aprovação | B23: =COUNTIFS('André Pullig'!$L$7:$L$396,"Aprovação")+COUNTIFS('Betania Ribeiro'!$L$7:$L$400,"Aprovação")+COUNTIFS('João Pullig'!$L$7:$L$385,"Aprovação")+COUNTIFS('Kaio Dias'!$L$7:$L$374,"Aprovação")+COUNTIFS('Pablo Ruan'!$L$7:$L$382,"Aprovação")+COUNTIFS(#REF!,"Aprovação") -> #REF! | C23: =SUMIFS('André Pullig'!$C$7:$C$396,'André Pullig'!$L$7:$L$396,"Aprovação")+SUMIFS('Betania Ribeiro'!$C$7:$C$400,'Betania Ribeiro'!$L$7:$L$400,"Aprovação")+SUMIFS('João Pullig'!$C$7:$C$385,'João Pullig'!$L$7:$L$385,"Aprovação")+SUMIFS('Kaio Dias'!$C$7:$C$374,'Kaio Dias'!$L$7:$L$374,"Aprovação")+SUMIFS('Pablo Ruan'!$C$7:$C$382,'Pablo Ruan'!$L$7:$L$382,"Aprovação")+SUMIFS(#REF!,#REF!,"Aprovação") -> #REF! | D23: =IF(SUM($C$20:$C$26)=0,"",C23/SUM($C$20:$C$26)) -> #REF!
A24: Assinatura de Contrato | B24: =COUNTIFS('André Pullig'!$L$7:$L$396,"Assinatura de Contrato")+COUNTIFS('Betania Ribeiro'!$L$7:$L$400,"Assinatura de Contrato")+COUNTIFS('João Pullig'!$L$7:$L$385,"Assinatura de Contrato")+COUNTIFS('Kaio Dias'!$L$7:$L$374,"Assinatura de Contrato")+COUNTIFS('Pablo Ruan'!$L$7:$L$382,"Assinatura de Contrato")+COUNTIFS(#REF!,"Assinatura de Contrato") -> #REF! | C24: =SUMIFS('André Pullig'!$C$7:$C$396,'André Pullig'!$L$7:$L$396,"Assinatura de Contrato")+SUMIFS('Betania Ribeiro'!$C$7:$C$400,'Betania Ribeiro'!$L$7:$L$400,"Assinatura de Contrato")+SUMIFS('João Pullig'!$C$7:$C$385,'João Pullig'!$L$7:$L$385,"Assinatura de Contrato")+SUMIFS('Kaio Dias'!$C$7:$C$374,'Kaio Dias'!$L$7:$L$374,"Assinatura de Contrato")+SUMIFS('Pablo Ruan'!$C$7:$C$382,'Pablo Ruan'!$L$7:$L$382,"Assinatura de Contrato")+SUMIFS(#REF!,#REF!,"Assinatura de Contrato") -> #REF! | D24: =IF(SUM($C$20:$C$26)=0,"",C24/SUM($C$20:$C$26)) -> #REF!
A25: Aprovado | B25: =COUNTIFS('André Pullig'!$L$7:$L$396,"Aprovado")+COUNTIFS('Betania Ribeiro'!$L$7:$L$400,"Aprovado")+COUNTIFS('João Pullig'!$L$7:$L$385,"Aprovado")+COUNTIFS('Kaio Dias'!$L$7:$L$374,"Aprovado")+COUNTIFS('Pablo Ruan'!$L$7:$L$382,"Aprovado")+COUNTIFS(#REF!,"Aprovado") -> #REF! | C25: =SUMIFS('André Pullig'!$C$7:$C$396,'André Pullig'!$L$7:$L$396,"Aprovado")+SUMIFS('Betania Ribeiro'!$C$7:$C$400,'Betania Ribeiro'!$L$7:$L$400,"Aprovado")+SUMIFS('João Pullig'!$C$7:$C$385,'João Pullig'!$L$7:$L$385,"Aprovado")+SUMIFS('Kaio Dias'!$C$7:$C$374,'Kaio Dias'!$L$7:$L$374,"Aprovado")+SUMIFS('Pablo Ruan'!$C$7:$C$382,'Pablo Ruan'!$L$7:$L$382,"Aprovado")+SUMIFS(#REF!,#REF!,"Aprovado") -> #REF! | D25: =IF(SUM($C$20:$C$26)=0,"",C25/SUM($C$20:$C$26)) -> #REF!
A26: Reprovado | B26: =COUNTIFS('André Pullig'!$L$7:$L$396,"Reprovado")+COUNTIFS('Betania Ribeiro'!$L$7:$L$400,"Reprovado")+COUNTIFS('João Pullig'!$L$7:$L$385,"Reprovado")+COUNTIFS('Kaio Dias'!$L$7:$L$374,"Reprovado")+COUNTIFS('Pablo Ruan'!$L$7:$L$382,"Reprovado")+COUNTIFS(#REF!,"Reprovado") -> #REF! | C26: =SUMIFS('André Pullig'!$C$7:$C$396,'André Pullig'!$L$7:$L$396,"Reprovado")+SUMIFS('Betania Ribeiro'!$C$7:$C$400,'Betania Ribeiro'!$L$7:$L$400,"Reprovado")+SUMIFS('João Pullig'!$C$7:$C$385,'João Pullig'!$L$7:$L$385,"Reprovado")+SUMIFS('Kaio Dias'!$C$7:$C$374,'Kaio Dias'!$L$7:$L$374,"Reprovado")+SUMIFS('Pablo Ruan'!$C$7:$C$382,'Pablo Ruan'!$L$7:$L$382,"Reprovado")+SUMIFS(#REF!,#REF!,"Reprovado") -> #REF! | D26: =IF(SUM($C$20:$C$26)=0,"",C26/SUM($C$20:$C$26)) -> #REF!
A28: POR TIPO DE OPERAÇÃO
A29: Tipo de operação | B29: Operações | C29: Volume | D29: Receita aprovada
A30: Capital de Giro | B30: =COUNTIFS('André Pullig'!$B$7:$B$396,"Capital de Giro")+COUNTIFS('Betania Ribeiro'!$B$7:$B$400,"Capital de Giro")+COUNTIFS('João Pullig'!$B$7:$B$385,"Capital de Giro")+COUNTIFS('Kaio Dias'!$B$7:$B$374,"Capital de Giro")+COUNTIFS('Pablo Ruan'!$B$7:$B$382,"Capital de Giro")+COUNTIFS(#REF!,"Capital de Giro") -> #REF! | C30: =SUMIFS('André Pullig'!$C$7:$C$396,'André Pullig'!$B$7:$B$396,"Capital de Giro")+SUMIFS('Betania Ribeiro'!$C$7:$C$400,'Betania Ribeiro'!$B$7:$B$400,"Capital de Giro")+SUMIFS('João Pullig'!$C$7:$C$385,'João Pullig'!$B$7:$B$385,"Capital de Giro")+SUMIFS('Kaio Dias'!$C$7:$C$374,'Kaio Dias'!$B$7:$B$374,"Capital de Giro")+SUMIFS('Pablo Ruan'!$C$7:$C$382,'Pablo Ruan'!$B$7:$B$382,"Capital de Giro")+SUMIFS(#REF!,#REF!,"Capital de Giro") -> #REF! | D30: =SUMIFS('André Pullig'!$E$7:$E$396,'André Pullig'!$B$7:$B$396,"Capital de Giro",'André Pullig'!$L$7:$L$396,"Aprovado")+SUMIFS('Betania Ribeiro'!$E$7:$E$400,'Betania Ribeiro'!$B$7:$B$400,"Capital de Giro",'Betania Ribeiro'!$L$7:$L$400,"Aprovado")+SUMIFS('João Pullig'!$E$7:$E$385,'João Pullig'!$B$7:$B$385,"Capital de Giro",'João Pullig'!$L$7:$L$385,"Aprovado")+SUMIFS('Kaio Dias'!$E$7:$E$374,'Kaio Dias'!$B$7:$B$374,"Capital de Giro",'Kaio Dias'!$L$7:$L$374,"Aprovado")+SUMIFS('Pablo Ruan'!$E$7:$E$382,'Pablo Ruan'!$B$7:$B$382,"Capital de Giro",'Pablo Ruan'!$L$7:$L$382,"Aprovado")+SUMIFS(#REF!,#REF!,"Capital de Giro",#REF!,"Aprovado") -> #REF!
A31: Pró-soluto | B31: =COUNTIFS('André Pullig'!$B$7:$B$396,"Pró-soluto")+COUNTIFS('Betania Ribeiro'!$B$7:$B$400,"Pró-soluto")+COUNTIFS('João Pullig'!$B$7:$B$385,"Pró-soluto")+COUNTIFS('Kaio Dias'!$B$7:$B$374,"Pró-soluto")+COUNTIFS('Pablo Ruan'!$B$7:$B$382,"Pró-soluto")+COUNTIFS(#REF!,"Pró-soluto") -> #REF! | C31: =SUMIFS('André Pullig'!$C$7:$C$396,'André Pullig'!$B$7:$B$396,"Pró-soluto")+SUMIFS('Betania Ribeiro'!$C$7:$C$400,'Betania Ribeiro'!$B$7:$B$400,"Pró-soluto")+SUMIFS('João Pullig'!$C$7:$C$385,'João Pullig'!$B$7:$B$385,"Pró-soluto")+SUMIFS('Kaio Dias'!$C$7:$C$374,'Kaio Dias'!$B$7:$B$374,"Pró-soluto")+SUMIFS('Pablo Ruan'!$C$7:$C$382,'Pablo Ruan'!$B$7:$B$382,"Pró-soluto")+SUMIFS(#REF!,#REF!,"Pró-soluto") -> #REF! | D31: =SUMIFS('André Pullig'!$E$7:$E$396,'André Pullig'!$B$7:$B$396,"Pró-soluto",'André Pullig'!$L$7:$L$396,"Aprovado")+SUMIFS('Betania Ribeiro'!$E$7:$E$400,'Betania Ribeiro'!$B$7:$B$400,"Pró-soluto",'Betania Ribeiro'!$L$7:$L$400,"Aprovado")+SUMIFS('João Pullig'!$E$7:$E$385,'João Pullig'!$B$7:$B$385,"Pró-soluto",'João Pullig'!$L$7:$L$385,"Aprovado")+SUMIFS('Kaio Dias'!$E$7:$E$374,'Kaio Dias'!$B$7:$B$374,"Pró-soluto",'Kaio Dias'!$L$7:$L$374,"Aprovado")+SUMIFS('Pablo Ruan'!$E$7:$E$382,'Pablo Ruan'!$B$7:$B$382,"Pró-soluto",'Pablo Ruan'!$L$7:$L$382,"Aprovado")+SUMIFS(#REF!,#REF!,"Pró-soluto",#REF!,"Aprovado") -> #REF!
A32: Antecipação de Recebíveis | B32: =COUNTIFS('André Pullig'!$B$7:$B$396,"Antecipação de Recebíveis")+COUNTIFS('Betania Ribeiro'!$B$7:$B$400,"Antecipação de Recebíveis")+COUNTIFS('João Pullig'!$B$7:$B$385,"Antecipação de Recebíveis")+COUNTIFS('Kaio Dias'!$B$7:$B$374,"Antecipação de Recebíveis")+COUNTIFS('Pablo Ruan'!$B$7:$B$382,"Antecipação de Recebíveis")+COUNTIFS(#REF!,"Antecipação de Recebíveis") -> #REF! | C32: =SUMIFS('André Pullig'!$C$7:$C$396,'André Pullig'!$B$7:$B$396,"Antecipação de Recebíveis")+SUMIFS('Betania Ribeiro'!$C$7:$C$400,'Betania Ribeiro'!$B$7:$B$400,"Antecipação de Recebíveis")+SUMIFS('João Pullig'!$C$7:$C$385,'João Pullig'!$B$7:$B$385,"Antecipação de Recebíveis")+SUMIFS('Kaio Dias'!$C$7:$C$374,'Kaio Dias'!$B$7:$B$374,"Antecipação de Recebíveis")+SUMIFS('Pablo Ruan'!$C$7:$C$382,'Pablo Ruan'!$B$7:$B$382,"Antecipação de Recebíveis")+SUMIFS(#REF!,#REF!,"Antecipação de Recebíveis") -> #REF! | D32: =SUMIFS('André Pullig'!$E$7:$E$396,'André Pullig'!$B$7:$B$396,"Antecipação de Recebíveis",'André Pullig'!$L$7:$L$396,"Aprovado")+SUMIFS('Betania Ribeiro'!$E$7:$E$400,'Betania Ribeiro'!$B$7:$B$400,"Antecipação de Recebíveis",'Betania Ribeiro'!$L$7:$L$400,"Aprovado")+SUMIFS('João Pullig'!$E$7:$E$385,'João Pullig'!$B$7:$B$385,"Antecipação de Recebíveis",'João Pullig'!$L$7:$L$385,"Aprovado")+SUMIFS('Kaio Dias'!$E$7:$E$374,'Kaio Dias'!$B$7:$B$374,"Antecipação de Recebíveis",'Kaio Dias'!$L$7:$L$374,"Aprovado")+SUMIFS('Pablo Ruan'!$E$7:$E$382,'Pablo Ruan'!$B$7:$B$382,"Antecipação de Recebíveis",'Pablo Ruan'!$L$7:$L$382,"Aprovado")+SUMIFS(#REF!,#REF!,"Antecipação de Recebíveis",#REF!,"Aprovado") -> #REF!
A33: Crédito Rural | B33: =COUNTIFS('André Pullig'!$B$7:$B$396,"Crédito Rural")+COUNTIFS('Betania Ribeiro'!$B$7:$B$400,"Crédito Rural")+COUNTIFS('João Pullig'!$B$7:$B$385,"Crédito Rural")+COUNTIFS('Kaio Dias'!$B$7:$B$374,"Crédito Rural")+COUNTIFS('Pablo Ruan'!$B$7:$B$382,"Crédito Rural")+COUNTIFS(#REF!,"Crédito Rural") -> #REF! | C33: =SUMIFS('André Pullig'!$C$7:$C$396,'André Pullig'!$B$7:$B$396,"Crédito Rural")+SUMIFS('Betania Ribeiro'!$C$7:$C$400,'Betania Ribeiro'!$B$7:$B$400,"Crédito Rural")+SUMIFS('João Pullig'!$C$7:$C$385,'João Pullig'!$B$7:$B$385,"Crédito Rural")+SUMIFS('Kaio Dias'!$C$7:$C$374,'Kaio Dias'!$B$7:$B$374,"Crédito Rural")+SUMIFS('Pablo Ruan'!$C$7:$C$382,'Pablo Ruan'!$B$7:$B$382,"Crédito Rural")+SUMIFS(#REF!,#REF!,"Crédito Rural") -> #REF! | D33: =SUMIFS('André Pullig'!$E$7:$E$396,'André Pullig'!$B$7:$B$396,"Crédito Rural",'André Pullig'!$L$7:$L$396,"Aprovado")+SUMIFS('Betania Ribeiro'!$E$7:$E$400,'Betania Ribeiro'!$B$7:$B$400,"Crédito Rural",'Betania Ribeiro'!$L$7:$L$400,"Aprovado")+SUMIFS('João Pullig'!$E$7:$E$385,'João Pullig'!$B$7:$B$385,"Crédito Rural",'João Pullig'!$L$7:$L$385,"Aprovado")+SUMIFS('Kaio Dias'!$E$7:$E$374,'Kaio Dias'!$B$7:$B$374,"Crédito Rural",'Kaio Dias'!$L$7:$L$374,"Aprovado")+SUMIFS('Pablo Ruan'!$E$7:$E$382,'Pablo Ruan'!$B$7:$B$382,"Crédito Rural",'Pablo Ruan'!$L$7:$L$382,"Aprovado")+SUMIFS(#REF!,#REF!,"Crédito Rural",#REF!,"Aprovado") -> #REF!
A34: Consórcio | B34: =COUNTIFS('André Pullig'!$B$7:$B$396,"Consórcio")+COUNTIFS('Betania Ribeiro'!$B$7:$B$400,"Consórcio")+COUNTIFS('João Pullig'!$B$7:$B$385,"Consórcio")+COUNTIFS('Kaio Dias'!$B$7:$B$374,"Consórcio")+COUNTIFS('Pablo Ruan'!$B$7:$B$382,"Consórcio")+COUNTIFS(#REF!,"Consórcio") -> #REF! | C34: =SUMIFS('André Pullig'!$C$7:$C$396,'André Pullig'!$B$7:$B$396,"Consórcio")+SUMIFS('Betania Ribeiro'!$C$7:$C$400,'Betania Ribeiro'!$B$7:$B$400,"Consórcio")+SUMIFS('João Pullig'!$C$7:$C$385,'João Pullig'!$B$7:$B$385,"Consórcio")+SUMIFS('Kaio Dias'!$C$7:$C$374,'Kaio Dias'!$B$7:$B$374,"Consórcio")+SUMIFS('Pablo Ruan'!$C$7:$C$382,'Pablo Ruan'!$B$7:$B$382,"Consórcio")+SUMIFS(#REF!,#REF!,"Consórcio") -> #REF! | D34: =SUMIFS('André Pullig'!$E$7:$E$396,'André Pullig'!$B$7:$B$396,"Consórcio",'André Pullig'!$L$7:$L$396,"Aprovado")+SUMIFS('Betania Ribeiro'!$E$7:$E$400,'Betania Ribeiro'!$B$7:$B$400,"Consórcio",'Betania Ribeiro'!$L$7:$L$400,"Aprovado")+SUMIFS('João Pullig'!$E$7:$E$385,'João Pullig'!$B$7:$B$385,"Consórcio",'João Pullig'!$L$7:$L$385,"Aprovado")+SUMIFS('Kaio Dias'!$E$7:$E$374,'Kaio Dias'!$B$7:$B$374,"Consórcio",'Kaio Dias'!$L$7:$L$374,"Aprovado")+SUMIFS('Pablo Ruan'!$E$7:$E$382,'Pablo Ruan'!$B$7:$B$382,"Consórcio",'Pablo Ruan'!$L$7:$L$382,"Aprovado")+SUMIFS(#REF!,#REF!,"Consórcio",#REF!,"Aprovado") -> #REF!
A35: Venda de Ativos | B35: =COUNTIFS('André Pullig'!$B$7:$B$396,"Venda de Ativos")+COUNTIFS('Betania Ribeiro'!$B$7:$B$400,"Venda de Ativos")+COUNTIFS('João Pullig'!$B$7:$B$385,"Venda de Ativos")+COUNTIFS('Kaio Dias'!$B$7:$B$374,"Venda de Ativos")+COUNTIFS('Pablo Ruan'!$B$7:$B$382,"Venda de Ativos")+COUNTIFS(#REF!,"Venda de Ativos") -> #REF! | C35: =SUMIFS('André Pullig'!$C$7:$C$396,'André Pullig'!$B$7:$B$396,"Venda de Ativos")+SUMIFS('Betania Ribeiro'!$C$7:$C$400,'Betania Ribeiro'!$B$7:$B$400,"Venda de Ativos")+SUMIFS('João Pullig'!$C$7:$C$385,'João Pullig'!$B$7:$B$385,"Venda de Ativos")+SUMIFS('Kaio Dias'!$C$7:$C$374,'Kaio Dias'!$B$7:$B$374,"Venda de Ativos")+SUMIFS('Pablo Ruan'!$C$7:$C$382,'Pablo Ruan'!$B$7:$B$382,"Venda de Ativos")+SUMIFS(#REF!,#REF!,"Venda de Ativos") -> #REF! | D35: =SUMIFS('André Pullig'!$E$7:$E$396,'André Pullig'!$B$7:$B$396,"Venda de Ativos",'André Pullig'!$L$7:$L$396,"Aprovado")+SUMIFS('Betania Ribeiro'!$E$7:$E$400,'Betania Ribeiro'!$B$7:$B$400,"Venda de Ativos",'Betania Ribeiro'!$L$7:$L$400,"Aprovado")+SUMIFS('João Pullig'!$E$7:$E$385,'João Pullig'!$B$7:$B$385,"Venda de Ativos",'João Pullig'!$L$7:$L$385,"Aprovado")+SUMIFS('Kaio Dias'!$E$7:$E$374,'Kaio Dias'!$B$7:$B$374,"Venda de Ativos",'Kaio Dias'!$L$7:$L$374,"Aprovado")+SUMIFS('Pablo Ruan'!$E$7:$E$382,'Pablo Ruan'!$B$7:$B$382,"Venda de Ativos",'Pablo Ruan'!$L$7:$L$382,"Aprovado")+SUMIFS(#REF!,#REF!,"Venda de Ativos",#REF!,"Aprovado") -> #REF!
A36: FGI | B36: =COUNTIFS('André Pullig'!$B$7:$B$396,"FGI")+COUNTIFS('Betania Ribeiro'!$B$7:$B$400,"FGI")+COUNTIFS('João Pullig'!$B$7:$B$385,"FGI")+COUNTIFS('Kaio Dias'!$B$7:$B$374,"FGI")+COUNTIFS('Pablo Ruan'!$B$7:$B$382,"FGI")+COUNTIFS(#REF!,"FGI") -> #REF! | C36: =SUMIFS('André Pullig'!$C$7:$C$396,'André Pullig'!$B$7:$B$396,"FGI")+SUMIFS('Betania Ribeiro'!$C$7:$C$400,'Betania Ribeiro'!$B$7:$B$400,"FGI")+SUMIFS('João Pullig'!$C$7:$C$385,'João Pullig'!$B$7:$B$385,"FGI")+SUMIFS('Kaio Dias'!$C$7:$C$374,'Kaio Dias'!$B$7:$B$374,"FGI")+SUMIFS('Pablo Ruan'!$C$7:$C$382,'Pablo Ruan'!$B$7:$B$382,"FGI")+SUMIFS(#REF!,#REF!,"FGI") -> #REF! | D36: =SUMIFS('André Pullig'!$E$7:$E$396,'André Pullig'!$B$7:$B$396,"FGI",'André Pullig'!$L$7:$L$396,"Aprovado")+SUMIFS('Betania Ribeiro'!$E$7:$E$400,'Betania Ribeiro'!$B$7:$B$400,"FGI",'Betania Ribeiro'!$L$7:$L$400,"Aprovado")+SUMIFS('João Pullig'!$E$7:$E$385,'João Pullig'!$B$7:$B$385,"FGI",'João Pullig'!$L$7:$L$385,"Aprovado")+SUMIFS('Kaio Dias'!$E$7:$E$374,'Kaio Dias'!$B$7:$B$374,"FGI",'Kaio Dias'!$L$7:$L$374,"Aprovado")+SUMIFS('Pablo Ruan'!$E$7:$E$382,'Pablo Ruan'!$B$7:$B$382,"FGI",'Pablo Ruan'!$L$7:$L$382,"Aprovado")+SUMIFS(#REF!,#REF!,"FGI",#REF!,"Aprovado") -> #REF!
A37: Serviço Cadastral | B37: =COUNTIFS('André Pullig'!$B$7:$B$396,"Serviço Cadastral")+COUNTIFS('Betania Ribeiro'!$B$7:$B$400,"Serviço Cadastral")+COUNTIFS('João Pullig'!$B$7:$B$385,"Serviço Cadastral")+COUNTIFS('Kaio Dias'!$B$7:$B$374,"Serviço Cadastral")+COUNTIFS('Pablo Ruan'!$B$7:$B$382,"Serviço Cadastral")+COUNTIFS(#REF!,"Serviço Cadastral") -> #REF! | C37: =SUMIFS('André Pullig'!$C$7:$C$396,'André Pullig'!$B$7:$B$396,"Serviço Cadastral")+SUMIFS('Betania Ribeiro'!$C$7:$C$400,'Betania Ribeiro'!$B$7:$B$400,"Serviço Cadastral")+SUMIFS('João Pullig'!$C$7:$C$385,'João Pullig'!$B$7:$B$385,"Serviço Cadastral")+SUMIFS('Kaio Dias'!$C$7:$C$374,'Kaio Dias'!$B$7:$B$374,"Serviço Cadastral")+SUMIFS('Pablo Ruan'!$C$7:$C$382,'Pablo Ruan'!$B$7:$B$382,"Serviço Cadastral")+SUMIFS(#REF!,#REF!,"Serviço Cadastral") -> #REF! | D37: =SUMIFS('André Pullig'!$E$7:$E$396,'André Pullig'!$B$7:$B$396,"Serviço Cadastral",'André Pullig'!$L$7:$L$396,"Aprovado")+SUMIFS('Betania Ribeiro'!$E$7:$E$400,'Betania Ribeiro'!$B$7:$B$400,"Serviço Cadastral",'Betania Ribeiro'!$L$7:$L$400,"Aprovado")+SUMIFS('João Pullig'!$E$7:$E$385,'João Pullig'!$B$7:$B$385,"Serviço Cadastral",'João Pullig'!$L$7:$L$385,"Aprovado")+SUMIFS('Kaio Dias'!$E$7:$E$374,'Kaio Dias'!$B$7:$B$374,"Serviço Cadastral",'Kaio Dias'!$L$7:$L$374,"Aprovado")+SUMIFS('Pablo Ruan'!$E$7:$E$382,'Pablo Ruan'!$B$7:$B$382,"Serviço Cadastral",'Pablo Ruan'!$L$7:$L$382,"Aprovado")+SUMIFS(#REF!,#REF!,"Serviço Cadastral",#REF!,"Aprovado") -> #REF!
A38: Venda de Colégio | B38: =COUNTIFS('André Pullig'!$B$7:$B$396,"Venda de Colégio")+COUNTIFS('Betania Ribeiro'!$B$7:$B$400,"Venda de Colégio")+COUNTIFS('João Pullig'!$B$7:$B$385,"Venda de Colégio")+COUNTIFS('Kaio Dias'!$B$7:$B$374,"Venda de Colégio")+COUNTIFS('Pablo Ruan'!$B$7:$B$382,"Venda de Colégio")+COUNTIFS(#REF!,"Venda de Colégio") -> #REF! | C38: =SUMIFS('André Pullig'!$C$7:$C$396,'André Pullig'!$B$7:$B$396,"Venda de Colégio")+SUMIFS('Betania Ribeiro'!$C$7:$C$400,'Betania Ribeiro'!$B$7:$B$400,"Venda de Colégio")+SUMIFS('João Pullig'!$C$7:$C$385,'João Pullig'!$B$7:$B$385,"Venda de Colégio")+SUMIFS('Kaio Dias'!$C$7:$C$374,'Kaio Dias'!$B$7:$B$374,"Venda de Colégio")+SUMIFS('Pablo Ruan'!$C$7:$C$382,'Pablo Ruan'!$B$7:$B$382,"Venda de Colégio")+SUMIFS(#REF!,#REF!,"Venda de Colégio") -> #REF! | D38: =SUMIFS('André Pullig'!$E$7:$E$396,'André Pullig'!$B$7:$B$396,"Venda de Colégio",'André Pullig'!$L$7:$L$396,"Aprovado")+SUMIFS('Betania Ribeiro'!$E$7:$E$400,'Betania Ribeiro'!$B$7:$B$400,"Venda de Colégio",'Betania Ribeiro'!$L$7:$L$400,"Aprovado")+SUMIFS('João Pullig'!$E$7:$E$385,'João Pullig'!$B$7:$B$385,"Venda de Colégio",'João Pullig'!$L$7:$L$385,"Aprovado")+SUMIFS('Kaio Dias'!$E$7:$E$374,'Kaio Dias'!$B$7:$B$374,"Venda de Colégio",'Kaio Dias'!$L$7:$L$374,"Aprovado")+SUMIFS('Pablo Ruan'!$E$7:$E$382,'Pablo Ruan'!$B$7:$B$382,"Venda de Colégio",'Pablo Ruan'!$L$7:$L$382,"Aprovado")+SUMIFS(#REF!,#REF!,"Venda de Colégio",#REF!,"Aprovado") -> #REF!
A39: Conta / Maquininha | B39: =COUNTIFS('André Pullig'!$B$7:$B$396,"Conta / Maquininha")+COUNTIFS('Betania Ribeiro'!$B$7:$B$400,"Conta / Maquininha")+COUNTIFS('João Pullig'!$B$7:$B$385,"Conta / Maquininha")+COUNTIFS('Kaio Dias'!$B$7:$B$374,"Conta / Maquininha")+COUNTIFS('Pablo Ruan'!$B$7:$B$382,"Conta / Maquininha")+COUNTIFS(#REF!,"Conta / Maquininha") -> #REF! | C39: =SUMIFS('André Pullig'!$C$7:$C$396,'André Pullig'!$B$7:$B$396,"Conta / Maquininha")+SUMIFS('Betania Ribeiro'!$C$7:$C$400,'Betania Ribeiro'!$B$7:$B$400,"Conta / Maquininha")+SUMIFS('João Pullig'!$C$7:$C$385,'João Pullig'!$B$7:$B$385,"Conta / Maquininha")+SUMIFS('Kaio Dias'!$C$7:$C$374,'Kaio Dias'!$B$7:$B$374,"Conta / Maquininha")+SUMIFS('Pablo Ruan'!$C$7:$C$382,'Pablo Ruan'!$B$7:$B$382,"Conta / Maquininha")+SUMIFS(#REF!,#REF!,"Conta / Maquininha") -> #REF! | D39: =SUMIFS('André Pullig'!$E$7:$E$396,'André Pullig'!$B$7:$B$396,"Conta / Maquininha",'André Pullig'!$L$7:$L$396,"Aprovado")+SUMIFS('Betania Ribeiro'!$E$7:$E$400,'Betania Ribeiro'!$B$7:$B$400,"Conta / Maquininha",'Betania Ribeiro'!$L$7:$L$400,"Aprovado")+SUMIFS('João Pullig'!$E$7:$E$385,'João Pullig'!$B$7:$B$385,"Conta / Maquininha",'João Pullig'!$L$7:$L$385,"Aprovado")+SUMIFS('Kaio Dias'!$E$7:$E$374,'Kaio Dias'!$B$7:$B$374,"Conta / Maquininha",'Kaio Dias'!$L$7:$L$374,"Aprovado")+SUMIFS('Pablo Ruan'!$E$7:$E$382,'Pablo Ruan'!$B$7:$B$382,"Conta / Maquininha",'Pablo Ruan'!$L$7:$L$382,"Aprovado")+SUMIFS(#REF!,#REF!,"Conta / Maquininha",#REF!,"Aprovado") -> #REF!
A40: Câmbio | B40: =COUNTIFS('André Pullig'!$B$7:$B$396,"Câmbio")+COUNTIFS('Betania Ribeiro'!$B$7:$B$400,"Câmbio")+COUNTIFS('João Pullig'!$B$7:$B$385,"Câmbio")+COUNTIFS('Kaio Dias'!$B$7:$B$374,"Câmbio")+COUNTIFS('Pablo Ruan'!$B$7:$B$382,"Câmbio")+COUNTIFS(#REF!,"Câmbio") -> #REF! | C40: =SUMIFS('André Pullig'!$C$7:$C$396,'André Pullig'!$B$7:$B$396,"Câmbio")+SUMIFS('Betania Ribeiro'!$C$7:$C$400,'Betania Ribeiro'!$B$7:$B$400,"Câmbio")+SUMIFS('João Pullig'!$C$7:$C$385,'João Pullig'!$B$7:$B$385,"Câmbio")+SUMIFS('Kaio Dias'!$C$7:$C$374,'Kaio Dias'!$B$7:$B$374,"Câmbio")+SUMIFS('Pablo Ruan'!$C$7:$C$382,'Pablo Ruan'!$B$7:$B$382,"Câmbio")+SUMIFS(#REF!,#REF!,"Câmbio") -> #REF! | D40: =SUMIFS('André Pullig'!$E$7:$E$396,'André Pullig'!$B$7:$B$396,"Câmbio",'André Pullig'!$L$7:$L$396,"Aprovado")+SUMIFS('Betania Ribeiro'!$E$7:$E$400,'Betania Ribeiro'!$B$7:$B$400,"Câmbio",'Betania Ribeiro'!$L$7:$L$400,"Aprovado")+SUMIFS('João Pullig'!$E$7:$E$385,'João Pullig'!$B$7:$B$385,"Câmbio",'João Pullig'!$L$7:$L$385,"Aprovado")+SUMIFS('Kaio Dias'!$E$7:$E$374,'Kaio Dias'!$B$7:$B$374,"Câmbio",'Kaio Dias'!$L$7:$L$374,"Aprovado")+SUMIFS('Pablo Ruan'!$E$7:$E$382,'Pablo Ruan'!$B$7:$B$382,"Câmbio",'Pablo Ruan'!$L$7:$L$382,"Aprovado")+SUMIFS(#REF!,#REF!,"Câmbio",#REF!,"Aprovado") -> #REF!
A41: Operação Estruturada | B41: =COUNTIFS('André Pullig'!$B$7:$B$396,"Operação Estruturada")+COUNTIFS('Betania Ribeiro'!$B$7:$B$400,"Operação Estruturada")+COUNTIFS('João Pullig'!$B$7:$B$385,"Operação Estruturada")+COUNTIFS('Kaio Dias'!$B$7:$B$374,"Operação Estruturada")+COUNTIFS('Pablo Ruan'!$B$7:$B$382,"Operação Estruturada")+COUNTIFS(#REF!,"Operação Estruturada") -> #REF! | C41: =SUMIFS('André Pullig'!$C$7:$C$396,'André Pullig'!$B$7:$B$396,"Operação Estruturada")+SUMIFS('Betania Ribeiro'!$C$7:$C$400,'Betania Ribeiro'!$B$7:$B$400,"Operação Estruturada")+SUMIFS('João Pullig'!$C$7:$C$385,'João Pullig'!$B$7:$B$385,"Operação Estruturada")+SUMIFS('Kaio Dias'!$C$7:$C$374,'Kaio Dias'!$B$7:$B$374,"Operação Estruturada")+SUMIFS('Pablo Ruan'!$C$7:$C$382,'Pablo Ruan'!$B$7:$B$382,"Operação Estruturada")+SUMIFS(#REF!,#REF!,"Operação Estruturada") -> #REF! | D41: =SUMIFS('André Pullig'!$E$7:$E$396,'André Pullig'!$B$7:$B$396,"Operação Estruturada",'André Pullig'!$L$7:$L$396,"Aprovado")+SUMIFS('Betania Ribeiro'!$E$7:$E$400,'Betania Ribeiro'!$B$7:$B$400,"Operação Estruturada",'Betania Ribeiro'!$L$7:$L$400,"Aprovado")+SUMIFS('João Pullig'!$E$7:$E$385,'João Pullig'!$B$7:$B$385,"Operação Estruturada",'João Pullig'!$L$7:$L$385,"Aprovado")+SUMIFS('Kaio Dias'!$E$7:$E$374,'Kaio Dias'!$B$7:$B$374,"Operação Estruturada",'Kaio Dias'!$L$7:$L$374,"Aprovado")+SUMIFS('Pablo Ruan'!$E$7:$E$382,'Pablo Ruan'!$B$7:$B$382,"Operação Estruturada",'Pablo Ruan'!$L$7:$L$382,"Aprovado")+SUMIFS(#REF!,#REF!,"Operação Estruturada",#REF!,"Aprovado") -> #REF!
A43: CONSULTA POR INSTITUIÇÃO
A44: Escolha a instituição: | B44: 7 ALDABRAN | D44: ← troque para consultar outra
A46: Operações | C46: Em negociação | E46: Volume aprovado | G46: Receita aprovada
A47: =COUNTIFS('André Pullig'!$H$7:$H$396,B44)+COUNTIFS('Betania Ribeiro'!$H$7:$H$400,B44)+COUNTIFS('João Pullig'!$H$7:$H$385,B44)+COUNTIFS('Kaio Dias'!$H$7:$H$374,B44)+COUNTIFS('Pablo Ruan'!$H$7:$H$382,B44)+COUNTIFS(#REF!,B44) -> #REF! | C47: =SUMIFS('André Pullig'!$C$7:$C$396,'André Pullig'!$H$7:$H$396,B44,'André Pullig'!$L$7:$L$396,"<>Aprovado",'André Pullig'!$L$7:$L$396,"<>Reprovado",'André Pullig'!$L$7:$L$396,"<>")+SUMIFS('Betania Ribeiro'!$C$7:$C$400,'Betania Ribeiro'!$H$7:$H$400,B44,'Betania Ribeiro'!$L$7:$L$400,"<>Aprovado",'Betania Ribeiro'!$L$7:$L$400,"<>Reprovado",'Betania Ribeiro'!$L$7:$L$400,"<>")+SUMIFS('João Pullig'!$C$7:$C$385,'João Pullig'!$H$7:$H$385,B44,'João Pullig'!$L$7:$L$385,"<>Aprovado",'João Pullig'!$L$7:$L$385,"<>Reprovado",'João Pullig'!$L$7:$L$385,"<>")+SUMIFS('Kaio Dias'!$C$7:$C$374,'Kaio Dias'!$H$7:$H$374,B44,'Kaio Dias'!$L$7:$L$374,"<>Aprovado",'Kaio Dias'!$L$7:$L$374,"<>Reprovado",'Kaio Dias'!$L$7:$L$374,"<>")+SUMIFS('Pablo Ruan'!$C$7:$C$382,'Pablo Ruan'!$H$7:$H$382,B44,'Pablo Ruan'!$L$7:$L$382,"<>Aprovado",'Pablo Ruan'!$L$7:$L$382,"<>Reprovado",'Pablo Ruan'!$L$7:$L$382,"<>")+SUMIFS(#REF!,#REF!,B44,#REF!,"<>Aprovado",#REF!,"<>Reprovado",#REF!,"<>") -> #REF! | E47: =SUMIFS('André Pullig'!$C$7:$C$396,'André Pullig'!$H$7:$H$396,B44,'André Pullig'!$L$7:$L$396,"Aprovado")+SUMIFS('Betania Ribeiro'!$C$7:$C$400,'Betania Ribeiro'!$H$7:$H$400,B44,'Betania Ribeiro'!$L$7:$L$400,"Aprovado")+SUMIFS('João Pullig'!$C$7:$C$385,'João Pullig'!$H$7:$H$385,B44,'João Pullig'!$L$7:$L$385,"Aprovado")+SUMIFS('Kaio Dias'!$C$7:$C$374,'Kaio Dias'!$H$7:$H$374,B44,'Kaio Dias'!$L$7:$L$374,"Aprovado")+SUMIFS('Pablo Ruan'!$C$7:$C$382,'Pablo Ruan'!$H$7:$H$382,B44,'Pablo Ruan'!$L$7:$L$382,"Aprovado")+SUMIFS(#REF!,#REF!,B44,#REF!,"Aprovado") -> #REF! | G47: =SUMIFS('André Pullig'!$E$7:$E$396,'André Pullig'!$H$7:$H$396,B44,'André Pullig'!$L$7:$L$396,"Aprovado")+SUMIFS('Betania Ribeiro'!$E$7:$E$400,'Betania Ribeiro'!$H$7:$H$400,B44,'Betania Ribeiro'!$L$7:$L$400,"Aprovado")+SUMIFS('João Pullig'!$E$7:$E$385,'João Pullig'!$H$7:$H$385,B44,'João Pullig'!$L$7:$L$385,"Aprovado")+SUMIFS('Kaio Dias'!$E$7:$E$374,'Kaio Dias'!$H$7:$H$374,B44,'Kaio Dias'!$L$7:$L$374,"Aprovado")+SUMIFS('Pablo Ruan'!$E$7:$E$382,'Pablo Ruan'!$H$7:$H$382,B44,'Pablo Ruan'!$L$7:$L$382,"Aprovado")+SUMIFS(#REF!,#REF!,B44,#REF!,"Aprovado") -> #REF!
A49: • Não escreva nada nesta aba: tudo aqui é fórmula. Para mudar um número, corrija a operação na aba do gerente.
A50: • "Em negociação" = tudo que não está Aprovado nem Reprovado e tem status preenchido. Cada linha conta como uma operação.
A51: • Reprovados ficam na aba HISTÓRICO e por isso não aparecem aqui.
A52: • Receita só existe onde o Fee está preenchido — sem fee, a operação entra no volume mas não na receita.
A53: • "Sem valor" em vermelho: operações lançadas sem o campo Valor. Elas não entram em nenhum total — preencha o valor na aba do gerente para elas aparecerem.

Sheet METAS
A1: METAS E REALIZADO — RECEITA POR GERENTE
A2: Receita da PJC, não volume operado. Preencha só a linha META: o realizado vem sozinho das operações — status Aprovado até junho/2026 e status Finalizado de julho/2026 em diante, somando a aba de cada gerente e a aba HISTÓRICO.
A3: Ano base: | B3: 2026 | C3: ← troque aqui para ver outro ano
A4: Finalizado a partir de: | B4: =DATE(2026,7,1) -> 46204 | C4: ← desta data em diante o Realizado conta status Finalizado; antes dela, Aprovado
A5: GERENTE / LINHA | B5: Janeiro | C5: Fevereiro | D5: Março | E5: Abril | F5: Maio | G5: Junho | H5: Julho | I5: Agosto | J5: Setembro | K5: Outubro | L5: Novembro | M5: Dezembro | N5: TOTAL ANO | O5: SITUAÇÃO | P5: SEM DATA DE FECHAMENTO
A6: ANDRÉ PULLIG
A7: Meta | B7: 20000 | C7: 23000 | D7: 26000 | E7: 30000 | F7: 25000 | G7: 23000 | H7: 26000 | I7: 30000 | J7: 26000 | K7: 25000 | L7: 20000 | M7: 18000 | N7: =SUM(B7:M7) -> 292000
A8: Realizado | B8: =IF(DATE($B$3,1,1)>=$B$4,SUMIFS('André Pullig'!$E$7:$E$396,'André Pullig'!$L$7:$L$396,"Finalizado",'André Pullig'!$M$7:$M$396,">="&DATE($B$3,1,1),'André Pullig'!$M$7:$M$396,"<"&DATE($B$3,2,1))+SUMIFS(HISTÓRICO!$F$5:$F$268,HISTÓRICO!$A$5:$A$268,"*André Pullig*",HISTÓRICO!$M$5:$M$268,"Finalizado",HISTÓRICO!$N$5:$N$268,">="&DATE($B$3,1,1),HISTÓRICO!$N$5:$N$268,"<"&DATE($B$3,2,1)),SUMIFS('André Pullig'!$E$7:$E$396,'André Pullig'!$L$7:$L$396,"Aprovado",'André Pullig'!$M$7:$M$396,">="&DATE($B$3,1,1),'André Pullig'!$M$7:$M$396,"<"&DATE($B$3,2,1))) -> 0 | C8: =IF(DATE($B$3,2,1)>=$B$4,SUMIFS('André Pullig'!$E$7:$E$396,'André Pullig'!$L$7:$L$396,"Finalizado",'André Pullig'!$M$7:$M$396,">="&DATE($B$3,2,1),'André Pullig'!$M$7:$M$396,"<"&DATE($B$3,3,1))+SUMIFS(HISTÓRICO!$F$5:$F$268,HISTÓRICO!$A$5:$A$268,"*André Pullig*",HISTÓRICO!$M$5:$M$268,"Finalizado",HISTÓRICO!$N$5:$N$268,">="&DATE($B$3,2,1),HISTÓRICO!$N$5:$N$268,"<"&DATE($B$3,3,1)),SUMIFS('André Pullig'!$E$7:$E$396,'André Pullig'!$L$7:$L$396,"Aprovado",'André Pullig'!$M$7:$M$396,">="&DATE($B$3,2,1),'André Pullig'!$M$7:$M$396,"<"&DATE($B$3,3,1))) -> 0 | D8: =IF(DATE($B$3,3,1)>=$B$4,SUMIFS('André Pullig'!$E$7:$E$396,'André Pullig'!$L$7:$L$396,"Finalizado",'André Pullig'!$M$7:$M$396,">="&DATE($B$3,3,1),'André Pullig'!$M$7:$M$396,"<"&DATE($B$3,4,1))+SUMIFS(HISTÓRICO!$F$5:$F$268,HISTÓRICO!$A$5:$A$268,"*André Pullig*",HISTÓRICO!$M$5:$M$268,"Finalizado",HISTÓRICO!$N$5:$N$268,">="&DATE($B$3,3,1),HISTÓRICO!$N$5:$N$268,"<"&DATE($B$3,4,1)),SUMIFS('André Pullig'!$E$7:$E$396,'André Pullig'!$L$7:$L$396,"Aprovado",'André Pullig'!$M$7:$M$396,">="&DATE($B$3,3,1),'André Pullig'!$M$7:$M$396,"<"&DATE($B$3,4,1))) -> 0 | E8: =IF(DATE($B$3,4,1)>=$B$4,SUMIFS('André Pullig'!$E$7:$E$396,'André Pullig'!$L$7:$L$396,"Finalizado",'André Pullig'!$M$7:$M$396,">="&DATE($B$3,4,1),'André Pullig'!$M$7:$M$396,"<"&DATE($B$3,5,1))+SUMIFS(HISTÓRICO!$F$5:$F$268,HISTÓRICO!$A$5:$A$268,"*André Pullig*",HISTÓRICO!$M$5:$M$268,"Finalizado",HISTÓRICO!$N$5:$N$268,">="&DATE($B$3,4,1),HISTÓRICO!$N$5:$N$268,"<"&DATE($B$3,5,1)),SUMIFS('André Pullig'!$E$7:$E$396,'André Pullig'!$L$7:$L$396,"Aprovado",'André Pullig'!$M$7:$M$396,">="&DATE($B$3,4,1),'André Pullig'!$M$7:$M$396,"<"&DATE($B$3,5,1))) -> 0 | F8: =IF(DATE($B$3,5,1)>=$B$4,SUMIFS('André Pullig'!$E$7:$E$396,'André Pullig'!$L$7:$L$396,"Finalizado",'André Pullig'!$M$7:$M$396,">="&DATE($B$3,5,1),'André Pullig'!$M$7:$M$396,"<"&DATE($B$3,6,1))+SUMIFS(HISTÓRICO!$F$5:$F$268,HISTÓRICO!$A$5:$A$268,"*André Pullig*",HISTÓRICO!$M$5:$M$268,"Finalizado",HISTÓRICO!$N$5:$N$268,">="&DATE($B$3,5,1),HISTÓRICO!$N$5:$N$268,"<"&DATE($B$3,6,1)),SUMIFS('André Pullig'!$E$7:$E$396,'André Pullig'!$L$7:$L$396,"Aprovado",'André Pullig'!$M$7:$M$396,">="&DATE($B$3,5,1),'André Pullig'!$M$7:$M$396,"<"&DATE($B$3,6,1))) -> 0 | G8: =IF(DATE($B$3,6,1)>=$B$4,SUMIFS('André Pullig'!$E$7:$E$396,'André Pullig'!$L$7:$L$396,"Finalizado",'André Pullig'!$M$7:$M$396,">="&DATE($B$3,6,1),'André Pullig'!$M$7:$M$396,"<"&DATE($B$3,7,1))+SUMIFS(HISTÓRICO!$F$5:$F$268,HISTÓRICO!$A$5:$A$268,"*André Pullig*",HISTÓRICO!$M$5:$M$268,"Finalizado",HISTÓRICO!$N$5:$N$268,">="&DATE($B$3,6,1),HISTÓRICO!$N$5:$N$268,"<"&DATE($B$3,7,1)),SUMIFS('André Pullig'!$E$7:$E$396,'André Pullig'!$L$7:$L$396,"Aprovado",'André Pullig'!$M$7:$M$396,">="&DATE($B$3,6,1),'André Pullig'!$M$7:$M$396,"<"&DATE($B$3,7,1))) -> 0 | H8: =IF(DATE($B$3,7,1)>=$B$4,SUMIFS('André Pullig'!$E$7:$E$396,'André Pullig'!$L$7:$L$396,"Finalizado",'André Pullig'!$M$7:$M$396,">="&DATE($B$3,7,1),'André Pullig'!$M$7:$M$396,"<"&DATE($B$3,8,1))+SUMIFS(HISTÓRICO!$F$5:$F$268,HISTÓRICO!$A$5:$A$268,"*André Pullig*",HISTÓRICO!$M$5:$M$268,"Finalizado",HISTÓRICO!$N$5:$N$268,">="&DATE($B$3,7,1),HISTÓRICO!$N$5:$N$268,"<"&DATE($B$3,8,1)),SUMIFS('André Pullig'!$E$7:$E$396,'André Pullig'!$L$7:$L$396,"Aprovado",'André Pullig'!$M$7:$M$396,">="&DATE($B$3,7,1),'André Pullig'!$M$7:$M$396,"<"&DATE($B$3,8,1))) -> 0 | I8: =IF(DATE($B$3,8,1)>=$B$4,SUMIFS('André Pullig'!$E$7:$E$396,'André Pullig'!$L$7:$L$396,"Finalizado",'André Pullig'!$M$7:$M$396,">="&DATE($B$3,8,1),'André Pullig'!$M$7:$M$396,"<"&DATE($B$3,9,1))+SUMIFS(HISTÓRICO!$F$5:$F$268,HISTÓRICO!$A$5:$A$268,"*André Pullig*",HISTÓRICO!$M$5:$M$268,"Finalizado",HISTÓRICO!$N$5:$N$268,">="&DATE($B$3,8,1),HISTÓRICO!$N$5:$N$268,"<"&DATE($B$3,9,1)),SUMIFS('André Pullig'!$E$7:$E$396,'André Pullig'!$L$7:$L$396,"Aprovado",'André Pullig'!$M$7:$M$396,">="&DATE($B$3,8,1),'André Pullig'!$M$7:$M$396,"<"&DATE($B$3,9,1))) -> 15000 | J8: =IF(DATE($B$3,9,1)>=$B$4,SUMIFS('André Pullig'!$E$7:$E$396,'André Pullig'!$L$7:$L$396,"Finalizado",'André Pullig'!$M$7:$M$396,">="&DATE($B$3,9,1),'André Pullig'!$M$7:$M$396,"<"&DATE($B$3,10,1))+SUMIFS(HISTÓRICO!$F$5:$F$268,HISTÓRICO!$A$5:$A$268,"*André Pullig*",HISTÓRICO!$M$5:$M$268,"Finalizado",HISTÓRICO!$N$5:$N$268,">="&DATE($B$3,9,1),HISTÓRICO!$N$5:$N$268,"<"&DATE($B$3,10,1)),SUMIFS('André Pullig'!$E$7:$E$396,'André Pullig'!$L$7:$L$396,"Aprovado",'André Pullig'!$M$7:$M$396,">="&DATE($B$3,9,1),'André Pullig'!$M$7:$M$396,"<"&DATE($B$3,10,1))) -> 10500 | K8: =IF(DATE($B$3,10,1)>=$B$4,SUMIFS('André Pullig'!$E$7:$E$396,'André Pullig'!$L$7:$L$396,"Finalizado",'André Pullig'!$M$7:$M$396,">="&DATE($B$3,10,1),'André Pullig'!$M$7:$M$396,"<"&DATE($B$3,11,1))+SUMIFS(HISTÓRICO!$F$5:$F$268,HISTÓRICO!$A$5:$A$268,"*André Pullig*",HISTÓRICO!$M$5:$M$268,"Finalizado",HISTÓRICO!$N$5:$N$268,">="&DATE($B$3,10,1),HISTÓRICO!$N$5:$N$268,"<"&DATE($B$3,11,1)),SUMIFS('André Pullig'!$E$7:$E$396,'André Pullig'!$L$7:$L$396,"Aprovado",'André Pullig'!$M$7:$M$396,">="&DATE($B$3,10,1),'André Pullig'!$M$7:$M$396,"<"&DATE($B$3,11,1))) -> 0 | L8: =IF(DATE($B$3,11,1)>=$B$4,SUMIFS('André Pullig'!$E$7:$E$396,'André Pullig'!$L$7:$L$396,"Finalizado",'André Pullig'!$M$7:$M$396,">="&DATE($B$3,11,1),'André Pullig'!$M$7:$M$396,"<"&DATE($B$3,12,1))+SUMIFS(HISTÓRICO!$F$5:$F$268,HISTÓRICO!$A$5:$A$268,"*André Pullig*",HISTÓRICO!$M$5:$M$268,"Finalizado",HISTÓRICO!$N$5:$N$268,">="&DATE($B$3,11,1),HISTÓRICO!$N$5:$N$268,"<"&DATE($B$3,12,1)),SUMIFS('André Pullig'!$E$7:$E$396,'André Pullig'!$L$7:$L$396,"Aprovado",'André Pullig'!$M$7:$M$396,">="&DATE($B$3,11,1),'André Pullig'!$M$7:$M$396,"<"&DATE($B$3,12,1))) -> 0 | M8: =IF(DATE($B$3,12,1)>=$B$4,SUMIFS('André Pullig'!$E$7:$E$396,'André Pullig'!$L$7:$L$396,"Finalizado",'André Pullig'!$M$7:$M$396,">="&DATE($B$3,12,1),'André Pullig'!$M$7:$M$396,"<"&DATE($B$3,13,1))+SUMIFS(HISTÓRICO!$F$5:$F$268,HISTÓRICO!$A$5:$A$268,"*André Pullig*",HISTÓRICO!$M$5:$M$268,"Finalizado",HISTÓRICO!$N$5:$N$268,">="&DATE($B$3,12,1),HISTÓRICO!$N$5:$N$268,"<"&DATE($B$3,13,1)),SUMIFS('André Pullig'!$E$7:$E$396,'André Pullig'!$L$7:$L$396,"Aprovado",'André Pullig'!$M$7:$M$396,">="&DATE($B$3,12,1),'André Pullig'!$M$7:$M$396,"<"&DATE($B$3,13,1))) -> 0 | N8: =SUM(B8:M8) -> 25500 | P8: =SUMIFS('André Pullig'!$E$7:$E$396,'André Pullig'!$L$7:$L$396,"Aprovado",'André Pullig'!$M$7:$M$396,"")+SUMIFS('André Pullig'!$E$7:$E$396,'André Pullig'!$L$7:$L$396,"Finalizado",'André Pullig'!$M$7:$M$396,"")+SUMIFS(HISTÓRICO!$F$5:$F$268,HISTÓRICO!$A$5:$A$268,"*André Pullig*",HISTÓRICO!$M$5:$M$268,"Aprovado",HISTÓRICO!$N$5:$N$268,"")+SUMIFS(HISTÓRICO!$F$5:$F$268,HISTÓRICO!$A$5:$A$268,"*André Pullig*",HISTÓRICO!$M$5:$M$268,"Finalizado",HISTÓRICO!$N$5:$N$268,"") -> 0
A9: % atingido | B9: =IF(N(B7)=0,"",B8/B7) -> 0 | C9: =IF(N(C7)=0,"",C8/C7) -> 0 | D9: =IF(N(D7)=0,"",D8/D7) -> 0 | E9: =IF(N(E7)=0,"",E8/E7) -> 0 | F9: =IF(N(F7)=0,"",F8/F7) -> 0 | G9: =IF(N(G7)=0,"",G8/G7) -> 0 | H9: =IF(N(H7)=0,"",H8/H7) -> 0 | I9: =IF(N(I7)=0,"",I8/I7) -> 0.5 | ... N9: =IF(N(N7)=0,"",N8/N7) -> 0.087328767 | O9: =IF(N(N7)=0,"sem meta",IF(N(N8)=0,"nada aprovado",IF(N8/N7>=1,"na meta",IF(N8/N7>=0.7,"perto","abaixo")))) -> abaixo
A11: BETANIA RIBEIRO
A12: Meta | N12: =SUM(B12:M12) -> 0
A13: Realizado | B13: =IF(DATE($B$3,1,1)>=$B$4,SUMIFS('Betania Ribeiro'!$E$7:$E$400,'Betania Ribeiro'!$L$7:$L$400,"Finalizado",'Betania Ribeiro'!$M$7:$M$400,">="&DATE($B$3,1,1),'Betania Ribeiro'!$M$7:$M$400,"<"&DATE($B$3,2,1))+SUMIFS(HISTÓRICO!$F$5:$F$268,HISTÓRICO!$A$5:$A$268,"*Betania Ribeiro*",HISTÓRICO!$M$5:$M$268,"Finalizado",HISTÓRICO!$N$5:$N$268,">="&DATE($B$3,1,1),HISTÓRICO!$N$5:$N$268,"<"&DATE($B$3,2,1)),SUMIFS('Betania Ribeiro'!$E$7:$E$400,'Betania Ribeiro'!$L$7:$L$400,"Aprovado",'Betania Ribeiro'!$M$7:$M$400,">="&DATE($B$3,1,1),'Betania Ribeiro'!$M$7:$M$400,"<"&DATE($B$3,2,1))) -> 0 | C13: =IF(DATE($B$3,2,1)>=$B$4,SUMIFS('Betania Ribeiro'!$E$7:$E$400,'Betania Ribeiro'!$L$7:$L$400,"Finalizado",'Betania Ribeiro'!$M$7:$M$400,">="&DATE($B$3,2,1),'Betania Ribeiro'!$M$7:$M$400,"<"&DATE($B$3,3,1))+SUMIFS(HISTÓRICO!$F$5:$F$268,HISTÓRICO!$A$5:$A$268,"*Betania Ribeiro*",HISTÓRICO!$M$5:$M$268,"Finalizado",HISTÓRICO!$N$5:$N$268,">="&DATE($B$3,2,1),HISTÓRICO!$N$5:$N$268,"<"&DATE($B$3,3,1)),SUMIFS('Betania Ribeiro'!$E$7:$E$400,'Betania Ribeiro'!$L$7:$L$400,"Aprovado",'Betania Ribeiro'!$M$7:$M$400,">="&DATE($B$3,2,1),'Betania Ribeiro'!$M$7:$M$400,"<"&DATE($B$3,3,1))) -> 0 | D13: =IF(DATE($B$3,3,1)>=$B$4,SUMIFS('Betania Ribeiro'!$E$7:$E$400,'Betania Ribeiro'!$L$7:$L$400,"Finalizado",'Betania Ribeiro'!$M$7:$M$400,">="&DATE($B$3,3,1),'Betania Ribeiro'!$M$7:$M$400,"<"&DATE($B$3,4,1))+SUMIFS(HISTÓRICO!$F$5:$F$268,HISTÓRICO!$A$5:$A$268,"*Betania Ribeiro*",HISTÓRICO!$M$5:$M$268,"Finalizado",HISTÓRICO!$N$5:$N$268,">="&DATE($B$3,3,1),HISTÓRICO!$N$5:$N$268,"<"&DATE($B$3,4,1)),SUMIFS('Betania Ribeiro'!$E$7:$E$400,'Betania Ribeiro'!$L$7:$L$400,"Aprovado",'Betania Ribeiro'!$M$7:$M$400,">="&DATE($B$3,3,1),'Betania Ribeiro'!$M$7:$M$400,"<"&DATE($B$3,4,1))) -> 0 | E13: =IF(DATE($B$3,4,1)>=$B$4,SUMIFS('Betania Ribeiro'!$E$7:$E$400,'Betania Ribeiro'!$L$7:$L$400,"Finalizado",'Betania Ribeiro'!$M$7:$M$400,">="&DATE($B$3,4,1),'Betania Ribeiro'!$M$7:$M$400,"<"&DATE($B$3,5,1))+SUMIFS(HISTÓRICO!$F$5:$F$268,HISTÓRICO!$A$5:$A$268,"*Betania Ribeiro*",HISTÓRICO!$M$5:$M$268,"Finalizado",HISTÓRICO!$N$5:$N$268,">="&DATE($B$3,4,1),HISTÓRICO!$N$5:$N$268,"<"&DATE($B$3,5,1)),SUMIFS('Betania Ribeiro'!$E$7:$E$400,'Betania Ribeiro'!$L$7:$L$400,"Aprovado",'Betania Ribeiro'!$M$7:$M$400,">="&DATE($B$3,4,1),'Betania Ribeiro'!$M$7:$M$400,"<"&DATE($B$3,5,1))) -> 0 | F13: =IF(DATE($B$3,5,1)>=$B$4,SUMIFS('Betania Ribeiro'!$E$7:$E$400,'Betania Ribeiro'!$L$7:$L$400,"Finalizado",'Betania Ribeiro'!$M$7:$M$400,">="&DATE($B$3,5,1),'Betania Ribeiro'!$M$7:$M$400,"<"&DATE($B$3,6,1))+SUMIFS(HISTÓRICO!$F$5:$F$268,HISTÓRICO!$A$5:$A$268,"*Betania Ribeiro*",HISTÓRICO!$M$5:$M$268,"Finalizado",HISTÓRICO!$N$5:$N$268,">="&DATE($B$3,5,1),HISTÓRICO!$N$5:$N$268,"<"&DATE($B$3,6,1)),SUMIFS('Betania Ribeiro'!$E$7:$E$400,'Betania Ribeiro'!$L$7:$L$400,"Aprovado",'Betania Ribeiro'!$M$7:$M$400,">="&DATE($B$3,5,1),'Betania Ribeiro'!$M$7:$M$400,"<"&DATE($B$3,6,1))) -> 0 | G13: =IF(DATE($B$3,6,1)>=$B$4,SUMIFS('Betania Ribeiro'!$E$7:$E$400,'Betania Ribeiro'!$L$7:$L$400,"Finalizado",'Betania Ribeiro'!$M$7:$M$400,">="&DATE($B$3,6,1),'Betania Ribeiro'!$M$7:$M$400,"<"&DATE($B$3,7,1))+SUMIFS(HISTÓRICO!$F$5:$F$268,HISTÓRICO!$A$5:$A$268,"*Betania Ribeiro*",HISTÓRICO!$M$5:$M$268,"Finalizado",HISTÓRICO!$N$5:$N$268,">="&DATE($B$3,6,1),HISTÓRICO!$N$5:$N$268,"<"&DATE($B$3,7,1)),SUMIFS('Betania Ribeiro'!$E$7:$E$400,'Betania Ribeiro'!$L$7:$L$400,"Aprovado",'Betania Ribeiro'!$M$7:$M$400,">="&DATE($B$3,6,1),'Betania Ribeiro'!$M$7:$M$400,"<"&DATE($B$3,7,1))) -> 0 | H13: =IF(DATE($B$3,7,1)>=$B$4,SUMIFS('Betania Ribeiro'!$E$7:$E$400,'Betania Ribeiro'!$L$7:$L$400,"Finalizado",'Betania Ribeiro'!$M$7:$M$400,">="&DATE($B$3,7,1),'Betania Ribeiro'!$M$7:$M$400,"<"&DATE($B$3,8,1))+SUMIFS(HISTÓRICO!$F$5:$F$268,HISTÓRICO!$A$5:$A$268,"*Betania Ribeiro*",HISTÓRICO!$M$5:$M$268,"Finalizado",HISTÓRICO!$N$5:$N$268,">="&DATE($B$3,7,1),HISTÓRICO!$N$5:$N$268,"<"&DATE($B$3,8,1)),SUMIFS('Betania Ribeiro'!$E$7:$E$400,'Betania Ribeiro'!$L$7:$L$400,"Aprovado",'Betania Ribeiro'!$M$7:$M$400,">="&DATE($B$3,7,1),'Betania Ribeiro'!$M$7:$M$400,"<"&DATE($B$3,8,1))) -> 0 | I13: =IF(DATE($B$3,8,1)>=$B$4,SUMIFS('Betania Ribeiro'!$E$7:$E$400,'Betania Ribeiro'!$L$7:$L$400,"Finalizado",'Betania Ribeiro'!$M$7:$M$400,">="&DATE($B$3,8,1),'Betania Ribeiro'!$M$7:$M$400,"<"&DATE($B$3,9,1))+SUMIFS(HISTÓRICO!$F$5:$F$268,HISTÓRICO!$A$5:$A$268,"*Betania Ribeiro*",HISTÓRICO!$M$5:$M$268,"Finalizado",HISTÓRICO!$N$5:$N$268,">="&DATE($B$3,8,1),HISTÓRICO!$N$5:$N$268,"<"&DATE($B$3,9,1)),SUMIFS('Betania Ribeiro'!$E$7:$E$400,'Betania Ribeiro'!$L$7:$L$400,"Aprovado",'Betania Ribeiro'!$M$7:$M$400,">="&DATE($B$3,8,1),'Betania Ribeiro'!$M$7:$M$400,"<"&DATE($B$3,9,1))) -> 0 | J13: =IF(DATE($B$3,9,1)>=$B$4,SUMIFS('Betania Ribeiro'!$E$7:$E$400,'Betania Ribeiro'!$L$7:$L$400,"Finalizado",'Betania Ribeiro'!$M$7:$M$400,">="&DATE($B$3,9,1),'Betania Ribeiro'!$M$7:$M$400,"<"&DATE($B$3,10,1))+SUMIFS(HISTÓRICO!$F$5:$F$268,HISTÓRICO!$A$5:$A$268,"*Betania Ribeiro*",HISTÓRICO!$M$5:$M$268,"Finalizado",HISTÓRICO!$N$5:$N$268,">="&DATE($B$3,9,1),HISTÓRICO!$N$5:$N$268,"<"&DATE($B$3,10,1)),SUMIFS('Betania Ribeiro'!$E$7:$E$400,'Betania Ribeiro'!$L$7:$L$400,"Aprovado",'Betania Ribeiro'!$M$7:$M$400,">="&DATE($B$3,9,1),'Betania Ribeiro'!$M$7:$M$400,"<"&DATE($B$3,10,1))) -> 0 | K13: =IF(DATE($B$3,10,1)>=$B$4,SUMIFS('Betania Ribeiro'!$E$7:$E$400,'Betania Ribeiro'!$L$7:$L$400,"Finalizado",'Betania Ribeiro'!$M$7:$M$400,">="&DATE($B$3,10,1),'Betania Ribeiro'!$M$7:$M$400,"<"&DATE($B$3,11,1))+SUMIFS(HISTÓRICO!$F$5:$F$268,HISTÓRICO!$A$5:$A$268,"*Betania Ribeiro*",HISTÓRICO!$M$5:$M$268,"Finalizado",HISTÓRICO!$N$5:$N$268,">="&DATE($B$3,10,1),HISTÓRICO!$N$5:$N$268,"<"&DATE($B$3,11,1)),SUMIFS('Betania Ribeiro'!$E$7:$E$400,'Betania Ribeiro'!$L$7:$L$400,"Aprovado",'Betania Ribeiro'!$M$7:$M$400,">="&DATE($B$3,10,1),'Betania Ribeiro'!$M$7:$M$400,"<"&DATE($B$3,11,1))) -> 0 | L13: =IF(DATE($B$3,11,1)>=$B$4,SUMIFS('Betania Ribeiro'!$E$7:$E$400,'Betania Ribeiro'!$L$7:$L$400,"Finalizado",'Betania Ribeiro'!$M$7:$M$400,">="&DATE($B$3,11,1),'Betania Ribeiro'!$M$7:$M$400,"<"&DATE($B$3,12,1))+SUMIFS(HISTÓRICO!$F$5:$F$268,HISTÓRICO!$A$5:$A$268,"*Betania Ribeiro*",HISTÓRICO!$M$5:$M$268,"Finalizado",HISTÓRICO!$N$5:$N$268,">="&DATE($B$3,11,1),HISTÓRICO!$N$5:$N$268,"<"&DATE($B$3,12,1)),SUMIFS('Betania Ribeiro'!$E$7:$E$400,'Betania Ribeiro'!$L$7:$L$400,"Aprovado",'Betania Ribeiro'!$M$7:$M$400,">="&DATE($B$3,11,1),'Betania Ribeiro'!$M$7:$M$400,"<"&DATE($B$3,12,1))) -> 0 | M13: =IF(DATE($B$3,12,1)>=$B$4,SUMIFS('Betania Ribeiro'!$E$7:$E$400,'Betania Ribeiro'!$L$7:$L$400,"Finalizado",'Betania Ribeiro'!$M$7:$M$400,">="&DATE($B$3,12,1),'Betania Ribeiro'!$M$7:$M$400,"<"&DATE($B$3,13,1))+SUMIFS(HISTÓRICO!$F$5:$F$268,HISTÓRICO!$A$5:$A$268,"*Betania Ribeiro*",HISTÓRICO!$M$5:$M$268,"Finalizado",HISTÓRICO!$N$5:$N$268,">="&DATE($B$3,12,1),HISTÓRICO!$N$5:$N$268,"<"&DATE($B$3,13,1)),SUMIFS('Betania Ribeiro'!$E$7:$E$400,'Betania Ribeiro'!$L$7:$L$400,"Aprovado",'Betania Ribeiro'!$M$7:$M$400,">="&DATE($B$3,12,1),'Betania Ribeiro'!$M$7:$M$400,"<"&DATE($B$3,13,1))) -> 0 | N13: =SUM(B13:M13) -> 0 | P13: =SUMIFS('Betania Ribeiro'!$E$7:$E$400,'Betania Ribeiro'!$L$7:$L$400,"Aprovado",'Betania Ribeiro'!$M$7:$M$400,"")+SUMIFS('Betania Ribeiro'!$E$7:$E$400,'Betania Ribeiro'!$L$7:$L$400,"Finalizado",'Betania Ribeiro'!$M$7:$M$400,"")+SUMIFS(HISTÓRICO!$F$5:$F$268,HISTÓRICO!$A$5:$A$268,"*Betania Ribeiro*",HISTÓRICO!$M$5:$M$268,"Aprovado",HISTÓRICO!$N$5:$N$268,"")+SUMIFS(HISTÓRICO!$F$5:$F$268,HISTÓRICO!$A$5:$A$268,"*Betania Ribeiro*",HISTÓRICO!$M$5:$M$268,"Finalizado",HISTÓRICO!$N$5:$N$268,"") -> 0
A14: % atingido | B14: =IF(N(B12)=0,"",B13/B12) | C14: =IF(N(C12)=0,"",C13/C12) | D14: =IF(N(D12)=0,"",D13/D12) | E14: =IF(N(E12)=0,"",E13/E12) | F14: =IF(N(F12)=0,"",F13/F12) | G14: =IF(N(G12)=0,"",G13/G12) | H14: =IF(N(H12)=0,"",H13/H12) | I14: =IF(N(I12)=0,"",I13/I12) | ... N14: =IF(N(N12)=0,"",N13/N12) | O14: =IF(N(N12)=0,"sem meta",IF(N(N13)=0,"nada aprovado",IF(N13/N12>=1,"na meta",IF(N13/N12>=0.7,"perto","abaixo")))) -> sem meta
A16: JOÃO PULLIG
A17: Meta | B17: 20000 | C17: 23000 | D17: 26000 | E17: 30000 | F17: 25000 | G17: 23000 | H17: 26000 | I17: 30000 | J17: 26000 | K17: 25000 | L17: 20000 | M17: 18000 | N17: =SUM(B17:M17) -> 292000
A18: Realizado | B18: =IF(DATE($B$3,1,1)>=$B$4,SUMIFS('João Pullig'!$E$7:$E$385,'João Pullig'!$L$7:$L$385,"Finalizado",'João Pullig'!$M$7:$M$385,">="&DATE($B$3,1,1),'João Pullig'!$M$7:$M$385,"<"&DATE($B$3,2,1))+SUMIFS(HISTÓRICO!$F$5:$F$268,HISTÓRICO!$A$5:$A$268,"*João Pullig*",HISTÓRICO!$M$5:$M$268,"Finalizado",HISTÓRICO!$N$5:$N$268,">="&DATE($B$3,1,1),HISTÓRICO!$N$5:$N$268,"<"&DATE($B$3,2,1)),SUMIFS('João Pullig'!$E$7:$E$385,'João Pullig'!$L$7:$L$385,"Aprovado",'João Pullig'!$M$7:$M$385,">="&DATE($B$3,1,1),'João Pullig'!$M$7:$M$385,"<"&DATE($B$3,2,1))) -> 0 | C18: =IF(DATE($B$3,2,1)>=$B$4,SUMIFS('João Pullig'!$E$7:$E$385,'João Pullig'!$L$7:$L$385,"Finalizado",'João Pullig'!$M$7:$M$385,">="&DATE($B$3,2,1),'João Pullig'!$M$7:$M$385,"<"&DATE($B$3,3,1))+SUMIFS(HISTÓRICO!$F$5:$F$268,HISTÓRICO!$A$5:$A$268,"*João Pullig*",HISTÓRICO!$M$5:$M$268,"Finalizado",HISTÓRICO!$N$5:$N$268,">="&DATE($B$3,2,1),HISTÓRICO!$N$5:$N$268,"<"&DATE($B$3,3,1)),SUMIFS('João Pullig'!$E$7:$E$385,'João Pullig'!$L$7:$L$385,"Aprovado",'João Pullig'!$M$7:$M$385,">="&DATE($B$3,2,1),'João Pullig'!$M$7:$M$385,"<"&DATE($B$3,3,1))) -> 0 | D18: =IF(DATE($B$3,3,1)>=$B$4,SUMIFS('João Pullig'!$E$7:$E$385,'João Pullig'!$L$7:$L$385,"Finalizado",'João Pullig'!$M$7:$M$385,">="&DATE($B$3,3,1),'João Pullig'!$M$7:$M$385,"<"&DATE($B$3,4,1))+SUMIFS(HISTÓRICO!$F$5:$F$268,HISTÓRICO!$A$5:$A$268,"*João Pullig*",HISTÓRICO!$M$5:$M$268,"Finalizado",HISTÓRICO!$N$5:$N$268,">="&DATE($B$3,3,1),HISTÓRICO!$N$5:$N$268,"<"&DATE($B$3,4,1)),SUMIFS('João Pullig'!$E$7:$E$385,'João Pullig'!$L$7:$L$385,"Aprovado",'João Pullig'!$M$7:$M$385,">="&DATE($B$3,3,1),'João Pullig'!$M$7:$M$385,"<"&DATE($B$3,4,1))) -> 0 | E18: =IF(DATE($B$3,4,1)>=$B$4,SUMIFS('João Pullig'!$E$7:$E$385,'João Pullig'!$L$7:$L$385,"Finalizado",'João Pullig'!$M$7:$M$385,">="&DATE($B$3,4,1),'João Pullig'!$M$7:$M$385,"<"&DATE($B$3,5,1))+SUMIFS(HISTÓRICO!$F$5:$F$268,HISTÓRICO!$A$5:$A$268,"*João Pullig*",HISTÓRICO!$M$5:$M$268,"Finalizado",HISTÓRICO!$N$5:$N$268,">="&DATE($B$3,4,1),HISTÓRICO!$N$5:$N$268,"<"&DATE($B$3,5,1)),SUMIFS('João Pullig'!$E$7:$E$385,'João Pullig'!$L$7:$L$385,"Aprovado",'João Pullig'!$M$7:$M$385,">="&DATE($B$3,4,1),'João Pullig'!$M$7:$M$385,"<"&DATE($B$3,5,1))) -> 0 | F18: =IF(DATE($B$3,5,1)>=$B$4,SUMIFS('João Pullig'!$E$7:$E$385,'João Pullig'!$L$7:$L$385,"Finalizado",'João Pullig'!$M$7:$M$385,">="&DATE($B$3,5,1),'João Pullig'!$M$7:$M$385,"<"&DATE($B$3,6,1))+SUMIFS(HISTÓRICO!$F$5:$F$268,HISTÓRICO!$A$5:$A$268,"*João Pullig*",HISTÓRICO!$M$5:$M$268,"Finalizado",HISTÓRICO!$N$5:$N$268,">="&DATE($B$3,5,1),HISTÓRICO!$N$5:$N$268,"<"&DATE($B$3,6,1)),SUMIFS('João Pullig'!$E$7:$E$385,'João Pullig'!$L$7:$L$385,"Aprovado",'João Pullig'!$M$7:$M$385,">="&DATE($B$3,5,1),'João Pullig'!$M$7:$M$385,"<"&DATE($B$3,6,1))) -> 0 | G18: =IF(DATE($B$3,6,1)>=$B$4,SUMIFS('João Pullig'!$E$7:$E$385,'João Pullig'!$L$7:$L$385,"Finalizado",'João Pullig'!$M$7:$M$385,">="&DATE($B$3,6,1),'João Pullig'!$M$7:$M$385,"<"&DATE($B$3,7,1))+SUMIFS(HISTÓRICO!$F$5:$F$268,HISTÓRICO!$A$5:$A$268,"*João Pullig*",HISTÓRICO!$M$5:$M$268,"Finalizado",HISTÓRICO!$N$5:$N$268,">="&DATE($B$3,6,1),HISTÓRICO!$N$5:$N$268,"<"&DATE($B$3,7,1)),SUMIFS('João Pullig'!$E$7:$E$385,'João Pullig'!$L$7:$L$385,"Aprovado",'João Pullig'!$M$7:$M$385,">="&DATE($B$3,6,1),'João Pullig'!$M$7:$M$385,"<"&DATE($B$3,7,1))) -> 0 | H18: =IF(DATE($B$3,7,1)>=$B$4,SUMIFS('João Pullig'!$E$7:$E$385,'João Pullig'!$L$7:$L$385,"Finalizado",'João Pullig'!$M$7:$M$385,">="&DATE($B$3,7,1),'João Pullig'!$M$7:$M$385,"<"&DATE($B$3,8,1))+SUMIFS(HISTÓRICO!$F$5:$F$268,HISTÓRICO!$A$5:$A$268,"*João Pullig*",HISTÓRICO!$M$5:$M$268,"Finalizado",HISTÓRICO!$N$5:$N$268,">="&DATE($B$3,7,1),HISTÓRICO!$N$5:$N$268,"<"&DATE($B$3,8,1)),SUMIFS('João Pullig'!$E$7:$E$385,'João Pullig'!$L$7:$L$385,"Aprovado",'João Pullig'!$M$7:$M$385,">="&DATE($B$3,7,1),'João Pullig'!$M$7:$M$385,"<"&DATE($B$3,8,1))) -> 20000 | I18: 6000 | J18: =IF(DATE($B$3,9,1)>=$B$4,SUMIFS('João Pullig'!$E$7:$E$385,'João Pullig'!$L$7:$L$385,"Finalizado",'João Pullig'!$M$7:$M$385,">="&DATE($B$3,9,1),'João Pullig'!$M$7:$M$385,"<"&DATE($B$3,10,1))+SUMIFS(HISTÓRICO!$F$5:$F$268,HISTÓRICO!$A$5:$A$268,"*João Pullig*",HISTÓRICO!$M$5:$M$268,"Finalizado",HISTÓRICO!$N$5:$N$268,">="&DATE($B$3,9,1),HISTÓRICO!$N$5:$N$268,"<"&DATE($B$3,10,1)),SUMIFS('João Pullig'!$E$7:$E$385,'João Pullig'!$L$7:$L$385,"Aprovado",'João Pullig'!$M$7:$M$385,">="&DATE($B$3,9,1),'João Pullig'!$M$7:$M$385,"<"&DATE($B$3,10,1))) -> 6000 | K18: =IF(DATE($B$3,10,1)>=$B$4,SUMIFS('João Pullig'!$E$7:$E$385,'João Pullig'!$L$7:$L$385,"Finalizado",'João Pullig'!$M$7:$M$385,">="&DATE($B$3,10,1),'João Pullig'!$M$7:$M$385,"<"&DATE($B$3,11,1))+SUMIFS(HISTÓRICO!$F$5:$F$268,HISTÓRICO!$A$5:$A$268,"*João Pullig*",HISTÓRICO!$M$5:$M$268,"Finalizado",HISTÓRICO!$N$5:$N$268,">="&DATE($B$3,10,1),HISTÓRICO!$N$5:$N$268,"<"&DATE($B$3,11,1)),SUMIFS('João Pullig'!$E$7:$E$385,'João Pullig'!$L$7:$L$385,"Aprovado",'João Pullig'!$M$7:$M$385,">="&DATE($B$3,10,1),'João Pullig'!$M$7:$M$385,"<"&DATE($B$3,11,1))) -> 0 | L18: =IF(DATE($B$3,11,1)>=$B$4,SUMIFS('João Pullig'!$E$7:$E$385,'João Pullig'!$L$7:$L$385,"Finalizado",'João Pullig'!$M$7:$M$385,">="&DATE($B$3,11,1),'João Pullig'!$M$7:$M$385,"<"&DATE($B$3,12,1))+SUMIFS(HISTÓRICO!$F$5:$F$268,HISTÓRICO!$A$5:$A$268,"*João Pullig*",HISTÓRICO!$M$5:$M$268,"Finalizado",HISTÓRICO!$N$5:$N$268,">="&DATE($B$3,11,1),HISTÓRICO!$N$5:$N$268,"<"&DATE($B$3,12,1)),SUMIFS('João Pullig'!$E$7:$E$385,'João Pullig'!$L$7:$L$385,"Aprovado",'João Pullig'!$M$7:$M$385,">="&DATE($B$3,11,1),'João Pullig'!$M$7:$M$385,"<"&DATE($B$3,12,1))) -> 0 | M18: =IF(DATE($B$3,12,1)>=$B$4,SUMIFS('João Pullig'!$E$7:$E$385,'João Pullig'!$L$7:$L$385,"Finalizado",'João Pullig'!$M$7:$M$385,">="&DATE($B$3,12,1),'João Pullig'!$M$7:$M$385,"<"&DATE($B$3,13,1))+SUMIFS(HISTÓRICO!$F$5:$F$268,HISTÓRICO!$A$5:$A$268,"*João Pullig*",HISTÓRICO!$M$5:$M$268,"Finalizado",HISTÓRICO!$N$5:$N$268,">="&DATE($B$3,12,1),HISTÓRICO!$N$5:$N$268,"<"&DATE($B$3,13,1)),SUMIFS('João Pullig'!$E$7:$E$385,'João Pullig'!$L$7:$L$385,"Aprovado",'João Pullig'!$M$7:$M$385,">="&DATE($B$3,12,1),'João Pullig'!$M$7:$M$385,"<"&DATE($B$3,13,1))) -> 0 | N18: =SUM(B18:M18) -> 32000 | P18: =SUMIFS('João Pullig'!$E$7:$E$385,'João Pullig'!$L$7:$L$385,"Aprovado",'João Pullig'!$M$7:$M$385,"")+SUMIFS('João Pullig'!$E$7:$E$385,'João Pullig'!$L$7:$L$385,"Finalizado",'João Pullig'!$M$7:$M$385,"")+SUMIFS(HISTÓRICO!$F$5:$F$268,HISTÓRICO!$A$5:$A$268,"*João Pullig*",HISTÓRICO!$M$5:$M$268,"Aprovado",HISTÓRICO!$N$5:$N$268,"")+SUMIFS(HISTÓRICO!$F$5:$F$268,HISTÓRICO!$A$5:$A$268,"*João Pullig*",HISTÓRICO!$M$5:$M$268,"Finalizado",HISTÓRICO!$N$5:$N$268,"") -> 65000
A19: % atingido | B19: =IF(N(B17)=0,"",B18/B17) -> 0 | C19: =IF(N(C17)=0,"",C18/C17) -> 0 | D19: =IF(N(D17)=0,"",D18/D17) -> 0 | E19: =IF(N(E17)=0,"",E18/E17) -> 0 | F19: =IF(N(F17)=0,"",F18/F17) -> 0 | G19: =IF(N(G17)=0,"",G18/G17) -> 0 | H19: =IF(N(H17)=0,"",H18/H17) -> 0.76923077 | I19: =IF(N(I17)=0,"",I18/I17) -> 0.2 | ... N19: =IF(N(N17)=0,"",N18/N17) -> 0.10958904 | O19: =IF(N(N17)=0,"sem meta",IF(N(N18)=0,"nada aprovado",IF(N18/N17>=1,"na meta",IF(N18/N17>=0.7,"perto","abaixo")))) -> abaixo
A21: KAIO DIAS
A22: Meta | B22: 20000 | C22: 23000 | D22: 26000 | E22: 30000 | F22: 25000 | G22: 23000 | H22: 26000 | I22: 30000 | J22: 26000 | K22: 25000 | L22: 20000 | M22: 18000 | N22: =SUM(B22:M22) -> 292000
A23: Realizado | B23: 12240 | C23: 0 | D23: 12500 | E23: 10900 | F23: 1906 | G23: 8000 | H23: 7042.58 | I23: =IF(DATE($B$3,8,1)>=$B$4,SUMIFS('Kaio Dias'!$E$7:$E$374,'Kaio Dias'!$L$7:$L$374,"Finalizado",'Kaio Dias'!$M$7:$M$374,">="&DATE($B$3,8,1),'Kaio Dias'!$M$7:$M$374,"<"&DATE($B$3,9,1))+SUMIFS(HISTÓRICO!$F$5:$F$268,HISTÓRICO!$A$5:$A$268,"*Kaio Dias*",HISTÓRICO!$M$5:$M$268,"Finalizado",HISTÓRICO!$N$5:$N$268,">="&DATE($B$3,8,1),HISTÓRICO!$N$5:$N$268,"<"&DATE($B$3,9,1)),SUMIFS('Kaio Dias'!$E$7:$E$374,'Kaio Dias'!$L$7:$L$374,"Aprovado",'Kaio Dias'!$M$7:$M$374,">="&DATE($B$3,8,1),'Kaio Dias'!$M$7:$M$374,"<"&DATE($B$3,9,1))) -> 37204.5 | J23: =IF(DATE($B$3,9,1)>=$B$4,SUMIFS('Kaio Dias'!$E$7:$E$374,'Kaio Dias'!$L$7:$L$374,"Finalizado",'Kaio Dias'!$M$7:$M$374,">="&DATE($B$3,9,1),'Kaio Dias'!$M$7:$M$374,"<"&DATE($B$3,10,1))+SUMIFS(HISTÓRICO!$F$5:$F$268,HISTÓRICO!$A$5:$A$268,"*Kaio Dias*",HISTÓRICO!$M$5:$M$268,"Finalizado",HISTÓRICO!$N$5:$N$268,">="&DATE($B$3,9,1),HISTÓRICO!$N$5:$N$268,"<"&DATE($B$3,10,1)),SUMIFS('Kaio Dias'!$E$7:$E$374,'Kaio Dias'!$L$7:$L$374,"Aprovado",'Kaio Dias'!$M$7:$M$374,">="&DATE($B$3,9,1),'Kaio Dias'!$M$7:$M$374,"<"&DATE($B$3,10,1))) -> 0 | K23: =IF(DATE($B$3,10,1)>=$B$4,SUMIFS('Kaio Dias'!$E$7:$E$374,'Kaio Dias'!$L$7:$L$374,"Finalizado",'Kaio Dias'!$M$7:$M$374,">="&DATE($B$3,10,1),'Kaio Dias'!$M$7:$M$374,"<"&DATE($B$3,11,1))+SUMIFS(HISTÓRICO!$F$5:$F$268,HISTÓRICO!$A$5:$A$268,"*Kaio Dias*",HISTÓRICO!$M$5:$M$268,"Finalizado",HISTÓRICO!$N$5:$N$268,">="&DATE($B$3,10,1),HISTÓRICO!$N$5:$N$268,"<"&DATE($B$3,11,1)),SUMIFS('Kaio Dias'!$E$7:$E$374,'Kaio Dias'!$L$7:$L$374,"Aprovado",'Kaio Dias'!$M$7:$M$374,">="&DATE($B$3,10,1),'Kaio Dias'!$M$7:$M$374,"<"&DATE($B$3,11,1))) -> 0 | L23: =IF(DATE($B$3,11,1)>=$B$4,SUMIFS('Kaio Dias'!$E$7:$E$374,'Kaio Dias'!$L$7:$L$374,"Finalizado",'Kaio Dias'!$M$7:$M$374,">="&DATE($B$3,11,1),'Kaio Dias'!$M$7:$M$374,"<"&DATE($B$3,12,1))+SUMIFS(HISTÓRICO!$F$5:$F$268,HISTÓRICO!$A$5:$A$268,"*Kaio Dias*",HISTÓRICO!$M$5:$M$268,"Finalizado",HISTÓRICO!$N$5:$N$268,">="&DATE($B$3,11,1),HISTÓRICO!$N$5:$N$268,"<"&DATE($B$3,12,1)),SUMIFS('Kaio Dias'!$E$7:$E$374,'Kaio Dias'!$L$7:$L$374,"Aprovado",'Kaio Dias'!$M$7:$M$374,">="&DATE($B$3,11,1),'Kaio Dias'!$M$7:$M$374,"<"&DATE($B$3,12,1))) -> 0 | M23: =IF(DATE($B$3,12,1)>=$B$4,SUMIFS('Kaio Dias'!$E$7:$E$374,'Kaio Dias'!$L$7:$L$374,"Finalizado",'Kaio Dias'!$M$7:$M$374,">="&DATE($B$3,12,1),'Kaio Dias'!$M$7:$M$374,"<"&DATE($B$3,13,1))+SUMIFS(HISTÓRICO!$F$5:$F$268,HISTÓRICO!$A$5:$A$268,"*Kaio Dias*",HISTÓRICO!$M$5:$M$268,"Finalizado",HISTÓRICO!$N$5:$N$268,">="&DATE($B$3,12,1),HISTÓRICO!$N$5:$N$268,"<"&DATE($B$3,13,1)),SUMIFS('Kaio Dias'!$E$7:$E$374,'Kaio Dias'!$L$7:$L$374,"Aprovado",'Kaio Dias'!$M$7:$M$374,">="&DATE($B$3,12,1),'Kaio Dias'!$M$7:$M$374,"<"&DATE($B$3,13,1))) -> 0 | N23: =SUM(B23:M23) -> 89793.08 | P23: =SUMIFS('Kaio Dias'!$E$7:$E$374,'Kaio Dias'!$L$7:$L$374,"Aprovado",'Kaio Dias'!$M$7:$M$374,"")+SUMIFS('Kaio Dias'!$E$7:$E$374,'Kaio Dias'!$L$7:$L$374,"Finalizado",'Kaio Dias'!$M$7:$M$374,"")+SUMIFS(HISTÓRICO!$F$5:$F$268,HISTÓRICO!$A$5:$A$268,"*Kaio Dias*",HISTÓRICO!$M$5:$M$268,"Aprovado",HISTÓRICO!$N$5:$N$268,"")+SUMIFS(HISTÓRICO!$F$5:$F$268,HISTÓRICO!$A$5:$A$268,"*Kaio Dias*",HISTÓRICO!$M$5:$M$268,"Finalizado",HISTÓRICO!$N$5:$N$268,"") -> 19431.05
A24: % atingido | B24: =IF(N(B22)=0,"",B23/B22) -> 0.612 | C24: =IF(N(C22)=0,"",C23/C22) -> 0 | D24: =IF(N(D22)=0,"",D23/D22) -> 0.48076923 | E24: =IF(N(E22)=0,"",E23/E22) -> 0.36333333 | F24: =IF(N(F22)=0,"",F23/F22) -> 0.07624 | G24: =IF(N(G22)=0,"",G23/G22) -> 0.34782609 | H24: =IF(N(H22)=0,"",H23/H22) -> 0.27086846 | I24: =IF(N(I22)=0,"",I23/I22) -> 1.24015 | ... N24: =IF(N(N22)=0,"",N23/N22) -> 0.30751055 | O24: =IF(N(N22)=0,"sem meta",IF(N(N23)=0,"nada aprovado",IF(N23/N22>=1,"na meta",IF(N23/N22>=0.7,"perto","abaixo")))) -> abaixo
A26: PABLO RUAN
A27: Meta | B27: 12000 | C27: 15000 | D27: 18000 | E27: 21000 | F27: 18000 | G27: 12000 | H27: 20000 | I27: 18000 | J27: 21000 | K27: 15000 | L27: 12000 | M27: 10000 | N27: =SUM(B27:M27) -> 192000
A28: Realizado | B28: 0 | C28: 2000 | D28: 14000 | E28: 6200.89 | F28: 3531 | G28: 5000 | H28: 6000 | I28: =IF(DATE($B$3,8,1)>=$B$4,SUMIFS('Pablo Ruan'!$E$7:$E$382,'Pablo Ruan'!$L$7:$L$382,"Finalizado",'Pablo Ruan'!$M$7:$M$382,">="&DATE($B$3,8,1),'Pablo Ruan'!$M$7:$M$382,"<"&DATE($B$3,9,1))+SUMIFS(HISTÓRICO!$F$5:$F$268,HISTÓRICO!$A$5:$A$268,"*Pablo Ruan*",HISTÓRICO!$M$5:$M$268,"Finalizado",HISTÓRICO!$N$5:$N$268,">="&DATE($B$3,8,1),HISTÓRICO!$N$5:$N$268,"<"&DATE($B$3,9,1)),SUMIFS('Pablo Ruan'!$E$7:$E$382,'Pablo Ruan'!$L$7:$L$382,"Aprovado",'Pablo Ruan'!$M$7:$M$382,">="&DATE($B$3,8,1),'Pablo Ruan'!$M$7:$M$382,"<"&DATE($B$3,9,1))) -> 0 | J28: =IF(DATE($B$3,9,1)>=$B$4,SUMIFS('Pablo Ruan'!$E$7:$E$382,'Pablo Ruan'!$L$7:$L$382,"Finalizado",'Pablo Ruan'!$M$7:$M$382,">="&DATE($B$3,9,1),'Pablo Ruan'!$M$7:$M$382,"<"&DATE($B$3,10,1))+SUMIFS(HISTÓRICO!$F$5:$F$268,HISTÓRICO!$A$5:$A$268,"*Pablo Ruan*",HISTÓRICO!$M$5:$M$268,"Finalizado",HISTÓRICO!$N$5:$N$268,">="&DATE($B$3,9,1),HISTÓRICO!$N$5:$N$268,"<"&DATE($B$3,10,1)),SUMIFS('Pablo Ruan'!$E$7:$E$382,'Pablo Ruan'!$L$7:$L$382,"Aprovado",'Pablo Ruan'!$M$7:$M$382,">="&DATE($B$3,9,1),'Pablo Ruan'!$M$7:$M$382,"<"&DATE($B$3,10,1))) -> 0 | K28: =IF(DATE($B$3,10,1)>=$B$4,SUMIFS('Pablo Ruan'!$E$7:$E$382,'Pablo Ruan'!$L$7:$L$382,"Finalizado",'Pablo Ruan'!$M$7:$M$382,">="&DATE($B$3,10,1),'Pablo Ruan'!$M$7:$M$382,"<"&DATE($B$3,11,1))+SUMIFS(HISTÓRICO!$F$5:$F$268,HISTÓRICO!$A$5:$A$268,"*Pablo Ruan*",HISTÓRICO!$M$5:$M$268,"Finalizado",HISTÓRICO!$N$5:$N$268,">="&DATE($B$3,10,1),HISTÓRICO!$N$5:$N$268,"<"&DATE($B$3,11,1)),SUMIFS('Pablo Ruan'!$E$7:$E$382,'Pablo Ruan'!$L$7:$L$382,"Aprovado",'Pablo Ruan'!$M$7:$M$382,">="&DATE($B$3,10,1),'Pablo Ruan'!$M$7:$M$382,"<"&DATE($B$3,11,1))) -> 0 | L28: =IF(DATE($B$3,11,1)>=$B$4,SUMIFS('Pablo Ruan'!$E$7:$E$382,'Pablo Ruan'!$L$7:$L$382,"Finalizado",'Pablo Ruan'!$M$7:$M$382,">="&DATE($B$3,11,1),'Pablo Ruan'!$M$7:$M$382,"<"&DATE($B$3,12,1))+SUMIFS(HISTÓRICO!$F$5:$F$268,HISTÓRICO!$A$5:$A$268,"*Pablo Ruan*",HISTÓRICO!$M$5:$M$268,"Finalizado",HISTÓRICO!$N$5:$N$268,">="&DATE($B$3,11,1),HISTÓRICO!$N$5:$N$268,"<"&DATE($B$3,12,1)),SUMIFS('Pablo Ruan'!$E$7:$E$382,'Pablo Ruan'!$L$7:$L$382,"Aprovado",'Pablo Ruan'!$M$7:$M$382,">="&DATE($B$3,11,1),'Pablo Ruan'!$M$7:$M$382,"<"&DATE($B$3,12,1))) -> 0 | M28: =IF(DATE($B$3,12,1)>=$B$4,SUMIFS('Pablo Ruan'!$E$7:$E$382,'Pablo Ruan'!$L$7:$L$382,"Finalizado",'Pablo Ruan'!$M$7:$M$382,">="&DATE($B$3,12,1),'Pablo Ruan'!$M$7:$M$382,"<"&DATE($B$3,13,1))+SUMIFS(HISTÓRICO!$F$5:$F$268,HISTÓRICO!$A$5:$A$268,"*Pablo Ruan*",HISTÓRICO!$M$5:$M$268,"Finalizado",HISTÓRICO!$N$5:$N$268,">="&DATE($B$3,12,1),HISTÓRICO!$N$5:$N$268,"<"&DATE($B$3,13,1)),SUMIFS('Pablo Ruan'!$E$7:$E$382,'Pablo Ruan'!$L$7:$L$382,"Aprovado",'Pablo Ruan'!$M$7:$M$382,">="&DATE($B$3,12,1),'Pablo Ruan'!$M$7:$M$382,"<"&DATE($B$3,13,1))) -> 0 | N28: =SUM(B28:M28) -> 36731.89 | P28: =SUMIFS('Pablo Ruan'!$E$7:$E$382,'Pablo Ruan'!$L$7:$L$382,"Aprovado",'Pablo Ruan'!$M$7:$M$382,"")+SUMIFS('Pablo Ruan'!$E$7:$E$382,'Pablo Ruan'!$L$7:$L$382,"Finalizado",'Pablo Ruan'!$M$7:$M$382,"")+SUMIFS(HISTÓRICO!$F$5:$F$268,HISTÓRICO!$A$5:$A$268,"*Pablo Ruan*",HISTÓRICO!$M$5:$M$268,"Aprovado",HISTÓRICO!$N$5:$N$268,"")+SUMIFS(HISTÓRICO!$F$5:$F$268,HISTÓRICO!$A$5:$A$268,"*Pablo Ruan*",HISTÓRICO!$M$5:$M$268,"Finalizado",HISTÓRICO!$N$5:$N$268,"") -> 63500
A29: % atingido | B29: =IF(N(B27)=0,"",B28/B27) -> 0 | C29: =IF(N(C27)=0,"",C28/C27) -> 0.13333333 | D29: =IF(N(D27)=0,"",D28/D27) -> 0.77777778 | E29: =IF(N(E27)=0,"",E28/E27) -> 0.29528048 | F29: =IF(N(F27)=0,"",F28/F27) -> 0.19616667 | G29: =IF(N(G27)=0,"",G28/G27) -> 0.41666667 | H29: =IF(N(H27)=0,"",H28/H27) -> 0.3 | I29: =IF(N(I27)=0,"",I28/I27) -> 0 | ... N29: =IF(N(N27)=0,"",N28/N27) -> 0.19131193 | O29: =IF(N(N27)=0,"sem meta",IF(N(N28)=0,"nada aprovado",IF(N28/N27>=1,"na meta",IF(N28/N27>=0.7,"perto","abaixo")))) -> abaixo
A31: RAFAEL NEDINO
A32: Meta | B32: 20000 | C32: 23000 | D32: 26000 | E32: 30000 | F32: 25000 | G32: 23000 | H32: 26000 | I32: 30000 | J32: 26000 | K32: 25000 | L32: 20000 | M32: 18000 | N32: =SUM(B32:M32) -> 292000
A33: Realizado
A34: % atingido
A36: TOTAL PJC — Meta | B36: =B7+B12+B17+B22+B27+B32 -> 92000 | C36: =C7+C12+C17+C22+C27+C32 -> 107000 | D36: =D7+D12+D17+D22+D27+D32 -> 122000 | E36: =E7+E12+E17+E22+E27+E32 -> 141000 | F36: =F7+F12+F17+F22+F27+F32 -> 118000 | G36: =G7+G12+G17+G22+G27+G32 -> 104000 | H36: =H7+H12+H17+H22+H27+H32 -> 124000 | I36: =I7+I12+I17+I22+I27+I32 -> 138000 | ... N36: =N7+N12+N17+N22+N27+N32 -> 1360000
A37: TOTAL PJC — Realizado | B37: =B8+B13+B18+B23+B28+B33 -> 12240 | C37: =C8+C13+C18+C23+C28+C33 -> 2000 | D37: =D8+D13+D18+D23+D28+D33 -> 26500 | E37: =E8+E13+E18+E23+E28+E33 -> 17100.89 | F37: =F8+F13+F18+F23+F28+F33 -> 5437 | G37: =G8+G13+G18+G23+G28+G33 -> 13000 | H37: =H8+H13+H18+H23+H28+H33 -> 33042.58 | I37: =I8+I13+I18+I23+I28+I33 -> 58204.5 | ... N37: =N8+N13+N18+N23+N28+N33 -> 184024.97
A39: Como funciona
A40: • META (fundo azul) é o único campo digitado. Preencha em azul quem ainda não tem meta.
A41: • REALIZADO (fundo verde) é fórmula: soma a Receita pelo mês da coluna DATA FECHAMENTO. Até junho/2026 conta só o status Aprovado da aba do gerente. De julho/2026 em diante conta o status Finalizado, na aba do gerente e também na aba HISTÓRICO. Não escreva nessas células.
A42: • Marcou uma operação como Finalizado? O realizado do mês muda na hora.
A43: • SEM DATA DE FECHAMENTO mostra receita Aprovada ou Finalizada sem data preenchida, na aba do gerente e no HISTÓRICO — ela não entra em mês nenhum. Se aparecer valor aí, preencha a DATA FECHAMENTO.
A44: • Verde = na meta · Amarelo = 70% a 99% · Vermelho = abaixo de 70%.
A45: • Reprovados continuam fora do realizado: do HISTÓRICO só entram as linhas com status Finalizado.
A46: • KAIO DIAS (janeiro a junho) e PABLO RUAN (janeiro a julho) têm o realizado digitado à mão, vindo do controle anterior. Essas células não são fórmula — não apague.

Sheet HISTÓRICO
A1: HISTÓRICO CONSOLIDADO
A2: Operações reprovadas e as vindas das abas antigas (KAIO1 e PABLO), de todos os gerentes. A coluna GERENTE indica de quem é cada linha.
A4: GERENTE | B4: CLIENTE | C4: OPERAÇÃO | D4: VALOR | E4: FEE | F4: RECEITA | G4: MANDATO | H4: QTD | I4: INSTITUIÇÃO | J4: PARCEIRO INDICADOR | K4: ATUALIZAÇÃO | L4: FLUXO | M4: STATUS | N4: DATA FECHAMENTO | O4: MOTIVO DE RECUSA | P4: OBSERVAÇÃO | Q4: ORIGEM
A5: Kaio Dias | B5: N DIDINI ENGENHARIA E CONSTRUCAO LTDA | C5: Capital de Giro | D5: 800000 | E5: 0.03 | F5: =E5*D5 -> 24000 | G5: Assinado | H5: 1 | I5: SAPIENS CAPITAL | J5: PJC Consultoria | K5: 46224 | L5: Enviado | M5: Reprovado | N5: 46224 | O5: Outro (detalhar na observação) | P5: Score baixo | Q5: Reprovado
A6: Kaio Dias | B6: MMA BRAZIL COMERCIO DE ALIMENTOS LTDA | C6: ⁠Antecipação de Recebíveis | D6: 300000 | E6: 0.03 | F6: =E6*D6 -> 9000 | G6: Não assinado | H6: 1 | I6: AFFIX FIDC | J6: PJC Consultoria | K6: 46224 | L6: Enviado | M6: Reprovado | N6: 46224 | O6: Restrição cadastral (Serasa / protesto) | Q6: Reprovado
A7: Kaio Dias | B7: MMA BRAZIL COMERCIO DE ALIMENTOS LTDA | C7: Capital de Giro | D7: 300000 | E7: 0.03 | F7: =E7*D7 -> 9000 | G7: Não assinado | H7: 1 | I7: SAPIENS CAPITAL | J7: PJC Consultoria | K7: 46223 | L7: Enviado | M7: Reprovado | N7: 46223 | O7: Restrição cadastral (Serasa / protesto) | Q7: Reprovado
A8: Kaio Dias | B8: MMA BRAZIL COMERCIO DE ALIMENTOS LTDA | C8: ⁠Antecipação de Recebíveis | D8: 300000 | E8: 0.03 | F8: =E8*D8 -> 9000 | G8: Não assinado | H8: 1 | I8: ACREDITAR FIDC | J8: PJC Consultoria | K8: 46223 | L8: Enviado | M8: Reprovado | N8: 46223 | O8: Restrição cadastral (Serasa / protesto) | Q8: Reprovado
A9: Kaio Dias | B9: TECOL-TECNOLOGIA, ENGENHARIA E CONSTRUCAO LTDA | C9: ⁠Pro-Soluto | D9: 11000000 | E9: 0.015 | F9: =E9*D9 -> 165000 | G9: Assinado | H9: 1 | I9: SAPIENS CAPITAL | J9: PJC Consultoria | K9: 46231 | L9: Enviado | M9: Reprovado | N9: 46231 | O9: Restrição cadastral (Serasa / protesto) | Q9: Reprovado
A10: Kaio Dias | B10: TECOL-TECNOLOGIA, ENGENHARIA E CONSTRUCAO LTDA | C10: ⁠Antecipação de Recebíveis | D10: 11000000 | E10: 0.015 | F10: =E10*D10 -> 165000 | G10: Assinado | H10: 1 | I10: SAPIENS CAPITAL | J10: PJC Consultoria | K10: 46231 | L10: Enviado | M10: Reprovado | N10: 46231 | O10: Restrição cadastral (Serasa / protesto) | Q10: Reprovado
A11: Kaio Dias | B11: SIMEMP SERVICOS TECNICOS E OBRAS LTDA | C11: ⁠Antecipação de Recebíveis | D11: 5000000 | E11: 0.015 | F11: =E11*D11 -> 75000 | G11: Não assinado | H11: 1 | I11: ACREDITAR FIDC | J11: PJC Consultoria | K11: 46227 | L11: Enviado | M11: Reprovado | N11: 46227 | O11: Fora do perfil da instituição | P11: Contratos publicos | Q11: Reprovado
A12: Kaio Dias | B12: SIMEMP SERVICOS TECNICOS E OBRAS LTDA | C12: ⁠Antecipação de Recebíveis | D12: 5000000 | E12: 0.015 | F12: =E12*D12 -> 75000 | G12: Não assinado | H12: 1 | I12: SOMA ASSET | J12: PJC Consultoria | K12: 46224 | L12: Enviado | M12: Reprovado | N12: 46224 | O12: Fora do perfil da instituição | P12: Contratos publicos | Q12: Reprovado
A13: Kaio Dias | B13: SIMEMP SERVICOS TECNICOS E OBRAS LTDA | C13: ⁠Antecipação de Recebíveis | D13: 5000000 | E13: 0.015 | F13: =E13*D13 -> 75000 | G13: Não assinado | H13: 1 | I13: AFFIX FIDC | J13: PJC Consultoria | K13: 46231 | L13: Enviado | M13: Reprovado | N13: 46231 | O13: Fora do perfil da instituição | P13: Contratos publicos | Q13: Reprovado
A14: Kaio Dias | B14: SIMEMP SERVICOS TECNICOS E OBRAS LTDA | C14: ⁠Antecipação de Recebíveis | D14: 5000000 | E14: 0.015 | F14: =E14*D14 -> 75000 | G14: Não assinado | H14: 1 | I14: RNX FIDIC | J14: PJC Consultoria | K14: 46231 | L14: Enviado | M14: Reprovado | N14: 46231 | O14: Fora do perfil da instituição | P14: Contratos publicos | Q14: Reprovado
A15: João Pullig | B15: CGPM CONSTRUTORA GOIANIA | C15: ⁠Antecipação de Recebíveis | D15: 500000 | E15: 0.02 | F15: =E15*D15 -> 10000 | G15: Assinado | H15: 1 | I15: TRUST CAPITAL | J15: PJC Consultoria | K15: 46204 | L15: Enviado | M15: Finalizado | N15: 46219 | Q15: Finalizado
A16: João Pullig | B16: CGPM CONSTRUTORA GOIANIA | C16: ⁠Antecipação de Recebíveis | D16: 500000 | E16: 0.02 | F16: =E16*D16 -> 10000 | G16: Assinado | H16: 1 | I16: SALVADOR SECURITIZADORA | J16: PJC Consultoria | K16: 46204 | L16: Enviado | M16: Finalizado | N16: 46219 | Q16: Finalizado
A17: João Pullig | B17: CGPM CONSTRUTORA GOIANIA | C17: ⁠Antecipação de Recebíveis | D17: 500000 | E17: 0.02 | F17: =E17*D17 -> 10000 | G17: Assinado | H17: 1 | I17: PRIX EMPRESARIAL | J17: PJC Consultoria | K17: 46238 | L17: Enviado | M17: Finalizado | N17: 46239 | Q17: Finalizado
A18: Kaio Dias | B18: FILLIPE DANESI DE CARVALHO SILVA | C18: ⁠Consórcio | D18: 76712 | E18: 0.0075 | F18: =E18*D18 -> 575.34 | G18: Não enviado | H18: 1 | I18: COSTA AZUL INVESTIMENTOS | J18: ⁠PS Finance | K18: 46231 | L18: Enviado | M18: Finalizado | N18: 46231 | O18: Outro (detalhar na observação) | P18: Desistencia por parte do cliente | Q18: Finalizado
A19: André Pullig | B19: AJF - 05.460.040/0001-90 | C19: ⁠Antecipação de Recebíveis | D19: 500000 | E19: 0.03 | F19: =E19*D19 -> 15000 | G19: Assinado | H19: 1 | I19: TRUST CAPITAL | J19: Astrum Finance | K19: 46239 | L19: Enviado | M19: Reprovado | O19: Outro (detalhar na observação) | P19: Parceiro Aleixo já atendeu a empresa e ñ é boa | Q19: Reprovado
A20: Pablo Ruan | B20: TRIMETAL | C20: ⁠Antecipação de Recebíveis | D20: 300000 | E20: 0 | F20: =E20*D20 -> 0 | G20: Não enviado | H20: 1 | I20: RNX FIDIC | J20: PJC Consultoria | K20: 46238 | L20: Enviado | M20: Reprovado | N20: 46244 | O20: Restrição cadastral (Serasa / protesto) | P20: REUNIAO FEITA | Q20: Reprovado
A21: Kaio Dias | B21: FOX PARTICIPACOES E INVESTIMENTOS S.A. | C21: Capital de Giro | D21: 3000000 | E21: 0.01 | F21: =E21*D21 -> 30000 | G21: Enviado | H21: 1 | I21: 7 ALDABRAN | J21: PJC Consultoria | K21: 46228 | L21: Enviado | M21: Finalizado | N21: 46246 | O21: Outro (detalhar na observação) | P21: Desistencia por parte do cliente | Q21: Finalizado
A22: Kaio Dias | B22: INTEGRAL ALIMENTOS LTDA | C22: ⁠Antecipação de Recebíveis | D22: 1000000 | E22: 0.015 | F22: =E22*D22 -> 15000 | G22: Não enviado | H22: 1 | I22: PRIX EMPRESARIAL | J22: ⁠PS Finance | K22: 46231 | L22: Enviado | M22: Reprovado | N22: 46239 | O22: Restrição cadastral (Serasa / protesto) | P22: Restrições com fundo | Q22: Reprovado
A23: Kaio Dias | B23: INTEGRAL ALIMENTOS LTDA | C23: ⁠Antecipação de Recebíveis | D23: 1000000 | E23: 0.015 | F23: =E23*D23 -> 15000 | G23: Não enviado | H23: 1 | I23: SOMA ASSET | J23: ⁠PS Finance | K23: 46231 | L23: Enviado | M23: Reprovado | N23: 46239 | O23: Restrição cadastral (Serasa / protesto) | P23: Restrições com fundo | Q23: Reprovado
A24: Kaio Dias | B24: TECOL-TECNOLOGIA, ENGENHARIA E CONSTRUCAO LTDA | C24: ⁠Pro-Soluto | D24: 11000000 | E24: 0.015 | F24: =E24*D24 -> 165000 | G24: Assinado | H24: 1 | I24: Oscar | J24: PJC Consultoria | K24: 46230 | L24: Enviado | M24: Reprovado | N24: 46246 | O24: Outro (detalhar na observação) | P24: Sem rotorno do parceiro | Q24: Reprovado
A25: João Pullig | B25: RODOJUNIOR TRANSPORTES | C25: Capital de Giro | D25: 50000000 | E25: 0.006666666 | F25: =E25*D25 -> 333333.3 | G25: Assinado | H25: 1 | I25: 7 ALDABRAN | J25: ⁠VM Consultoria | K25: 46239 | L25: Enviado | M25: Finalizado | N25: 46253 | P25: Operação paga | Q25: Finalizado
A26: Kaio Dias | B26: TALENTUS ESQUADRIAS LTDA | C26: ⁠Consultoria | D26: 10000 | E26: 1 | F26: =E26*D26 -> 10000 | G26: Não enviado | H26: 1 | I26: PJC | J26: PJC Consultoria | K26: 46251 | L26: Enviado | M26: Reprovado | N26: 46253 | O26: Outro (detalhar na observação) | P26: Desistencia por parte do cliente | Q26: Reprovado
A27: Kaio Dias | B27: TALENTUS ESQUADRIAS LTDA | C27: Capital de Giro | D27: 500000 | E27: 0.02 | F27: =E27*D27 -> 10000 | G27: Não enviado | H27: 1 | I27: 7 ALDABRAN | J27: PJC Consultoria | K27: 46251 | L27: Enviado | M27: Reprovado | N27: 46253 | O27: Outro (detalhar na observação) | P27: Desistencia por parte do cliente | Q27: Reprovado
A28: Kaio Dias | B28: INOVA TRADING COMERCIO DE GRAOS LTDA | C28: ⁠Antecipação de Recebíveis | D28: 500000 | E28: 0.02 | F28: =E28*D28 -> 10000 | G28: Não assinado | H28: 1 | I28: ALX NEGOCIOS | J28: PJC Consultoria | K28: 46231 | L28: Enviado | M28: Reprovado | N28: 46237 | O28: Outro (detalhar na observação) | P28: Ja são clientes | Q28: Reprovado
A29: Kaio Dias | B29: TECOL-TECNOLOGIA, ENGENHARIA E CONSTRUCAO LTDA | C29: ⁠Consórcio | D29: 10000000 | E29: 0.015 | F29: =E29*D29 -> 150000 | G29: Assinado | H29: 1 | I29: COSTA AZUL INVESTIMENTOS | J29: PJC Consultoria | K29: 46227 | L29: Enviado | M29: Reprovado | N29: 46247 | O29: Restrição cadastral (Serasa / protesto) | P29: Inicio de RJ | Q29: Reprovado
A30: Kaio Dias | B30: TECOL-TECNOLOGIA, ENGENHARIA E CONSTRUCAO LTDA | C30: ⁠Pro-Soluto | D30: 11000000 | E30: 0.015 | F30: =E30*D30 -> 165000 | G30: Assinado | H30: 1 | I30: COSTA AZUL INVESTIMENTOS | J30: PJC Consultoria | K30: 46237 | L30: Enviado | M30: Reprovado | N30: 46247 | O30: Restrição cadastral (Serasa / protesto) | P30: Inicio de RJ | Q30: Reprovado
A31: Pablo Ruan | B31: TRIMETAL | C31: ⁠Antecipação de Recebíveis | D31: 300000 | E31: 0 | F31: =E31*D31 -> 0 | G31: Não enviado | H31: 1 | I31: AFFIX FIDC | J31: PJC Consultoria | K31: 46247 | L31: Enviado | M31: Reprovado | N31: 46246 | O31: Restrição cadastral (Serasa / protesto) | Q31: Reprovado
A32: Pablo Ruan | B32: THP INDUSTRIA | C32: ⁠Antecipação de Recebíveis | D32: 1000000 | E32: 0.025 | F32: =E32*D32 -> 25000 | G32: Enviado | H32: 1 | I32: SAPIENS CAPITAL | J32: PJC Consultoria | K32: 46247 | L32: Enviado | M32: Reprovado | N32: 46253 | O32: Restrição cadastral (Serasa / protesto) | Q32: Reprovado
A33: André Pullig | B33: LOFT CONSTRUTORA | C33: Capital de Giro | D33: 500000 | E33: 0.03 | F33: =E33*D33 -> 15000 | G33: Assinado | H33: 1 | I33: GOIAS BANK | J33: PJC Consultoria | K33: 46254 | L33: Finalizado | M33: Finalizado | N33: 46241 | P33: PAGAMENTO ESTÁ SENDO FEITO DIA 15/08 | Q33: Finalizado
A34: André Pullig | B34: ULTRAMAX - 51.651.478/0001-12 | C34: ⁠Antecipação de Recebíveis | D34: 200000 | E34: 0.03 | F34: =E34*D34 -> 6000 | G34: Assinado | H34: 1 | I34: NÃO ATRIBUÍDO | J34: Astrum Finance | K34: 46254 | L34: Em andamento | M34: Reprovado | N34: 46254 | O34: OPEROU COM PROMOTOR | P34: DECLINADO | Q34: Reprovado
A35: André Pullig | B35: ULTRAMAX - 51.651.478/0001-12 | C35: ⁠Antecipação de Recebíveis | D35: 200000 | E35: 0.03 | F35: =E35*D35 -> 6000 | G35: Assinado | H35: 1 | I35: NÃO ATRIBUÍDO | J35: Astrum Finance | K35: 46254 | L35: Em andamento | M35: Reprovado | N35: 46254 | O35: OPEROU COM PROMOTOR | P35: DECLINADO | Q35: Reprovado
A36: André Pullig | B36: RIBEIRO - 24.467.220/0001-98 | C36: ⁠Antecipação de Recebíveis | D36: 300000 | E36: 0.03 | F36: =E36*D36 -> 9000 | G36: Assinado | H36: 1 | I36: RNX FIDIC | J36: ⁠Blue Score | K36: 46254 | L36: Em andamento | M36: Reprovado | N36: 46254 | O36: SÓ OPERA PESSOA FISICA | Q36: Reprovado
A37: André Pullig | B37: BARRIERE - 51.544.166/0001-00 | C37: ⁠Antecipação de Recebíveis | D37: 300000 | E37: 0.03 | F37: =E37*D37 -> 9000 | G37: Assinado | H37: 1 | I37: AFFIX FIDC | J37: ⁠Blue Score | K37: 46254 | L37: Enviado | M37: Reprovado | N37: 46254 | O37: SÓ OPERA PESSOA FISICA | Q37: Reprovado
A38: André Pullig | B38: BARRIERE - 51.544.166/0001-00 | C38: ⁠Antecipação de Recebíveis | D38: 300000 | E38: 0.03 | F38: =E38*D38 -> 9000 | G38: Assinado | H38: 1 | I38: RNX FIDIC | J38: ⁠Blue Score | K38: 46254 | L38: Enviado | M38: Reprovado | N38: 46254 | O38: SÓ OPERA PESSOA FISICA | Q38: Reprovado
A39: André Pullig | B39: A.WAI - 05.946.250/0001-32 | C39: Capital de Giro | D39: 500000 | E39: 0.03 | F39: =E39*D39 -> 15000 | G39: Enviado | H39: 1 | I39: RNX FIDIC | J39: ⁠Blue Score | K39: 46254 | L39: Enviado | M39: Reprovado | N39: 46254 | O39: CLIENTE DECLINOU | P39: NÃO QUIS COMPLETAR A DOCUMENTAÇÃO | Q39: Reprovado
A40: Kaio Dias | B40: AGENCIA FUEGO | C40: ⁠Antecipação de Recebíveis | D40: 5000000 | E40: 0.03 | F40: =E40*D40 -> 150000 | G40: Não enviado | H40: 1 | I40: RNX FIDIC | J40: PJC Consultoria | K40: 46258 | L40: Não enviado | M40: Reprovado | N40: 46258 | O40: Outro (detalhar na observação) | P40: Parceiro não atua com modelo de operação | Q40: Reprovado
A41: Kaio Dias | B41: INTEGRAL ALIMENTOS LTDA | C41: ⁠Antecipação de Recebíveis | D41: 1000000 | E41: 0.015 | F41: =E41*D41 -> 15000 | G41: Não enviado | H41: 1 | I41: RNX FIDIC | J41: ⁠PS Finance | K41: 46258 | L41: Enviado | M41: Reprovado | N41: 46258 | O41: Outro (detalhar na observação) | P41: Não tivemos detalhamento | Q41: Reprovado
A42: Kaio Dias | B42: SIMEMP SERVICOS TECNICOS E OBRAS LTDA | C42: Capital de Giro | D42: 5000000 | E42: 0.015 | F42: =E42*D42 -> 75000 | G42: Não assinado | H42: 1 | I42: PS FINANCE | J42: PJC Consultoria | K42: 46227 | L42: Enviado | M42: Reprovado | N42: 46258 | O42: Outro (detalhar na observação) | P42: Solicitado FGI na CEF, Paula recusou por não conhecer empresa | Q42: Reprovado
A43: Pablo Ruan | B43: PHOSBOI | C43: ⁠Antecipação de Recebíveis | D43: 500000 | E43: 0.015 | F43: =E43*D43 -> 7500 | G43: Enviado | H43: 1 | I43: JPI FIDC | J43: PJC Consultoria | K43: 46258 | L43: Enviado | M43: Reprovado | N43: 46258 | O43: Restrição cadastral (Serasa / protesto) | Q43: Reprovado
A44: Kaio Dias | B44: N DIDINI ENGENHARIA E CONSTRUCAO LTDA | C44: Capital de Giro | D44: 150000 | E44: 0.03 | F44: =E44*D44 -> 4500 | G44: Assinado | H44: 1 | I44: BLUE SCORE | J44: PJC Consultoria | K44: 46258 | L44: Enviado | M44: Reprovado | N44: 46258 | O44: Outro (detalhar na observação) | P44: Reprovado pelo parceiro Daycoval | Q44: Reprovado
A45: Kaio Dias | B45: N DIDINI ENGENHARIA E CONSTRUCAO LTDA | C45: Capital de Giro | D45: 480300 | E45: 0.015 | F45: =E45*D45 -> 7204.5 | G45: Assinado | H45: 1 | I45: 7 ALDABRAN | J45: PJC Consultoria | K45: 46258 | L45: Enviado | M45: Finalizado | N45: 46259 | P45: Op 1 - R$ 12159,00 / Op 2 - R$ 2250,00 | Q45: Finalizado
A46: Pablo Ruan | B46: INNOVA BRAZIL | C46: ⁠Antecipação de Recebíveis | D46: 1000000 | E46: 0.02 | F46: =E46*D46 -> 20000 | G46: Não enviado | H46: 1 | I46: PRIX EMPRESARIAL | J46: PJC Consultoria | K46: 46258 | L46: Enviado | M46: Reprovado | N46: 46259 | O46: Restrição cadastral (Serasa / protesto) | Q46: Reprovado
A47: Pablo Ruan | B47: RENOVAR | C47: Pronampe | D47: 200000 | E47: 0.05 | F47: =E47*D47 -> 10000 | G47: Enviado | H47: 1 | I47: 7 ALDABRAN | J47: PJC Consultoria | K47: 46254 | L47: Enviado | M47: Reprovado | O47: Garantia insuficiente | Q47: Reprovado
A48: Pablo Ruan | B48: COTRITECH | C48: ⁠Antecipação de Recebíveis | D48: 300000 | E48: 0.02 | F48: =E48*D48 -> 6000 | G48: Enviado | H48: 1 | I48: RNX FIDIC | J48: PJC Consultoria | K48: 46251 | L48: Enviado | M48: Reprovado | O48: Fora do perfil da instituição | Q48: Reprovado
A49: Pablo Ruan | B49: THP INDUSTRIA | C49: ⁠Antecipação de Recebíveis | D49: 1000000 | E49: 0.025 | F49: =E49*D49 -> 25000 | G49: Enviado | H49: 1 | I49: JPI FIDC | J49: PJC Consultoria | K49: 46257 | L49: Enviado | M49: Reprovado | O49: Restrição cadastral (Serasa / protesto) | Q49: Reprovado
A50: André Pullig | B50: JULIO CESAR - 14.768.649/0001-61 | C50: FGI | D50: 1500000 | E50: 0.05 | F50: =E50*D50 -> 75000 | G50: Não enviado | H50: 1 | I50: 7 ALDABRAN | J50: Astrum Finance | K50: 46254 | L50: Em andamento | M50: Reprovado | P50: AGUARDANDO DOCUMENTOS | Q50: Reprovado
A51: André Pullig | B51: LEOMAM - 51.223.372/0001-18 | C51: ⁠FGI | D51: 1000000 | E51: 0.03 | F51: =E51*D51 -> 30000 | G51: Não enviado | H51: 1 | I51: SAPIENS CAPITAL | J51: Astrum Finance | K51: 46254 | L51: Em andamento | M51: Reprovado | P51: AGUARDANDO DOCUMENTOS | Q51: Reprovado
A52: André Pullig | B52: LEOMAM - 51.223.372/0001-18 | C52: ⁠FGI | D52: 1000000 | E52: 0.03 | F52: =E52*D52 -> 30000 | G52: Não enviado | H52: 1 | I52: 7 ALDABRAN | J52: Astrum Finance | K52: 46254 | L52: Em andamento | M52: Reprovado | Q52: Reprovado
A53: João Pullig | B53: RODOJUNIOR TRANSPORTES | C53: Capital de Giro | D53: 7000000 | E53: 0.006666666 | F53: =E53*D53 -> 46666.662 | G53: Assinado | H53: 1 | I53: SOMA ASSET | J53: ⁠ VM Consultoria | K53: 46258 | L53: Enviado | M53: Finalizado | N53: 46262 | P53: Aguardando registro no cartório | Q53: Finalizado
A54: Pablo Ruan | B54: COTRITECH | C54: ⁠Antecipação de Recebíveis | D54: 500000 | E54: 0.02 | F54: =E54*D54 -> 10000 | G54: Enviado | H54: 1 | I54: JPI FIDC | J54: PJC Consultoria | K54: 46259 | L54: Pré-análise | M54: Reprovado | O54: Outro (detalhar na observação) | P54: Troca de segmento e baixa movimentaçao financeira | Q54: Reprovado
A55: João Pullig | B55: RENOVADORA ALVORADA COMERCIO | C55: ⁠Antecipação de Recebíveis | D55: 200000 | E55: 0.03 | F55: =E55*D55 -> 6000 | G55: Não enviado | H55: 1 | I55: RNX FIDIC | J55: PJC Consultoria | K55: 46258 | L55: Enviado | M55: Finalizado | N55: 46267 | Q55: Finalizado
A56: Pablo Ruan | B56: LIPON QUIMICA | C56: ⁠Antecipação de Recebíveis | D56: 1000000 | F56: =E56*D56 -> 0 | G56: Enviado | H56: 1 | I56: AFFIX FIDC | J56: PJC Consultoria | K56: 46266 | L56: Enviado | M56: Reprovado | Q56: Reprovado
A57: Pablo Ruan | B57: LIPON QUIMICA | C57: ⁠Antecipação de Recebíveis | D57: 1000000 | F57: =E57*D57 -> 0 | G57: Enviado | H57: 1 | I57: RNX FIDIC | J57: PJC Consultoria | K57: 46266 | L57: Não enviado | M57: Reprovado | Q57: Reprovado
A58: Kaio Dias | B58: RURAL CRIA INDUSTRIA E COMERCIO DE RACAO LTDA | C58: Capital de Giro | D58: 210000 | E58: 0.025 | F58: =E58*D58 -> 5250 | G58: Enviado | H58: 1 | I58: FRANK NEGOCIOS | J58: PJC Consultoria | K58: 46266 | L58: Enviado | M58: Reprovado | N58: 46266 | O58: Outro (detalhar na observação) | P58: Sem interesse comercial da PJC | Q58: Reprovado
A59: Kaio Dias | B59: RURAL CRIA INDUSTRIA E COMERCIO DE RACAO LTDA | C59: Capital de Giro | D59: 300000 | E59: 0.025 | F59: =E59*D59 -> 7500 | G59: Enviado | H59: 1 | I59: SAPIENS CAPITAL | J59: PJC Consultoria | K59: 46258 | L59: Enviado | M59: Reprovado | N59: 46266 | O59: Outro (detalhar na observação) | P59: Sem interesse comercial da PJC | Q59: Reprovado
A60: Kaio Dias | B60: INOVA TRADING COMERCIO DE GRAOS LTDA | C60: ⁠Antecipação de Recebíveis | D60: 500000 | E60: 0.02 | F60: =E60*D60 -> 10000 | G60: Não assinado | H60: 1 | I60: RNX FIDIC | J60: PJC Consultoria | K60: 46274 | L60: Enviado | M60: Reprovado | N60: 46274 | O60: Outro (detalhar na observação) | P60: Reprovado na analise, fundo não passou o motivo | Q60: Reprovado
A61: Kaio Dias | B61: DAM ESTETICA AVANCADA LTDA | C61: Capital de Giro | D61: 300000 | E61: 0.04 | F61: =E61*D61 -> 12000 | G61: Não enviado | H61: 1 | I61: SAPIENS CAPITAL | J61: PJC Consultoria | K61: 46279 | L61: Enviado | M61: Reprovado | N61: 46279 | O61: Outro (detalhar na observação) | P61: Cliente não nos da retorno | Q61: Reprovado
A62: Kaio Dias | B62: DAM ESTETICA AVANCADA LTDA | C62: Capital de Giro | D62: 300000 | E62: 0.04 | F62: =E62*D62 -> 12000 | G62: Não enviado | H62: 1 | I62: BLUE SCORE | J62: PJC Consultoria | K62: 46279 | L62: Enviado | M62: Reprovado | N62: 46279 | O62: Outro (detalhar na observação) | P62: Cliente não nos da retorno | Q62: Reprovado
A63: Kaio Dias | B63: DAM ESTETICA AVANCADA LTDA | C63: Capital de Giro | D63: 300000 | E63: 0.04 | F63: =E63*D63 -> 12000 | G63: Não enviado | H63: 1 | I63: 7 ALDABRAN | J63: PJC Consultoria | K63: 46279 | L63: Enviado | M63: Reprovado | N63: 46279 | O63: Outro (detalhar na observação) | P63: Cliente não nos da retorno | Q63: Reprovado
A64: Kaio Dias | B64: PEDRO BRIDI | C64: ⁠Consórcio | D64: 4500000 | E64: 0.015 | F64: =E64*D64 -> 67500 | G64: Enviado | H64: 1 | I64: COSTA AZUL INVESTIMENTOS | J64: ⁠VM Consultoria | K64: 46279 | L64: Enviado | M64: Reprovado | N64: 46279 | O64: Outro (detalhar na observação) | P64: Desistencia do cooperado referente ao valor aprovado | Q64: Reprovado
A65: João Pullig | B65: TECOL ENGENHARIA E TECNOLOGIA | C65: ⁠Pro-Soluto | D65: 30000000 | E65: 0.015 | F65: =E65*D65 -> 450000 | G65: Assinado | H65: 1 | I65: CERES FIDC | J65: PJC Consultoria | K65: 46258 | L65: Enviado | M65: Reprovado | Q65: Reprovado
A66: Kaio Dias | B66: MMA BRAZIL COMERCIO DE ALIMENTOS LTDA | C66: ⁠Antecipação de Recebíveis | D66: 300000 | E66: 0.03 | F66: =E66*D66 -> 9000 | G66: Não assinado | H66: 1 | I66: ACREDITAR FIDC | J66: PJC Consultoria | K66: 46234 | L66: Enviado | M66: Reprovado | P66: Aguardando documentação | Q66: Reprovado
A67: Pablo Ruan | B67: LIPON QUIMICA | C67: ⁠Antecipação de Recebíveis | D67: 1000000 | F67: =E67*D67 -> 0 | G67: Não enviado | H67: 1 | I67: AFFIX FIDC | J67: PJC Consultoria | K67: 46266 | L67: Não enviado | M67: Finalizado | N67: 46267 | O67: Fora do perfil da instituição | Q67: Finalizado
A68: Pablo Ruan | B68: LIPON QUIMICA | C68: ⁠Antecipação de Recebíveis | D68: 1000000 | F68: =E68*D68 -> 0 | G68: Não enviado | H68: 1 | I68: SP CAPITAL | J68: PJC Consultoria | K68: 46279 | L68: Não enviado | M68: Finalizado | N68: 46281 | O68: Fora do perfil da instituição | Q68: Finalizado
A69: Pablo Ruan | B69: PHOSBOI | C69: ⁠Consultoria | D69: 8000 | F69: =E69*D69 -> 0 | G69: Enviado | H69: 1 | I69: NÃO ATRIBUÍDO | J69: PJC Consultoria | K69: 46251 | L69: Enviado | M69: Reprovado | P69: REUNIAO PRESENCIAL 13/08 | Q69: Reprovado
A70: João Pullig | B70: MEDFARMA COMERCIO DE MEDICAMENTOS | C70: ⁠Antecipação de Recebíveis | D70: 8000000 | E70: 0.015 | F70: =E70*D70 -> 120000 | G70: Assinado | H70: 1 | I70: 7 ALDABRAN | J70: ⁠Sapiens Capital | K70: 46258 | L70: Enviado | M70: Reprovado | P70: Aguardando validação da Cintia | Q70: Reprovado
A71: André Pullig | B71: AM TRANSP - 45.838.247/0001-10 | C71: Pronampe | D71: 500000 | E71: 0.15 | F71: =E71*D71 -> 75000 | G71: Assinado | H71: 1 | I71: 7 ALDABRAN | J71: Sandro | K71: 46274 | L71: Em andamento | M71: Reprovado | P71: AGUARDANDO DOCUMENTOS | Q71: Reprovado
A72: André Pullig | B72: ABSOLUTA - 34.773.909/0001-02 | C72: Pronampe | D72: 500000 | E72: 0.15 | F72: =E72*D72 -> 75000 | G72: Assinado | H72: 1 | I72: 7 ALDABRAN | J72: Sandro | K72: 46274 | L72: Em andamento | M72: Reprovado | P72: AGUARDANDO DOCUMENTOS | Q72: Reprovado
A73: Betania Ribeiro | B73: A E B INDÚSTRIA DE ALIMENTOS LTDA | C73: Capital de Giro | D73: 1000000 | E73: 0.02 | F73: =E73*D73 -> 20000 | G73: Não assinado | H73: 1 | I73: RNX FIDIC | K73: 46238 | L73: Aguardando retorno | M73: Reprovado | Q73: Reprovado
A74: Betania Ribeiro | B74: A E B INDÚSTRIA DE ALIMENTOS LTDA | C74: ⁠Antecipação de Recebíveis | D74: 800000 | E74: 0.02 | F74: =E74*D74 -> 16000 | G74: Não assinado | H74: 1 | I74: RNX FIDIC | K74: 46238 | L74: Aguardando retorno | M74: Reprovado | O74: Outro (detalhar na observação) | P74: Cliente achou Fee caro baixamos para 2% e sem retorno | Q74: Reprovado
A75: Kaio Dias | B75: AGENCIA FUEGO | C75: ⁠Antecipação de Recebíveis | D75: 5000000 | E75: 0.03 | F75: =E75*D75 -> 150000 | G75: Não enviado | H75: 1 | I75: BLUE SCORE | J75: PJC Consultoria | K75: 46287 | L75: Não enviado | M75: Reprovado | N75: 46287 | O75: Outro (detalhar na observação) | P75: Sem possibilidades | Q75: Reprovado
A76: Kaio Dias | B76: AGENCIA FUEGO | C76: ⁠Antecipação de Recebíveis | D76: 5000000 | E76: 0.03 | F76: =E76*D76 -> 150000 | G76: Não enviado | H76: 1 | I76: PS FINANCE | J76: PJC Consultoria | K76: 46287 | L76: Enviado | M76: Reprovado | N76: 46258 | O76: Outro (detalhar na observação) | P76: Havia encaminhado para tentativa de FGI na CEF, Paula não demonstrou interesse | Q76: Reprovado
A77: Kaio Dias | B77: RURAL CRIA INDUSTRIA E COMERCIO DE RACAO LTDA | C77: Capital de Giro | D77: 300000 | E77: 0.025 | F77: =E77*D77 -> 7500 | G77: Assinado | H77: 1 | I77: 7 ALDABRAN | J77: PJC Consultoria | K77: 46287 | L77: Enviado | M77: Reprovado | P77: Declinado devido falta de pagamento de outras operações | Q77: Reprovado
A78: Kaio Dias | B78: JARDEL | C78: ⁠Consórcio | D78: 9000000 | E78: 0.01 | F78: =E78*D78 -> 90000 | G78: Enviado | H78: 1 | I78: COSTA AZUL INVESTIMENTOS | J78: ⁠VM Consultoria | K78: 46287 | L78: Enviado | M78: Reprovado | N78: 46287 | O78: Outro (detalhar na observação) | P78: Reprovado devido a penhor de grãos na matricula, não aceito pelo fundo | Q78: Reprovado
A79: Pablo Ruan | B79: COTRITECH | C79: ⁠Antecipação de Recebíveis | D79: 1000000 | E79: 0.02 | F79: =E79*D79 -> 20000 | G79: Enviado | H79: 1 | I79: SP CAPITAL | J79: PJC Consultoria | K79: 46286 | L79: Enviado | M79: Reprovado | N79: 46286 | O79: Outro (detalhar na observação) | P79: TAXA ALTA NAO OPERA | Q79: Reprovado
A80: Pablo Ruan | B80: THP INDUSTRIA | C80: ⁠Antecipação de Recebíveis | D80: 800000 | E80: 0.025 | F80: =E80*D80 -> 20000 | G80: Enviado | H80: 1 | I80: SOMA ASSET | J80: PJC Consultoria | K80: 46254 | L80: Enviado | M80: Reprovado | N80: 46283 | O80: Restrição cadastral (Serasa / protesto) | Q80: Reprovado
F209: =IF(OR(D209="",E209=""),"",D209*E209)
F210: =IF(OR(D210="",E210=""),"",D210*E210)
F211: =IF(OR(D211="",E211=""),"",D211*E211)
F212: =IF(OR(D212="",E212=""),"",D212*E212)
F213: =IF(OR(D213="",E213=""),"",D213*E213)
F214: =IF(OR(D214="",E214=""),"",D214*E214)
F215: =IF(OR(D215="",E215=""),"",D215*E215)
F216: =IF(OR(D216="",E216=""),"",D216*E216)
F217: =IF(OR(D217="",E217=""),"",D217*E217)
F218: =IF(OR(D218="",E218=""),"",D218*E218)
F219: =IF(OR(D219="",E219=""),"",D219*E219)
F220: =IF(OR(D220="",E220=""),"",D220*E220)
... F268: =IF(OR(D268="",E268=""),"",D268*E268)

Sheet COMO USAR
B2: COMO USAR ESTA PLANILHA
B4: Preenchendo uma operação
B5: Cada linha é uma operação. Os campos Operação, Mandato, Instituição, Parceiro Indicador, Fluxo, Status e Motivo de Recusa são de escolha: clique na célula e use a seta. Digitar por fora é bloqueado — é isso que mantém os nomes padronizados.
B7: Receita não se digita
B8: A coluna Receita é calculada: Valor × Fee. Preencha o Fee como porcentagem (2,5%) e a receita aparece sozinha.
B10: Mesma operação em vários bancos
B11: Lance uma linha por banco. Cada linha conta como uma operação — foi a regra que definimos para o painel.
B13: Operação reprovada
B14: Marque o Status como Reprovado e preencha o Motivo de Recusa. Na virada, essas linhas são levadas para a aba HISTÓRICO, que junta os reprovados de todos os gerentes.
B16: Incluir um parceiro ou tipo novo
B17: Vá na aba PARAMETROS e escreva na primeira linha vazia da coluna. A lista passa a oferecer o item na hora, em todas as abas.
B19: Itens marcados com *
B20: Ficam no fim das listas e estão pendentes de confirmação: FIRMA CAPITAL*, DAVOS FIDC*, RNX FIDIC* e BANCO BCG*. Confirmado o nome, é só tirar o asterisco na aba PARAMETROS.
